Workbook

Sheet PAINEL ENTRADA
A1: SÃO FRANCISCO | T1: =A1 -> SÃO FRANCISCO

Sheet SÃO FRANCISCO
A1: MOVIMENTAÇÃO FAZENDA SÃO FRANCISCO | S1: COMPRA
D2: ENTRADAS | J2: SAIDAS | O2: POSIÇÃO | S2: NASC.
S3: TRANSF. E
A4: CATEGORIAS | D4: SALDO ANTERIOR | E4: COMPRA | F4: EVOLUÇ | G4: NASC. | H4: TRANSF. E | I4: TOTAL | J4: ABATE | K4: MORTE | L4: VENDA | M4: TRANSF. S | N4: TOTAL | O4: FINAL | S4: ABATE
A5: Femeas + 36 meses | E5: =SUMIFS($E$20:$E$1048576,$D$20:$D$1048576,$E$4,$C$20:$C$1048576,A5) -> 0 | F5: =SUMIFS($E$20:$E$1048576,$D$20:$D$1048576,$F$4,$C$20:$C$1048576,B5) -> 0 | G5: =SUMIFS($E$20:$E$1048576,$D$20:$D$1048576,$G$4,$C$20:$C$1048576,A5) -> 0 | H5: =SUMIFS($E$20:$E$1048576,$D$20:$D$1048576,$H$4,$C$20:$C$1048576,A5) -> 0 | I5: =SUM(D5:H5) -> 0 | J5: =SUMIFS($E$20:$E$1048576,$D$20:$D$1048576,$J$4,$C$20:$C$1048576,A5) -> 0 | K5: =SUMIFS($E$20:$E$1048576,$D$20:$D$1048576,$K$4,$C$20:$C$1048576,A5) -> 0 | L5: =SUMIFS($E$20:$E$1048576,$D$20:$D$1048576,$L$4,$C$20:$C$1048576,A5) -> 0 | M5: =SUMIFS($E$20:$E$1048576,$D$20:$D$1048576,$M$4,$C$20:$C$1048576,A5) -> 0 | N5: =SUM(J5:M5) -> 0 | O5: =SUM(I5-N5) -> 0 | S5: MORTE
A6: Femeas 25 a 36 meses | E6: =SUMIFS($E$20:$E$1048576,$D$20:$D$1048576,$E$4,$C$20:$C$1048576,A6) -> 0 | F6: =SUMIFS($E$20:$E$1048576,$D$20:$D$1048576,$F$4,$C$20:$C$1048576,B6) -> 0 | G6: =SUMIFS($E$20:$E$1048576,$D$20:$D$1048576,$G$4,$C$20:$C$1048576,A6) -> 0 | H6: =SUMIFS($E$20:$E$1048576,$D$20:$D$1048576,$H$4,$C$20:$C$1048576,A6) -> 0 | I6: =SUM(D6:H6) -> 0 | J6: =SUMIFS($E$20:$E$1048576,$D$20:$D$1048576,$J$4,$C$20:$C$1048576,A6) -> 0 | K6: =SUMIFS($E$20:$E$1048576,$D$20:$D$1048576,$K$4,$C$20:$C$1048576,A6) -> 0 | L6: =SUMIFS($E$20:$E$1048576,$D$20:$D$1048576,$L$4,$C$20:$C$1048576,A6) -> 0 | M6: =SUMIFS($E$20:$E$1048576,$D$20:$D$1048576,$M$4,$C$20:$C$1048576,A6) -> 0 | N6: =SUM(J6:M6) -> 0 | O6: =SUM(I6-N6) -> 0 | S6: TRANSF. S
A7: Femeas 13 a 24 meses | E7: =SUMIFS($E$20:$E$1048576,$D$20:$D$1048576,$E$4,$C$20:$C$1048576,A7) -> 0 | F7: =SUMIFS($E$20:$E$1048576,$D$20:$D$1048576,$F$4,$C$20:$C$1048576,B7) -> 0 | G7: =SUMIFS($E$20:$E$1048576,$D$20:$D$1048576,$G$4,$C$20:$C$1048576,A7) -> 0 | H7: =SUMIFS($E$20:$E$1048576,$D$20:$D$1048576,$H$4,$C$20:$C$1048576,A7) -> 0 | I7: =SUM(D7:H7) -> 0 | J7: =SUMIFS($E$20:$E$1048576,$D$20:$D$1048576,$J$4,$C$20:$C$1048576,A7) -> 0 | K7: =SUMIFS($E$20:$E$1048576,$D$20:$D$1048576,$K$4,$C$20:$C$1048576,A7) -> 0 | L7: =SUMIFS($E$20:$E$1048576,$D$20:$D$1048576,$L$4,$C$20:$C$1048576,A7) -> 0 | M7: =SUMIFS($E$20:$E$1048576,$D$20:$D$1048576,$M$4,$C$20:$C$1048576,A7) -> 0 | N7: =SUM(J7:M7) -> 0 | O7: =SUM(I7-N7) -> 0 | S7: SALDO ANTERIOR
A8: Femeas Desm. até 12m | E8: =SUMIFS($E$20:$E$1048576,$D$20:$D$1048576,$E$4,$C$20:$C$1048576,A8) -> 0 | F8: =SUMIFS($E$20:$E$1048576,$D$20:$D$1048576,$F$4,$C$20:$C$1048576,B8) -> 0 | G8: =SUMIFS($E$20:$E$1048576,$D$20:$D$1048576,$G$4,$C$20:$C$1048576,A8) -> 0 | H8: =SUMIFS($E$20:$E$1048576,$D$20:$D$1048576,$H$4,$C$20:$C$1048576,A8) -> 0 | I8: =SUM(D8:H8) -> 0 | J8: =SUMIFS($E$20:$E$1048576,$D$20:$D$1048576,$J$4,$C$20:$C$1048576,A8) -> 0 | K8: =SUMIFS($E$20:$E$1048576,$D$20:$D$1048576,$K$4,$C$20:$C$1048576,A8) -> 0 | L8: =SUMIFS($E$20:$E$1048576,$D$20:$D$1048576,$L$4,$C$20:$C$1048576,A8) -> 0 | M8: =SUMIFS($E$20:$E$1048576,$D$20:$D$1048576,$M$4,$C$20:$C$1048576,A8) -> 0 | N8: =SUM(J8:M8) -> 0 | O8: =SUM(I8-N8) -> 0 | S8: EVOLUÇ
A9: Bezerras Mamando | E9: =SUMIFS($E$20:$E$1048576,$D$20:$D$1048576,$E$4,$C$20:$C$1048576,A9) -> 0 | F9: =SUMIFS($E$20:$E$1048576,$D$20:$D$1048576,$F$4,$C$20:$C$1048576,B9) -> 0 | G9: =SUMIFS($E$20:$E$1048576,$D$20:$D$1048576,$G$4,$C$20:$C$1048576,A9) -> 0 | H9: =SUMIFS($E$20:$E$1048576,$D$20:$D$1048576,$H$4,$C$20:$C$1048576,A9) -> 0 | I9: =SUM(D9:H9) -> 0 | J9: =SUMIFS($E$20:$E$1048576,$D$20:$D$1048576,$J$4,$C$20:$C$1048576,A9) -> 0 | K9: =SUMIFS($E$20:$E$1048576,$D$20:$D$1048576,$K$4,$C$20:$C$1048576,A9) -> 0 | L9: =SUMIFS($E$20:$E$1048576,$D$20:$D$1048576,$L$4,$C$20:$C$1048576,A9) -> 0 | M9: =SUMIFS($E$20:$E$1048576,$D$20:$D$1048576,$M$4,$C$20:$C$1048576,A9) -> 0 | N9: =SUM(J9:M9) -> 0 | O9: =SUM(I9-N9) -> 0 | S9: VENDA
A10: Bezerros Mamando | E10: =SUMIFS($E$20:$E$1048576,$D$20:$D$1048576,$E$4,$C$20:$C$1048576,A10) -> 0 | F10: =SUMIFS($E$20:$E$1048576,$D$20:$D$1048576,$F$4,$C$20:$C$1048576,B10) -> 0 | G10: =SUMIFS($E$20:$E$1048576,$D$20:$D$1048576,$G$4,$C$20:$C$1048576,A10) -> 0 | H10: =SUMIFS($E$20:$E$1048576,$D$20:$D$1048576,$H$4,$C$20:$C$1048576,A10) -> 0 | I10: =SUM(D10:H10) -> 0 | J10: =SUMIFS($E$20:$E$1048576,$D$20:$D$1048576,$J$4,$C$20:$C$1048576,A10) -> 0 | K10: =SUMIFS($E$20:$E$1048576,$D$20:$D$1048576,$K$4,$C$20:$C$1048576,A10) -> 0 | L10: =SUMIFS($E$20:$E$1048576,$D$20:$D$1048576,$L$4,$C$20:$C$1048576,A10) -> 0 | M10: =SUMIFS($E$20:$E$1048576,$D$20:$D$1048576,$M$4,$C$20:$C$1048576,A10) -> 0 | N10: =SUM(J10:M10) -> 0 | O10: =SUM(I10-N10) -> 0
A11: Machos Desm. até 12m | D11: 552 | E11: =SUMIFS($E$20:$E$1048576,$D$20:$D$1048576,$E$4,$C$20:$C$1048576,A11) -> 828 | F11: =SUMIFS($E$20:$E$1048576,$D$20:$D$1048576,$F$4,$C$20:$C$1048576,B11) -> 0 | G11: =SUMIFS($E$20:$E$1048576,$D$20:$D$1048576,$G$4,$C$20:$C$1048576,A11) -> 0 | H11: =SUMIFS($E$20:$E$1048576,$D$20:$D$1048576,$H$4,$C$20:$C$1048576,A11) -> 0 | I11: =SUM(D11:H11) -> 1380 | J11: =SUMIFS($E$20:$E$1048576,$D$20:$D$1048576,$J$4,$C$20:$C$1048576,A11) -> 0 | K11: =SUMIFS($E$20:$E$1048576,$D$20:$D$1048576,$K$4,$C$20:$C$1048576,A11) -> 12 | L11: =SUMIFS($E$20:$E$1048576,$D$20:$D$1048576,$L$4,$C$20:$C$1048576,A11) -> 0 | M11: =SUMIFS($E$20:$E$1048576,$D$20:$D$1048576,$M$4,$C$20:$C$1048576,A11) -> 0 | N11: =SUM(J11:M11) -> 12 | O11: =SUM(I11-N11) -> 1368 | P11: ANIMAIS ABAIXO DE 8 @
A12: Machos 13 a 24 meses | D12: 171 | E12: =SUMIFS($E$20:$E$1048576,$D$20:$D$1048576,$E$4,$C$20:$C$1048576,A12) -> 0 | F12: =SUMIFS($E$20:$E$1048576,$D$20:$D$1048576,$F$4,$C$20:$C$1048576,B12) -> 0 | G12: =SUMIFS($E$20:$E$1048576,$D$20:$D$1048576,$G$4,$C$20:$C$1048576,A12) -> 0 | H12: =SUMIFS($E$20:$E$1048576,$D$20:$D$1048576,$H$4,$C$20:$C$1048576,A12) -> 0 | I12: =SUM(D12:H12) -> 171 | J12: =SUMIFS($E$20:$E$1048576,$D$20:$D$1048576,$J$4,$C$20:$C$1048576,A12) -> 0 | K12: =SUMIFS($E$20:$E$1048576,$D$20:$D$1048576,$K$4,$C$20:$C$1048576,A12) -> 8 | L12: =SUMIFS($E$20:$E$1048576,$D$20:$D$1048576,$L$4,$C$20:$C$1048576,A12) -> 0 | M12: =SUMIFS($E$20:$E$1048576,$D$20:$D$1048576,$M$4,$C$20:$C$1048576,A12) -> 0 | N12: =SUM(J12:M12) -> 8 | O12: =SUM(I12-N12) -> 163 | P12: ANIMAIS DE 8 A 12 @
A13: Machos 25 a 36 meses | D13: 780 | E13: =SUMIFS($E$20:$E$1048576,$D$20:$D$1048576,$E$4,$C$20:$C$1048576,A13) -> 0 | F13: =SUMIFS($E$20:$E$1048576,$D$20:$D$1048576,$F$4,$C$20:$C$1048576,B13) -> 0 | G13: =SUMIFS($E$20:$E$1048576,$D$20:$D$1048576,$G$4,$C$20:$C$1048576,A13) -> 0 | H13: =SUMIFS($E$20:$E$1048576,$D$20:$D$1048576,$H$4,$C$20:$C$1048576,A13) -> 0 | I13: =SUM(D13:H13) -> 780 | J13: =SUMIFS($E$20:$E$1048576,$D$20:$D$1048576,$J$4,$C$20:$C$1048576,A13) -> 354 | K13: =SUMIFS($E$20:$E$1048576,$D$20:$D$1048576,$K$4,$C$20:$C$1048576,A13) -> 3 | L13: =SUMIFS($E$20:$E$1048576,$D$20:$D$1048576,$L$4,$C$20:$C$1048576,A13) -> 0 | M13: =SUMIFS($E$20:$E$1048576,$D$20:$D$1048576,$M$4,$C$20:$C$1048576,A13) -> 0 | N13: =SUM(J13:M13) -> 357 | O13: =SUM(I13-N13) -> 423 | P13: ANIMAIS ACIMA DE 12 @
A14: Touros | E14: =SUMIFS($E$20:$E$1048576,$D$20:$D$1048576,$E$4,$C$20:$C$1048576,A14) -> 0 | F14: =SUMIFS($E$20:$E$1048576,$D$20:$D$1048576,$F$4,$C$20:$C$1048576,B14) -> 0 | G14: =SUMIFS($E$20:$E$1048576,$D$20:$D$1048576,$G$4,$C$20:$C$1048576,A14) -> 0 | H14: =SUMIFS($E$20:$E$1048576,$D$20:$D$1048576,$H$4,$C$20:$C$1048576,A14) -> 0 | I14: =SUM(D14:H14) -> 0 | J14: =SUMIFS($E$20:$E$1048576,$D$20:$D$1048576,$J$4,$C$20:$C$1048576,A14) -> 0 | K14: =SUMIFS($E$20:$E$1048576,$D$20:$D$1048576,$K$4,$C$20:$C$1048576,A14) -> 0 | L14: =SUMIFS($E$20:$E$1048576,$D$20:$D$1048576,$L$4,$C$20:$C$1048576,A14) -> 0 | M14: =SUMIFS($E$20:$E$1048576,$D$20:$D$1048576,$M$4,$C$20:$C$1048576,A14) -> 0 | N14: =SUM(J14:M14) -> 0 | O14: =SUM(I14-N14) -> 0
A15: TROPA | E15: =SUMIFS($E$20:$E$1048576,$D$20:$D$1048576,$E$4,$C$20:$C$1048576,A15) -> 0 | F15: 0 | G15: =SUMIFS($E$20:$E$1048576,$D$20:$D$1048576,$G$4,$C$20:$C$1048576,A15) -> 0 | H15: =SUMIFS($E$20:$E$1048576,$D$20:$D$1048576,$H$4,$C$20:$C$1048576,A15) -> 0 | I15: =SUM(D15:H15) -> 0 | J15: =SUMIFS($E$20:$E$1048576,$D$20:$D$1048576,$J$4,$C$20:$C$1048576,A15) -> 0 | K15: =SUMIFS($E$20:$E$1048576,$D$20:$D$1048576,$K$4,$C$20:$C$1048576,A15) -> 0 | L15: =SUMIFS($E$20:$E$1048576,$D$20:$D$1048576,$L$4,$C$20:$C$1048576,A15) -> 0 | M15: =SUMIFS($E$20:$E$1048576,$D$20:$D$1048576,$M$4,$C$20:$C$1048576,A15) -> 0 | N15: =SUM(J15:M15) -> 0 | O15: =SUM(I15-N15) -> 0
A16: TOTAL | D16: =SUM(D5:D15) -> 1503 | E16: =SUM(E5:E15) -> 828 | F16: =SUM(F5:F15) -> 0 | G16: =SUM(G5:G15) -> 0 | H16: =SUM(H5:H15) -> 0 | I16: =SUM(I5:I15) -> 2331 | J16: =SUM(J5:J15) -> 354 | K16: =SUM(K5:K15) -> 23 | ... O16: =SUM(O5:O15) -> 1954
A18: MOVIMENTAÇÕES DE BOVINOS
A19: DATA | B19: MÊS | C19: CATEGORIA | D19: TIPO | E19: QUANTIDADE | F19: SAIDA | G19: DESTINO | H19: PESO TOTAL | I19: PESO MÉDIO
A20: 45852 | B20: =TEXT(Tabela2234[[#This Row],[DATA]],"mmm") -> jul | C20: Machos Desm. até 12m | D20: MORTE | E20: 1 | F20: MORTE | G20: MORTE | H20: 150 | I20: =Tabela2234[[#This Row],[PESO TOTAL]]/Tabela2234[[#This Row],[QUANTIDADE]] -> 150
A21: 45855 | B21: =TEXT(Tabela2234[[#This Row],[DATA]],"mmm") -> jul | C21: Machos Desm. até 12m | D21: MORTE | E21: 1 | F21: MORTE | G21: MORTE | H21: 150 | I21: =Tabela2234[[#This Row],[PESO TOTAL]]/Tabela2234[[#This Row],[QUANTIDADE]] -> 150
A22: 45872 | B22: =TEXT(Tabela2234[[#This Row],[DATA]],"mmm") -> ago | C22: Machos 25 a 36 meses | D22: ABATE | E22: 84 | F22: ABATE | G22: COPERFRIGU | H22: 47040 | I22: =Tabela2234[[#This Row],[PESO TOTAL]]/Tabela2234[[#This Row],[QUANTIDADE]] -> 560
A23: 45860 | B23: =TEXT(Tabela2234[[#This Row],[DATA]],"mmm") -> jul | C23: Machos Desm. até 12m | D23: COMPRA | E23: 1 | F23: COMPRA | G23: ENTREGA COMPRA | H23: 150 | I23: =Tabela2234[[#This Row],[PESO TOTAL]]/Tabela2234[[#This Row],[QUANTIDADE]] -> 150
A24: 45909 | B24: =TEXT(Tabela2234[[#This Row],[DATA]],"mmm") -> set | C24: Machos Desm. até 12m | D24: COMPRA | E24: 133 | F24: COMPRA | G24: COMPRA GOIANO | H24: 27668 | I24: =Tabela2234[[#This Row],[PESO TOTAL]]/Tabela2234[[#This Row],[QUANTIDADE]] -> 208.03008
A25: 45894 | B25: =TEXT(Tabela2234[[#This Row],[DATA]],"mmm") -> ago | C25: Machos Desm. até 12m | D25: MORTE | E25: 1 | F25: MORTE | I25: =Tabela2234[[#This Row],[PESO TOTAL]]/Tabela2234[[#This Row],[QUANTIDADE]] -> 0
A26: 45898 | B26: =TEXT(Tabela2234[[#This Row],[DATA]],"mmm") -> ago | C26: Machos Desm. até 12m | D26: COMPRA | E26: 2 | G26: COMPRA GOIANO | H26: 416 | I26: =Tabela2234[[#This Row],[PESO TOTAL]]/Tabela2234[[#This Row],[QUANTIDADE]] -> 208
A27: 45908 | B27: =TEXT(Tabela2234[[#This Row],[DATA]],"mmmm") -> setembro | C27: Machos Desm. até 12m | D27: MORTE | E27: 1 | I27: =Tabela2234[[#This Row],[PESO TOTAL]]/Tabela2234[[#This Row],[QUANTIDADE]] -> 0
A28: 45947 | B28: =TEXT(Tabela2234[[#This Row],[DATA]],"mmmm") -> outubro | C28: Machos 13 a 24 meses | D28: MORTE | E28: 1 | I28: =Tabela2234[[#This Row],[PESO TOTAL]]/Tabela2234[[#This Row],[QUANTIDADE]] -> 0
A29: 45947 | B29: =TEXT(Tabela2234[[#This Row],[DATA]],"mmmm") -> outubro | C29: Machos Desm. até 12m | D29: COMPRA | E29: 12 | F29: COMPRA | H29: 1775 | I29: =Tabela2234[[#This Row],[PESO TOTAL]]/Tabela2234[[#This Row],[QUANTIDADE]] -> 147.91667
A30: 45950 | B30: =TEXT(Tabela2234[[#This Row],[DATA]],"mmmm") -> outubro | C30: Machos 25 a 36 meses | D30: MORTE | E30: 1 | G30: CANTINA | I30: =Tabela2234[[#This Row],[PESO TOTAL]]/Tabela2234[[#This Row],[QUANTIDADE]] -> 0
A31: 45953 | B31: =TEXT(Tabela2234[[#This Row],[DATA]],"mmmm") -> outubro | C31: Machos Desm. até 12m | D31: COMPRA | E31: 42 | F31: COMPRA | H31: 5647 | I31: =Tabela2234[[#This Row],[PESO TOTAL]]/Tabela2234[[#This Row],[QUANTIDADE]] -> 134.45238
A32: 45959 | B32: =TEXT(Tabela2234[[#This Row],[DATA]],"mmmm") -> outubro | C32: Machos Desm. até 12m | D32: MORTE | E32: 1 | I32: =Tabela2234[[#This Row],[PESO TOTAL]]/Tabela2234[[#This Row],[QUANTIDADE]] -> 0
A33: 45974 | B33: =TEXT(Tabela2234[[#This Row],[DATA]],"mmmm") -> novembro | C33: Machos Desm. até 12m | D33: MORTE | E33: 1 | I33: =Tabela2234[[#This Row],[PESO TOTAL]]/Tabela2234[[#This Row],[QUANTIDADE]] -> 0
A34: 45982 | B34: =TEXT(Tabela2234[[#This Row],[DATA]],"mmmm") -> novembro | C34: Machos Desm. até 12m | D34: COMPRA | E34: 150 | F34: COMPRA | H34: 22279 | I34: =Tabela2234[[#This Row],[PESO TOTAL]]/Tabela2234[[#This Row],[QUANTIDADE]] -> 148.52667
A35: 45985 | B35: =TEXT(Tabela2234[[#This Row],[DATA]],"mmmm") -> novembro | C35: Machos Desm. até 12m | D35: MORTE | E35: 1 | I35: =Tabela2234[[#This Row],[PESO TOTAL]]/Tabela2234[[#This Row],[QUANTIDADE]] -> 0
A36: 45988 | B36: =TEXT(Tabela2234[[#This Row],[DATA]],"mmmm") -> novembro | C36: Machos Desm. até 12m | D36: COMPRA | E36: 40 | F36: COMPRA | H36: 5941 | I36: =Tabela2234[[#This Row],[PESO TOTAL]]/Tabela2234[[#This Row],[QUANTIDADE]] -> 148.525
A37: 45999 | B37: =TEXT(Tabela2234[[#This Row],[DATA]],"mmmm") -> dezembro | C37: Machos Desm. até 12m | D37: MORTE | E37: 1 | I37: =Tabela2234[[#This Row],[PESO TOTAL]]/Tabela2234[[#This Row],[QUANTIDADE]] -> 0
A38: 46000 | B38: =TEXT(Tabela2234[[#This Row],[DATA]],"mmmm") -> dezembro | C38: Machos Desm. até 12m | D38: MORTE | E38: 1 | I38: =Tabela2234[[#This Row],[PESO TOTAL]]/Tabela2234[[#This Row],[QUANTIDADE]] -> 0
A39: 46004 | B39: =TEXT(Tabela2234[[#This Row],[DATA]],"mmmm") -> dezembro | C39: Machos Desm. até 12m | D39: MORTE | E39: 1 | I39: =Tabela2234[[#This Row],[PESO TOTAL]]/Tabela2234[[#This Row],[QUANTIDADE]] -> 0
A40: 46006 | B40: =TEXT(Tabela2234[[#This Row],[DATA]],"mmmm") -> dezembro | C40: Machos 13 a 24 meses | D40: MORTE | E40: 1 | I40: =Tabela2234[[#This Row],[PESO TOTAL]]/Tabela2234[[#This Row],[QUANTIDADE]] -> 0
A41: 46021 | B41: =TEXT(Tabela2234[[#This Row],[DATA]],"mmmm") -> dezembro | C41: Machos Desm. até 12m | D41: COMPRA | E41: 105 | F41: COMPRA | H41: 18345 | I41: =Tabela2234[[#This Row],[PESO TOTAL]]/Tabela2234[[#This Row],[QUANTIDADE]] -> 174.71429
A42: 46027 | B42: =TEXT(Tabela2234[[#This Row],[DATA]],"mmmm") -> janeiro | C42: Machos 13 a 24 meses | D42: MORTE | E42: 1 | I42: =Tabela2234[[#This Row],[PESO TOTAL]]/Tabela2234[[#This Row],[QUANTIDADE]] -> 0
A43: 46031 | B43: =TEXT(Tabela2234[[#This Row],[DATA]],"mmmm") -> janeiro | C43: Machos 13 a 24 meses | D43: MORTE | E43: 1 | G43: CANTINA | I43: =Tabela2234[[#This Row],[PESO TOTAL]]/Tabela2234[[#This Row],[QUANTIDADE]] -> 0
A44: 46049 | B44: =TEXT(Tabela2234[[#This Row],[DATA]],"mmmm") -> janeiro | C44: Machos 13 a 24 meses | D44: MORTE | E44: 1 | I44: =Tabela2234[[#This Row],[PESO TOTAL]]/Tabela2234[[#This Row],[QUANTIDADE]] -> 0
A45: 46053 | B45: =TEXT(Tabela2234[[#This Row],[DATA]],"mmmm") -> janeiro | C45: Machos 13 a 24 meses | D45: MORTE | E45: 1 | I45: =Tabela2234[[#This Row],[PESO TOTAL]]/Tabela2234[[#This Row],[QUANTIDADE]] -> 0
A46: 46057 | B46: =TEXT(Tabela2234[[#This Row],[DATA]],"mmmm") -> fevereiro | C46: Machos 13 a 24 meses | D46: MORTE | E46: 1 | I46: =Tabela2234[[#This Row],[PESO TOTAL]]/Tabela2234[[#This Row],[QUANTIDADE]] -> 0
A47: 46062 | B47: =TEXT(Tabela2234[[#This Row],[DATA]],"mmmm") -> fevereiro | C47: Machos 13 a 24 meses | D47: MORTE | E47: 1 | I47: =Tabela2234[[#This Row],[PESO TOTAL]]/Tabela2234[[#This Row],[QUANTIDADE]] -> 0
A48: 46063 | B48: =TEXT(Tabela2234[[#This Row],[DATA]],"mmmm") -> fevereiro | C48: Machos Desm. até 12m | D48: MORTE | E48: 1 | I48: =Tabela2234[[#This Row],[PESO TOTAL]]/Tabela2234[[#This Row],[QUANTIDADE]] -> 0
A49: 46065 | B49: =TEXT(Tabela2234[[#This Row],[DATA]],"mmmm") -> fevereiro | C49: Machos Desm. até 12m | D49: MORTE | E49: 1 | I49: =Tabela2234[[#This Row],[PESO TOTAL]]/Tabela2234[[#This Row],[QUANTIDADE]] -> 0
A50: 46364 | B50: =TEXT(Tabela2234[[#This Row],[DATA]],"mmmm") -> dezembro | C50: Machos Desm. até 12m | D50: COMPRA | E50: 69 | H50: 10695 | I50: =Tabela2234[[#This Row],[PESO TOTAL]]/Tabela2234[[#This Row],[QUANTIDADE]] -> 155
A51: 46098 | B51: =TEXT(Tabela2234[[#This Row],[DATA]],"mmmm") -> março | C51: Machos Desm. até 12m | D51: COMPRA | E51: 6 | F51: COMPRA | H51: 1045 | I51: =Tabela2234[[#This Row],[PESO TOTAL]]/Tabela2234[[#This Row],[QUANTIDADE]] -> 174.16667
A52: 46107 | B52: =TEXT(Tabela2234[[#This Row],[DATA]],"mmmm") -> março | C52: Machos 25 a 36 meses | D52: ABATE | E52: 189 | F52: VENDA | H52: 115617 | I52: =Tabela2234[[#This Row],[PESO TOTAL]]/Tabela2234[[#This Row],[QUANTIDADE]] -> 611.73016
A53: 46119 | B53: =TEXT(Tabela2234[[#This Row],[DATA]],"mmmm") -> abril | C53: Machos 25 a 36 meses | D53: MORTE | E53: 1 | G53: CANTINA | I53: =Tabela2234[[#This Row],[PESO TOTAL]]/Tabela2234[[#This Row],[QUANTIDADE]] -> 0
A54: 46135 | B54: =TEXT(Tabela2234[[#This Row],[DATA]],"mmmm") -> abril | C54: Machos 25 a 36 meses | D54: ABATE | E54: 81 | H54: 47878 | I54: =Tabela2234[[#This Row],[PESO TOTAL]]/Tabela2234[[#This Row],[QUANTIDADE]] -> 591.08642
A55: 46140 | B55: =TEXT(Tabela2234[[#This Row],[DATA]],"mmmm") -> abril | C55: Machos 25 a 36 meses | D55: MORTE | E55: 1 | F55: MORTE | G55: MORTE | I55: =Tabela2234[[#This Row],[PESO TOTAL]]/Tabela2234[[#This Row],[QUANTIDADE]] -> 0
A56: 46139 | B56: =TEXT(Tabela2234[[#This Row],[DATA]],"mmmm") -> abril | C56: Machos Desm. até 12m | D56: COMPRA | E56: 268 | H56: 36116 | I56: =Tabela2234[[#This Row],[PESO TOTAL]]/Tabela2234[[#This Row],[QUANTIDADE]] -> 134.76119
B57: =TEXT(Tabela2234[[#This Row],[DATA]],"mmmm") -> janeiro | I57: =Tabela2234[[#This Row],[PESO TOTAL]]/Tabela2234[[#This Row],[QUANTIDADE]] -> #DIV/0!
B58: =TEXT(Tabela2234[[#This Row],[DATA]],"mmmm") -> janeiro | I58: =Tabela2234[[#This Row],[PESO TOTAL]]/Tabela2234[[#This Row],[QUANTIDADE]] -> #DIV/0!
B59: =TEXT(Tabela2234[[#This Row],[DATA]],"mmmm") -> janeiro | I59: =Tabela2234[[#This Row],[PESO TOTAL]]/Tabela2234[[#This Row],[QUANTIDADE]] -> #DIV/0!
B60: =TEXT(Tabela2234[[#This Row],[DATA]],"mmmm") -> janeiro | I60: =Tabela2234[[#This Row],[PESO TOTAL]]/Tabela2234[[#This Row],[QUANTIDADE]] -> #DIV/0!
B61: =TEXT(Tabela2234[[#This Row],[DATA]],"mmmm") -> janeiro | I61: =Tabela2234[[#This Row],[PESO TOTAL]]/Tabela2234[[#This Row],[QUANTIDADE]] -> #DIV/0!
B62: =TEXT(Tabela2234[[#This Row],[DATA]],"mmmm") -> janeiro | I62: =Tabela2234[[#This Row],[PESO TOTAL]]/Tabela2234[[#This Row],[QUANTIDADE]] -> #DIV/0!
B63: =TEXT(Tabela2234[[#This Row],[DATA]],"mmmm") -> janeiro | I63: =Tabela2234[[#This Row],[PESO TOTAL]]/Tabela2234[[#This Row],[QUANTIDADE]] -> #DIV/0!
B64: =TEXT(Tabela2234[[#This Row],[DATA]],"mmmm") -> janeiro | I64: =Tabela2234[[#This Row],[PESO TOTAL]]/Tabela2234[[#This Row],[QUANTIDADE]] -> #DIV/0!
B65: =TEXT(Tabela2234[[#This Row],[DATA]],"mmmm") -> janeiro | I65: =Tabela2234[[#This Row],[PESO TOTAL]]/Tabela2234[[#This Row],[QUANTIDADE]] -> #DIV/0!
B66: =TEXT(Tabela2234[[#This Row],[DATA]],"mmmm") -> janeiro | I66: =Tabela2234[[#This Row],[PESO TOTAL]]/Tabela2234[[#This Row],[QUANTIDADE]] -> #DIV/0!
B67: =TEXT(Tabela2234[[#This Row],[DATA]],"mmmm") -> janeiro | I67: =Tabela2234[[#This Row],[PESO TOTAL]]/Tabela2234[[#This Row],[QUANTIDADE]] -> #DIV/0!
B68: =TEXT(Tabela2234[[#This Row],[DATA]],"mmmm") -> janeiro | I68: =Tabela2234[[#This Row],[PESO TOTAL]]/Tabela2234[[#This Row],[QUANTIDADE]] -> #DIV/0!
... B567: =TEXT(Tabela2234[[#This Row],[DATA]],"mmmm") -> janeiro | I567: =Tabela2234[[#This Row],[PESO TOTAL]]/Tabela2234[[#This Row],[QUANTIDADE]] -> #DIV/0!

Sheet GOIANO
A1: MOVIMENTAÇÃO FAZENDA GOIANO | S1: COMPRA
D2: ENTRADAS | J2: SAIDAS | O2: POSIÇÃO | S2: NASC.
S3: TRANSF. E
A4: CATEGORIAS | D4: SALDO ANTERIOR | E4: COMPRA | F4: EVOLUÇ | G4: NASC. | H4: TRANSF. E | I4: TOTAL | J4: ABATE | K4: MORTE | L4: VENDA | M4: TRANSF. S | N4: TOTAL | O4: FINAL | S4: ABATE
A5: Femeas + 36 meses | E5: =SUMIFS($E$20:$E$1048576,$D$20:$D$1048576,$E$4,$C$20:$C$1048576,A5) -> 0 | F5: =SUMIFS($E$20:$E$1048576,$D$20:$D$1048576,$F$4,$C$20:$C$1048576,B5) -> 0 | G5: =SUMIFS($E$20:$E$1048576,$D$20:$D$1048576,$G$4,$C$20:$C$1048576,A5) -> 0 | H5: =SUMIFS($E$20:$E$1048576,$D$20:$D$1048576,$H$4,$C$20:$C$1048576,A5) -> 0 | I5: =SUM(D5:H5) -> 0 | J5: =SUMIFS($E$20:$E$1048576,$D$20:$D$1048576,$J$4,$C$20:$C$1048576,A5) -> 0 | K5: =SUMIFS($E$20:$E$1048576,$D$20:$D$1048576,$K$4,$C$20:$C$1048576,A5) -> 0 | L5: =SUMIFS($E$20:$E$1048576,$D$20:$D$1048576,$L$4,$C$20:$C$1048576,A5) -> 0 | M5: =SUMIFS($E$20:$E$1048576,$D$20:$D$1048576,$M$4,$C$20:$C$1048576,A5) -> 0 | N5: =SUM(J5:M5) -> 0 | O5: =SUM(I5-N5) -> 0 | S5: MORTE
A6: Femeas 25 a 36 meses | E6: =SUMIFS($E$20:$E$1048576,$D$20:$D$1048576,$E$4,$C$20:$C$1048576,A6) -> 0 | F6: =SUMIFS($E$20:$E$1048576,$D$20:$D$1048576,$F$4,$C$20:$C$1048576,B6) -> 0 | G6: =SUMIFS($E$20:$E$1048576,$D$20:$D$1048576,$G$4,$C$20:$C$1048576,A6) -> 0 | H6: =SUMIFS($E$20:$E$1048576,$D$20:$D$1048576,$H$4,$C$20:$C$1048576,A6) -> 0 | I6: =SUM(D6:H6) -> 0 | J6: =SUMIFS($E$20:$E$1048576,$D$20:$D$1048576,$J$4,$C$20:$C$1048576,A6) -> 0 | K6: =SUMIFS($E$20:$E$1048576,$D$20:$D$1048576,$K$4,$C$20:$C$1048576,A6) -> 0 | L6: =SUMIFS($E$20:$E$1048576,$D$20:$D$1048576,$L$4,$C$20:$C$1048576,A6) -> 0 | M6: =SUMIFS($E$20:$E$1048576,$D$20:$D$1048576,$M$4,$C$20:$C$1048576,A6) -> 0 | N6: =SUM(J6:M6) -> 0 | O6: =SUM(I6-N6) -> 0 | S6: TRANSF. S
A7: Femeas 13 a 24 meses | E7: =SUMIFS($E$20:$E$1048576,$D$20:$D$1048576,$E$4,$C$20:$C$1048576,A7) -> 0 | F7: =SUMIFS($E$20:$E$1048576,$D$20:$D$1048576,$F$4,$C$20:$C$1048576,B7) -> 0 | G7: =SUMIFS($E$20:$E$1048576,$D$20:$D$1048576,$G$4,$C$20:$C$1048576,A7) -> 0 | H7: =SUMIFS($E$20:$E$1048576,$D$20:$D$1048576,$H$4,$C$20:$C$1048576,A7) -> 0 | I7: =SUM(D7:H7) -> 0 | J7: =SUMIFS($E$20:$E$1048576,$D$20:$D$1048576,$J$4,$C$20:$C$1048576,A7) -> 0 | K7: =SUMIFS($E$20:$E$1048576,$D$20:$D$1048576,$K$4,$C$20:$C$1048576,A7) -> 0 | L7: =SUMIFS($E$20:$E$1048576,$D$20:$D$1048576,$L$4,$C$20:$C$1048576,A7) -> 0 | M7: =SUMIFS($E$20:$E$1048576,$D$20:$D$1048576,$M$4,$C$20:$C$1048576,A7) -> 0 | N7: =SUM(J7:M7) -> 0 | O7: =SUM(I7-N7) -> 0 | S7: SALDO ANTERIOR
A8: Femeas Desm. até 12m | E8: =SUMIFS($E$20:$E$1048576,$D$20:$D$1048576,$E$4,$C$20:$C$1048576,A8) -> 0 | F8: =SUMIFS($E$20:$E$1048576,$D$20:$D$1048576,$F$4,$C$20:$C$1048576,B8) -> 0 | G8: =SUMIFS($E$20:$E$1048576,$D$20:$D$1048576,$G$4,$C$20:$C$1048576,A8) -> 0 | H8: =SUMIFS($E$20:$E$1048576,$D$20:$D$1048576,$H$4,$C$20:$C$1048576,A8) -> 0 | I8: =SUM(D8:H8) -> 0 | J8: =SUMIFS($E$20:$E$1048576,$D$20:$D$1048576,$J$4,$C$20:$C$1048576,A8) -> 0 | K8: =SUMIFS($E$20:$E$1048576,$D$20:$D$1048576,$K$4,$C$20:$C$1048576,A8) -> 0 | L8: =SUMIFS($E$20:$E$1048576,$D$20:$D$1048576,$L$4,$C$20:$C$1048576,A8) -> 0 | M8: =SUMIFS($E$20:$E$1048576,$D$20:$D$1048576,$M$4,$C$20:$C$1048576,A8) -> 0 | N8: =SUM(J8:M8) -> 0 | O8: =SUM(I8-N8) -> 0 | S8: EVOLUÇ
A9: Bezerras Mamando | E9: =SUMIFS($E$20:$E$1048576,$D$20:$D$1048576,$E$4,$C$20:$C$1048576,A9) -> 0 | F9: =SUMIFS($E$20:$E$1048576,$D$20:$D$1048576,$F$4,$C$20:$C$1048576,B9) -> 0 | G9: =SUMIFS($E$20:$E$1048576,$D$20:$D$1048576,$G$4,$C$20:$C$1048576,A9) -> 0 | H9: =SUMIFS($E$20:$E$1048576,$D$20:$D$1048576,$H$4,$C$20:$C$1048576,A9) -> 0 | I9: =SUM(D9:H9) -> 0 | J9: =SUMIFS($E$20:$E$1048576,$D$20:$D$1048576,$J$4,$C$20:$C$1048576,A9) -> 0 | K9: =SUMIFS($E$20:$E$1048576,$D$20:$D$1048576,$K$4,$C$20:$C$1048576,A9) -> 0 | L9: =SUMIFS($E$20:$E$1048576,$D$20:$D$1048576,$L$4,$C$20:$C$1048576,A9) -> 0 | M9: =SUMIFS($E$20:$E$1048576,$D$20:$D$1048576,$M$4,$C$20:$C$1048576,A9) -> 0 | N9: =SUM(J9:M9) -> 0 | O9: =SUM(I9-N9) -> 0 | S9: VENDA
A10: Bezerros Mamando | E10: =SUMIFS($E$20:$E$1048576,$D$20:$D$1048576,$E$4,$C$20:$C$1048576,A10) -> 0 | F10: =SUMIFS($E$20:$E$1048576,$D$20:$D$1048576,$F$4,$C$20:$C$1048576,B10) -> 0 | G10: =SUMIFS($E$20:$E$1048576,$D$20:$D$1048576,$G$4,$C$20:$C$1048576,A10) -> 0 | H10: =SUMIFS($E$20:$E$1048576,$D$20:$D$1048576,$H$4,$C$20:$C$1048576,A10) -> 0 | I10: =SUM(D10:H10) -> 0 | J10: =SUMIFS($E$20:$E$1048576,$D$20:$D$1048576,$J$4,$C$20:$C$1048576,A10) -> 0 | K10: =SUMIFS($E$20:$E$1048576,$D$20:$D$1048576,$K$4,$C$20:$C$1048576,A10) -> 0 | L10: =SUMIFS($E$20:$E$1048576,$D$20:$D$1048576,$L$4,$C$20:$C$1048576,A10) -> 0 | M10: =SUMIFS($E$20:$E$1048576,$D$20:$D$1048576,$M$4,$C$20:$C$1048576,A10) -> 0 | N10: =SUM(J10:M10) -> 0 | O10: =SUM(I10-N10) -> 0
A11: Machos Desm. até 12m | E11: =SUMIFS($E$20:$E$1048576,$D$20:$D$1048576,$E$4,$C$20:$C$1048576,A11) -> 0 | F11: =SUMIFS($E$20:$E$1048576,$D$20:$D$1048576,$F$4,$C$20:$C$1048576,B11) -> 0 | G11: =SUMIFS($E$20:$E$1048576,$D$20:$D$1048576,$G$4,$C$20:$C$1048576,A11) -> 0 | H11: =SUMIFS($E$20:$E$1048576,$D$20:$D$1048576,$H$4,$C$20:$C$1048576,A11) -> 0 | I11: =SUM(D11:H11) -> 0 | J11: =SUMIFS($E$20:$E$1048576,$D$20:$D$1048576,$J$4,$C$20:$C$1048576,A11) -> 0 | K11: =SUMIFS($E$20:$E$1048576,$D$20:$D$1048576,$K$4,$C$20:$C$1048576,A11) -> 0 | L11: =SUMIFS($E$20:$E$1048576,$D$20:$D$1048576,$L$4,$C$20:$C$1048576,A11) -> 0 | M11: =SUMIFS($E$20:$E$1048576,$D$20:$D$1048576,$M$4,$C$20:$C$1048576,A11) -> 140 | N11: =SUM(J11:M11) -> 140 | O11: =SUM(I11-N11) -> -140
A12: Machos 13 a 24 meses | E12: =SUMIFS($E$20:$E$1048576,$D$20:$D$1048576,$E$4,$C$20:$C$1048576,A12) -> 0 | F12: =SUMIFS($E$20:$E$1048576,$D$20:$D$1048576,$F$4,$C$20:$C$1048576,B12) -> 0 | G12: =SUMIFS($E$20:$E$1048576,$D$20:$D$1048576,$G$4,$C$20:$C$1048576,A12) -> 0 | H12: =SUMIFS($E$20:$E$1048576,$D$20:$D$1048576,$H$4,$C$20:$C$1048576,A12) -> 0 | I12: =SUM(D12:H12) -> 0 | J12: =SUMIFS($E$20:$E$1048576,$D$20:$D$1048576,$J$4,$C$20:$C$1048576,A12) -> 0 | K12: =SUMIFS($E$20:$E$1048576,$D$20:$D$1048576,$K$4,$C$20:$C$1048576,A12) -> 0 | L12: =SUMIFS($E$20:$E$1048576,$D$20:$D$1048576,$L$4,$C$20:$C$1048576,A12) -> 0 | M12: =SUMIFS($E$20:$E$1048576,$D$20:$D$1048576,$M$4,$C$20:$C$1048576,A12) -> 0 | N12: =SUM(J12:M12) -> 0 | O12: =SUM(I12-N12) -> 0
A13: Machos 25 a 36 meses | E13: =SUMIFS($E$20:$E$1048576,$D$20:$D$1048576,$E$4,$C$20:$C$1048576,A13) -> 0 | F13: =SUMIFS($E$20:$E$1048576,$D$20:$D$1048576,$F$4,$C$20:$C$1048576,B13) -> 0 | G13: =SUMIFS($E$20:$E$1048576,$D$20:$D$1048576,$G$4,$C$20:$C$1048576,A13) -> 0 | H13: =SUMIFS($E$20:$E$1048576,$D$20:$D$1048576,$H$4,$C$20:$C$1048576,A13) -> 0 | I13: =SUM(D13:H13) -> 0 | J13: =SUMIFS($E$20:$E$1048576,$D$20:$D$1048576,$J$4,$C$20:$C$1048576,A13) -> 0 | K13: =SUMIFS($E$20:$E$1048576,$D$20:$D$1048576,$K$4,$C$20:$C$1048576,A13) -> 0 | L13: =SUMIFS($E$20:$E$1048576,$D$20:$D$1048576,$L$4,$C$20:$C$1048576,A13) -> 0 | M13: =SUMIFS($E$20:$E$1048576,$D$20:$D$1048576,$M$4,$C$20:$C$1048576,A13) -> 0 | N13: =SUM(J13:M13) -> 0 | O13: =SUM(I13-N13) -> 0
A14: Touros | E14: =SUMIFS($E$20:$E$1048576,$D$20:$D$1048576,$E$4,$C$20:$C$1048576,A14) -> 0 | F14: =SUMIFS($E$20:$E$1048576,$D$20:$D$1048576,$F$4,$C$20:$C$1048576,B14) -> 0 | G14: =SUMIFS($E$20:$E$1048576,$D$20:$D$1048576,$G$4,$C$20:$C$1048576,A14) -> 0 | H14: =SUMIFS($E$20:$E$1048576,$D$20:$D$1048576,$H$4,$C$20:$C$1048576,A14) -> 0 | I14: =SUM(D14:H14) -> 0 | J14: =SUMIFS($E$20:$E$1048576,$D$20:$D$1048576,$J$4,$C$20:$C$1048576,A14) -> 0 | K14: =SUMIFS($E$20:$E$1048576,$D$20:$D$1048576,$K$4,$C$20:$C$1048576,A14) -> 0 | L14: =SUMIFS($E$20:$E$1048576,$D$20:$D$1048576,$L$4,$C$20:$C$1048576,A14) -> 0 | M14: =SUMIFS($E$20:$E$1048576,$D$20:$D$1048576,$M$4,$C$20:$C$1048576,A14) -> 0 | N14: =SUM(J14:M14) -> 0 | O14: =SUM(I14-N14) -> 0
A15: TROPA | E15: =SUMIFS($E$20:$E$1048576,$D$20:$D$1048576,$E$4,$C$20:$C$1048576,A15) -> 0 | G15: =SUMIFS($E$20:$E$1048576,$D$20:$D$1048576,$G$4,$C$20:$C$1048576,A15) -> 0 | H15: =SUMIFS($E$20:$E$1048576,$D$20:$D$1048576,$H$4,$C$20:$C$1048576,A15) -> 0 | I15: =SUM(D15:H15) -> 0 | J15: =SUMIFS($E$20:$E$1048576,$D$20:$D$1048576,$J$4,$C$20:$C$1048576,A15) -> 0 | K15: =SUMIFS($E$20:$E$1048576,$D$20:$D$1048576,$K$4,$C$20:$C$1048576,A15) -> 0 | L15: =SUMIFS($E$20:$E$1048576,$D$20:$D$1048576,$L$4,$C$20:$C$1048576,A15) -> 0 | M15: =SUMIFS($E$20:$E$1048576,$D$20:$D$1048576,$M$4,$C$20:$C$1048576,A15) -> 0 | N15: =SUM(J15:M15) -> 0 | O15: =SUM(I15-N15) -> 0
A16: TOTAL | D16: =SUM(D5:D15) -> 0 | E16: =SUM(E5:E15) -> 0 | F16: =SUM(F5:F15) -> 0 | G16: =SUM(G5:G15) -> 0 | H16: =SUM(H5:H15) -> 0 | I16: =SUM(I5:I15) -> 0 | J16: =SUM(J5:J15) -> 0 | K16: =SUM(K5:K15) -> 0 | ... O16: =SUM(O5:O15) -> -140
A18: MOVIMENTAÇÕES DE BOVINOS
A19: DATA | B19: MÊS | C19: CATEGORIA | D19: TIPO | E19: QUANTIDADE | F19: SAIDA | G19: DESTINO | H19: PESO TOTAL | I19: PESO MÉDIO
A20: 45858 | B20: =TEXT(Tabela22[[#This Row],[DATA]],"mmm") -> jul | C20: Machos Desm. até 12m | D20: TRANSF. S | E20: 95 | F20: - | G20: GOIANO | H20: - | I20: =Tabela22[[#This Row],[PESO TOTAL]]/Tabela22[[#This Row],[QUANTIDADE]] -> #VALUE!
A21: 45889 | B21: =TEXT(Tabela22[[#This Row],[DATA]],"mmm") -> ago | C21: Machos Desm. até 12m | D21: TRANSF. S | E21: 45 | G21: GOIANO | I21: =Tabela22[[#This Row],[PESO TOTAL]]/Tabela22[[#This Row],[QUANTIDADE]] -> 0
B22: =TEXT(Tabela22[[#This Row],[DATA]],"mmm") -> jan | I22: =Tabela22[[#This Row],[PESO TOTAL]]/Tabela22[[#This Row],[QUANTIDADE]] -> #DIV/0!
B23: =TEXT(Tabela22[[#This Row],[DATA]],"mmm") -> jan | I23: =Tabela22[[#This Row],[PESO TOTAL]]/Tabela22[[#This Row],[QUANTIDADE]] -> #DIV/0!
B24: =TEXT(Tabela22[[#This Row],[DATA]],"mmm") -> jan | I24: =Tabela22[[#This Row],[PESO TOTAL]]/Tabela22[[#This Row],[QUANTIDADE]] -> #DIV/0!
B25: =TEXT(Tabela22[[#This Row],[DATA]],"mmm") -> jan | I25: =Tabela22[[#This Row],[PESO TOTAL]]/Tabela22[[#This Row],[QUANTIDADE]] -> #DIV/0!
B26: =TEXT(Tabela22[[#This Row],[DATA]],"mmm") -> jan | I26: =Tabela22[[#This Row],[PESO TOTAL]]/Tabela22[[#This Row],[QUANTIDADE]] -> #DIV/0!
B27: =TEXT(Tabela22[[#This Row],[DATA]],"mmm") -> jan | I27: =Tabela22[[#This Row],[PESO TOTAL]]/Tabela22[[#This Row],[QUANTIDADE]] -> #DIV/0!
B28: =TEXT(Tabela22[[#This Row],[DATA]],"mmmm") -> janeiro | I28: =Tabela22[[#This Row],[PESO TOTAL]]/Tabela22[[#This Row],[QUANTIDADE]] -> #DIV/0!
B29: =TEXT(Tabela22[[#This Row],[DATA]],"mmmm") -> janeiro | I29: =Tabela22[[#This Row],[PESO TOTAL]]/Tabela22[[#This Row],[QUANTIDADE]] -> #DIV/0!
B30: =TEXT(Tabela22[[#This Row],[DATA]],"mmmm") -> janeiro | I30: =Tabela22[[#This Row],[PESO TOTAL]]/Tabela22[[#This Row],[QUANTIDADE]] -> #DIV/0!
B31: =TEXT(Tabela22[[#This Row],[DATA]],"mmmm") -> janeiro | I31: =Tabela22[[#This Row],[PESO TOTAL]]/Tabela22[[#This Row],[QUANTIDADE]] -> #DIV/0!
B32: =TEXT(Tabela22[[#This Row],[DATA]],"mmmm") -> janeiro | I32: =Tabela22[[#This Row],[PESO TOTAL]]/Tabela22[[#This Row],[QUANTIDADE]] -> #DIV/0!
B33: =TEXT(Tabela22[[#This Row],[DATA]],"mmmm") -> janeiro | I33: =Tabela22[[#This Row],[PESO TOTAL]]/Tabela22[[#This Row],[QUANTIDADE]] -> #DIV/0!
B34: =TEXT(Tabela22[[#This Row],[DATA]],"mmmm") -> janeiro | I34: =Tabela22[[#This Row],[PESO TOTAL]]/Tabela22[[#This Row],[QUANTIDADE]] -> #DIV/0!
B35: =TEXT(Tabela22[[#This Row],[DATA]],"mmmm") -> janeiro | I35: =Tabela22[[#This Row],[PESO TOTAL]]/Tabela22[[#This Row],[QUANTIDADE]] -> #DIV/0!
B36: =TEXT(Tabela22[[#This Row],[DATA]],"mmmm") -> janeiro | I36: =Tabela22[[#This Row],[PESO TOTAL]]/Tabela22[[#This Row],[QUANTIDADE]] -> #DIV/0!
B37: =TEXT(Tabela22[[#This Row],[DATA]],"mmmm") -> janeiro | I37: =Tabela22[[#This Row],[PESO TOTAL]]/Tabela22[[#This Row],[QUANTIDADE]] -> #DIV/0!
B38: =TEXT(Tabela22[[#This Row],[DATA]],"mmmm") -> janeiro | I38: =Tabela22[[#This Row],[PESO TOTAL]]/Tabela22[[#This Row],[QUANTIDADE]] -> #DIV/0!
B39: =TEXT(Tabela22[[#This Row],[DATA]],"mmmm") -> janeiro | I39: =Tabela22[[#This Row],[PESO TOTAL]]/Tabela22[[#This Row],[QUANTIDADE]] -> #DIV/0!
... B572: =TEXT(Tabela22[[#This Row],[DATA]],"mmmm") -> janeiro | I572: =Tabela22[[#This Row],[PESO TOTAL]]/Tabela22[[#This Row],[QUANTIDADE]] -> #DIV/0!

Sheet BAIXÃO
A1: MOVIMENTAÇÃO FAZENDA BAIXÃO | S1: COMPRA
D2: ENTRADAS | J2: SAIDAS | O2: POSIÇÃO | S2: NASC.
S3: TRANSF. E
A4: CATEGORIAS | D4: SALDO ANTERIOR | E4: COMPRA | F4: EVOLUÇ | G4: NASC. | H4: TRANSF. E | I4: TOTAL | J4: ABATE | K4: MORTE | L4: VENDA | M4: TRANSF. S | N4: TOTAL | O4: FINAL | S4: ABATE
A5: Femeas + 36 meses | E5: =SUMIFS($E$20:$E$1048576,$D$20:$D$1048576,$E$4,$C$20:$C$1048576,A5) -> 0 | F5: =SUMIFS($E$20:$E$1048576,$D$20:$D$1048576,$F$4,$C$20:$C$1048576,B5) -> 0 | G5: =SUMIFS($E$20:$E$1048576,$D$20:$D$1048576,$G$4,$C$20:$C$1048576,A5) -> 0 | H5: =SUMIFS($E$20:$E$1048576,$D$20:$D$1048576,$H$4,$C$20:$C$1048576,A5) -> 0 | I5: =SUM(D5:H5) -> 0 | J5: =SUMIFS($E$20:$E$1048576,$D$20:$D$1048576,$J$4,$C$20:$C$1048576,A5) -> 0 | K5: =SUMIFS($E$20:$E$1048576,$D$20:$D$1048576,$K$4,$C$20:$C$1048576,A5) -> 0 | L5: =SUMIFS($E$20:$E$1048576,$D$20:$D$1048576,$L$4,$C$20:$C$1048576,A5) -> 0 | M5: =SUMIFS($E$20:$E$1048576,$D$20:$D$1048576,$M$4,$C$20:$C$1048576,A5) -> 0 | N5: =SUM(J5:M5) -> 0 | O5: =SUM(I5-N5) -> 0 | S5: MORTE
A6: Femeas 25 a 36 meses | E6: =SUMIFS($E$20:$E$1048576,$D$20:$D$1048576,$E$4,$C$20:$C$1048576,A6) -> 0 | F6: =SUMIFS($E$20:$E$1048576,$D$20:$D$1048576,$F$4,$C$20:$C$1048576,B6) -> 0 | G6: =SUMIFS($E$20:$E$1048576,$D$20:$D$1048576,$G$4,$C$20:$C$1048576,A6) -> 0 | H6: =SUMIFS($E$20:$E$1048576,$D$20:$D$1048576,$H$4,$C$20:$C$1048576,A6) -> 0 | I6: =SUM(D6:H6) -> 0 | J6: =SUMIFS($E$20:$E$1048576,$D$20:$D$1048576,$J$4,$C$20:$C$1048576,A6) -> 0 | K6: =SUMIFS($E$20:$E$1048576,$D$20:$D$1048576,$K$4,$C$20:$C$1048576,A6) -> 0 | L6: =SUMIFS($E$20:$E$1048576,$D$20:$D$1048576,$L$4,$C$20:$C$1048576,A6) -> 0 | M6: =SUMIFS($E$20:$E$1048576,$D$20:$D$1048576,$M$4,$C$20:$C$1048576,A6) -> 0 | N6: =SUM(J6:M6) -> 0 | O6: =SUM(I6-N6) -> 0 | S6: TRANSF. S
A7: Femeas 13 a 24 meses | E7: =SUMIFS($E$20:$E$1048576,$D$20:$D$1048576,$E$4,$C$20:$C$1048576,A7) -> 0 | F7: =SUMIFS($E$20:$E$1048576,$D$20:$D$1048576,$F$4,$C$20:$C$1048576,B7) -> 0 | G7: =SUMIFS($E$20:$E$1048576,$D$20:$D$1048576,$G$4,$C$20:$C$1048576,A7) -> 0 | H7: =SUMIFS($E$20:$E$1048576,$D$20:$D$1048576,$H$4,$C$20:$C$1048576,A7) -> 0 | I7: =SUM(D7:H7) -> 0 | J7: =SUMIFS($E$20:$E$1048576,$D$20:$D$1048576,$J$4,$C$20:$C$1048576,A7) -> 0 | K7: =SUMIFS($E$20:$E$1048576,$D$20:$D$1048576,$K$4,$C$20:$C$1048576,A7) -> 0 | L7: =SUMIFS($E$20:$E$1048576,$D$20:$D$1048576,$L$4,$C$20:$C$1048576,A7) -> 0 | M7: =SUMIFS($E$20:$E$1048576,$D$20:$D$1048576,$M$4,$C$20:$C$1048576,A7) -> 0 | N7: =SUM(J7:M7) -> 0 | O7: =SUM(I7-N7) -> 0 | S7: SALDO ANTERIOR
A8: Femeas Desm. até 12m | E8: =SUMIFS($E$20:$E$1048576,$D$20:$D$1048576,$E$4,$C$20:$C$1048576,A8) -> 0 | F8: =SUMIFS($E$20:$E$1048576,$D$20:$D$1048576,$F$4,$C$20:$C$1048576,B8) -> 0 | G8: =SUMIFS($E$20:$E$1048576,$D$20:$D$1048576,$G$4,$C$20:$C$1048576,A8) -> 0 | H8: =SUMIFS($E$20:$E$1048576,$D$20:$D$1048576,$H$4,$C$20:$C$1048576,A8) -> 0 | I8: =SUM(D8:H8) -> 0 | J8: =SUMIFS($E$20:$E$1048576,$D$20:$D$1048576,$J$4,$C$20:$C$1048576,A8) -> 0 | K8: =SUMIFS($E$20:$E$1048576,$D$20:$D$1048576,$K$4,$C$20:$C$1048576,A8) -> 0 | L8: =SUMIFS($E$20:$E$1048576,$D$20:$D$1048576,$L$4,$C$20:$C$1048576,A8) -> 0 | M8: =SUMIFS($E$20:$E$1048576,$D$20:$D$1048576,$M$4,$C$20:$C$1048576,A8) -> 0 | N8: =SUM(J8:M8) -> 0 | O8: =SUM(I8-N8) -> 0 | S8: EVOLUÇ
A9: Bezerras Mamando | E9: =SUMIFS($E$20:$E$1048576,$D$20:$D$1048576,$E$4,$C$20:$C$1048576,A9) -> 0 | F9: =SUMIFS($E$20:$E$1048576,$D$20:$D$1048576,$F$4,$C$20:$C$1048576,B9) -> 0 | G9: =SUMIFS($E$20:$E$1048576,$D$20:$D$1048576,$G$4,$C$20:$C$1048576,A9) -> 0 | H9: =SUMIFS($E$20:$E$1048576,$D$20:$D$1048576,$H$4,$C$20:$C$1048576,A9) -> 0 | I9: =SUM(D9:H9) -> 0 | J9: =SUMIFS($E$20:$E$1048576,$D$20:$D$1048576,$J$4,$C$20:$C$1048576,A9) -> 0 | K9: =SUMIFS($E$20:$E$1048576,$D$20:$D$1048576,$K$4,$C$20:$C$1048576,A9) -> 0 | L9: =SUMIFS($E$20:$E$1048576,$D$20:$D$1048576,$L$4,$C$20:$C$1048576,A9) -> 0 | M9: =SUMIFS($E$20:$E$1048576,$D$20:$D$1048576,$M$4,$C$20:$C$1048576,A9) -> 0 | N9: =SUM(J9:M9) -> 0 | O9: =SUM(I9-N9) -> 0 | S9: VENDA
A10: Bezerros Mamando | E10: =SUMIFS($E$20:$E$1048576,$D$20:$D$1048576,$E$4,$C$20:$C$1048576,A10) -> 0 | F10: =SUMIFS($E$20:$E$1048576,$D$20:$D$1048576,$F$4,$C$20:$C$1048576,B10) -> 0 | G10: =SUMIFS($E$20:$E$1048576,$D$20:$D$1048576,$G$4,$C$20:$C$1048576,A10) -> 0 | H10: =SUMIFS($E$20:$E$1048576,$D$20:$D$1048576,$H$4,$C$20:$C$1048576,A10) -> 0 | I10: =SUM(D10:H10) -> 0 | J10: =SUMIFS($E$20:$E$1048576,$D$20:$D$1048576,$J$4,$C$20:$C$1048576,A10) -> 0 | K10: =SUMIFS($E$20:$E$1048576,$D$20:$D$1048576,$K$4,$C$20:$C$1048576,A10) -> 0 | L10: =SUMIFS($E$20:$E$1048576,$D$20:$D$1048576,$L$4,$C$20:$C$1048576,A10) -> 0 | M10: =SUMIFS($E$20:$E$1048576,$D$20:$D$1048576,$M$4,$C$20:$C$1048576,A10) -> 0 | N10: =SUM(J10:M10) -> 0 | O10: =SUM(I10-N10) -> 0
A11: Machos Desm. até 12m | E11: =SUMIFS($E$20:$E$1048576,$D$20:$D$1048576,$E$4,$C$20:$C$1048576,A11) -> 0 | F11: =SUMIFS($E$20:$E$1048576,$D$20:$D$1048576,$F$4,$C$20:$C$1048576,B11) -> 0 | G11: =SUMIFS($E$20:$E$1048576,$D$20:$D$1048576,$G$4,$C$20:$C$1048576,A11) -> 0 | H11: =SUMIFS($E$20:$E$1048576,$D$20:$D$1048576,$H$4,$C$20:$C$1048576,A11) -> 0 | I11: =SUM(D11:H11) -> 0 | J11: =SUMIFS($E$20:$E$1048576,$D$20:$D$1048576,$J$4,$C$20:$C$1048576,A11) -> 0 | K11: =SUMIFS($E$20:$E$1048576,$D$20:$D$1048576,$K$4,$C$20:$C$1048576,A11) -> 0 | L11: =SUMIFS($E$20:$E$1048576,$D$20:$D$1048576,$L$4,$C$20:$C$1048576,A11) -> 0 | M11: =SUMIFS($E$20:$E$1048576,$D$20:$D$1048576,$M$4,$C$20:$C$1048576,A11) -> 0 | N11: =SUM(J11:M11) -> 0 | O11: =SUM(I11-N11) -> 0
A12: Machos 13 a 24 meses | E12: =SUMIFS($E$20:$E$1048576,$D$20:$D$1048576,$E$4,$C$20:$C$1048576,A12) -> 0 | F12: =SUMIFS($E$20:$E$1048576,$D$20:$D$1048576,$F$4,$C$20:$C$1048576,B12) -> 0 | G12: =SUMIFS($E$20:$E$1048576,$D$20:$D$1048576,$G$4,$C$20:$C$1048576,A12) -> 0 | H12: =SUMIFS($E$20:$E$1048576,$D$20:$D$1048576,$H$4,$C$20:$C$1048576,A12) -> 0 | I12: =SUM(D12:H12) -> 0 | J12: =SUMIFS($E$20:$E$1048576,$D$20:$D$1048576,$J$4,$C$20:$C$1048576,A12) -> 0 | K12: =SUMIFS($E$20:$E$1048576,$D$20:$D$1048576,$K$4,$C$20:$C$1048576,A12) -> 0 | L12: =SUMIFS($E$20:$E$1048576,$D$20:$D$1048576,$L$4,$C$20:$C$1048576,A12) -> 0 | M12: =SUMIFS($E$20:$E$1048576,$D$20:$D$1048576,$M$4,$C$20:$C$1048576,A12) -> 0 | N12: =SUM(J12:M12) -> 0 | O12: =SUM(I12-N12) -> 0
A13: Machos 25 a 36 meses | E13: =SUMIFS($E$20:$E$1048576,$D$20:$D$1048576,$E$4,$C$20:$C$1048576,A13) -> 0 | F13: =SUMIFS($E$20:$E$1048576,$D$20:$D$1048576,$F$4,$C$20:$C$1048576,B13) -> 0 | G13: =SUMIFS($E$20:$E$1048576,$D$20:$D$1048576,$G$4,$C$20:$C$1048576,A13) -> 0 | H13: =SUMIFS($E$20:$E$1048576,$D$20:$D$1048576,$H$4,$C$20:$C$1048576,A13) -> 0 | I13: =SUM(D13:H13) -> 0 | J13: =SUMIFS($E$20:$E$1048576,$D$20:$D$1048576,$J$4,$C$20:$C$1048576,A13) -> 0 | K13: =SUMIFS($E$20:$E$1048576,$D$20:$D$1048576,$K$4,$C$20:$C$1048576,A13) -> 0 | L13: =SUMIFS($E$20:$E$1048576,$D$20:$D$1048576,$L$4,$C$20:$C$1048576,A13) -> 0 | M13: =SUMIFS($E$20:$E$1048576,$D$20:$D$1048576,$M$4,$C$20:$C$1048576,A13) -> 0 | N13: =SUM(J13:M13) -> 0 | O13: =SUM(I13-N13) -> 0
A14: Touros | E14: =SUMIFS($E$20:$E$1048576,$D$20:$D$1048576,$E$4,$C$20:$C$1048576,A14) -> 0 | F14: =SUMIFS($E$20:$E$1048576,$D$20:$D$1048576,$F$4,$C$20:$C$1048576,B14) -> 0 | G14: =SUMIFS($E$20:$E$1048576,$D$20:$D$1048576,$G$4,$C$20:$C$1048576,A14) -> 0 | H14: =SUMIFS($E$20:$E$1048576,$D$20:$D$1048576,$H$4,$C$20:$C$1048576,A14) -> 0 | I14: =SUM(D14:H14) -> 0 | J14: =SUMIFS($E$20:$E$1048576,$D$20:$D$1048576,$J$4,$C$20:$C$1048576,A14) -> 0 | K14: =SUMIFS($E$20:$E$1048576,$D$20:$D$1048576,$K$4,$C$20:$C$1048576,A14) -> 0 | L14: =SUMIFS($E$20:$E$1048576,$D$20:$D$1048576,$L$4,$C$20:$C$1048576,A14) -> 0 | M14: =SUMIFS($E$20:$E$1048576,$D$20:$D$1048576,$M$4,$C$20:$C$1048576,A14) -> 0 | N14: =SUM(J14:M14) -> 0 | O14: =SUM(I14-N14) -> 0
A15: TROPA | E15: =SUMIFS($E$20:$E$1048576,$D$20:$D$1048576,$E$4,$C$20:$C$1048576,A15) -> 0 | F15: 0 | G15: =SUMIFS($E$20:$E$1048576,$D$20:$D$1048576,$G$4,$C$20:$C$1048576,A15) -> 0 | H15: =SUMIFS($E$20:$E$1048576,$D$20:$D$1048576,$H$4,$C$20:$C$1048576,A15) -> 0 | I15: =SUM(D15:H15) -> 0 | J15: =SUMIFS($E$20:$E$1048576,$D$20:$D$1048576,$J$4,$C$20:$C$1048576,A15) -> 0 | K15: =SUMIFS($E$20:$E$1048576,$D$20:$D$1048576,$K$4,$C$20:$C$1048576,A15) -> 0 | L15: =SUMIFS($E$20:$E$1048576,$D$20:$D$1048576,$L$4,$C$20:$C$1048576,A15) -> 0 | M15: =SUMIFS($E$20:$E$1048576,$D$20:$D$1048576,$M$4,$C$20:$C$1048576,A15) -> 0 | N15: =SUM(J15:M15) -> 0 | O15: =SUM(I15-N15) -> 0
A16: TOTAL | D16: =SUM(D5:D15) -> 0 | E16: =SUM(E5:E15) -> 0 | F16: =SUM(F5:F15) -> 0 | G16: =SUM(G5:G15) -> 0 | H16: =SUM(H5:H15) -> 0 | I16: =SUM(I5:I15) -> 0 | J16: =SUM(J5:J15) -> 0 | K16: =SUM(K5:K15) -> 0 | ... O16: =SUM(O5:O15) -> 0
A18: MOVIMENTAÇÕES DE BOVINOS
A19: DATA | B19: MÊS | C19: CATEGORIA | D19: TIPO | E19: QUANTIDADE | F19: SAIDA | G19: DESTINO | H19: PESO TOTAL | I19: PESO MÉDIO
B20: =TEXT(Tabela223[[#This Row],[DATA]],"mmm") -> jan | I20: =Tabela22[[#This Row],[PESO TOTAL]]/Tabela22[[#This Row],[QUANTIDADE]] -> #VALUE!
B21: =TEXT(Tabela223[[#This Row],[DATA]],"mmm") -> jan | I21: =Tabela22[[#This Row],[PESO TOTAL]]/Tabela22[[#This Row],[QUANTIDADE]] -> 0
B22: =TEXT(Tabela223[[#This Row],[DATA]],"mmm") -> jan | I22: =Tabela22[[#This Row],[PESO TOTAL]]/Tabela22[[#This Row],[QUANTIDADE]] -> #DIV/0!
B23: =TEXT(Tabela223[[#This Row],[DATA]],"mmm") -> jan | I23: =Tabela22[[#This Row],[PESO TOTAL]]/Tabela22[[#This Row],[QUANTIDADE]] -> #DIV/0!
B24: =TEXT(Tabela223[[#This Row],[DATA]],"mmm") -> jan | I24: =Tabela22[[#This Row],[PESO TOTAL]]/Tabela22[[#This Row],[QUANTIDADE]] -> #DIV/0!
B25: =TEXT(Tabela223[[#This Row],[DATA]],"mmm") -> jan | I25: =Tabela22[[#This Row],[PESO TOTAL]]/Tabela22[[#This Row],[QUANTIDADE]] -> #DIV/0!
B26: =TEXT(Tabela223[[#This Row],[DATA]],"mmm") -> jan | I26: =Tabela22[[#This Row],[PESO TOTAL]]/Tabela22[[#This Row],[QUANTIDADE]] -> #DIV/0!
B27: =TEXT(Tabela223[[#This Row],[DATA]],"mmm") -> jan | I27: =Tabela22[[#This Row],[PESO TOTAL]]/Tabela22[[#This Row],[QUANTIDADE]] -> #DIV/0!
B28: =TEXT(Tabela223[[#This Row],[DATA]],"mmmm") -> janeiro | I28: =Tabela22[[#This Row],[PESO TOTAL]]/Tabela22[[#This Row],[QUANTIDADE]] -> #DIV/0!
B29: =TEXT(Tabela223[[#This Row],[DATA]],"mmmm") -> janeiro | I29: =Tabela22[[#This Row],[PESO TOTAL]]/Tabela22[[#This Row],[QUANTIDADE]] -> #DIV/0!
B30: =TEXT(Tabela223[[#This Row],[DATA]],"mmmm") -> janeiro | I30: =Tabela22[[#This Row],[PESO TOTAL]]/Tabela22[[#This Row],[QUANTIDADE]] -> #DIV/0!
B31: =TEXT(Tabela223[[#This Row],[DATA]],"mmmm") -> janeiro | I31: =Tabela22[[#This Row],[PESO TOTAL]]/Tabela22[[#This Row],[QUANTIDADE]] -> #DIV/0!
B32: =TEXT(Tabela223[[#This Row],[DATA]],"mmmm") -> janeiro | I32: =Tabela22[[#This Row],[PESO TOTAL]]/Tabela22[[#This Row],[QUANTIDADE]] -> #DIV/0!
B33: =TEXT(Tabela223[[#This Row],[DATA]],"mmmm") -> janeiro | I33: =Tabela22[[#This Row],[PESO TOTAL]]/Tabela22[[#This Row],[QUANTIDADE]] -> #DIV/0!
B34: =TEXT(Tabela223[[#This Row],[DATA]],"mmmm") -> janeiro | I34: =Tabela22[[#This Row],[PESO TOTAL]]/Tabela22[[#This Row],[QUANTIDADE]] -> #DIV/0!
B35: =TEXT(Tabela223[[#This Row],[DATA]],"mmmm") -> janeiro | I35: =Tabela22[[#This Row],[PESO TOTAL]]/Tabela22[[#This Row],[QUANTIDADE]] -> #DIV/0!
B36: =TEXT(Tabela223[[#This Row],[DATA]],"mmmm") -> janeiro | I36: =Tabela22[[#This Row],[PESO TOTAL]]/Tabela22[[#This Row],[QUANTIDADE]] -> #DIV/0!
B37: =TEXT(Tabela223[[#This Row],[DATA]],"mmmm") -> janeiro | I37: =Tabela22[[#This Row],[PESO TOTAL]]/Tabela22[[#This Row],[QUANTIDADE]] -> #DIV/0!
B38: =TEXT(Tabela223[[#This Row],[DATA]],"mmmm") -> janeiro | I38: =Tabela22[[#This Row],[PESO TOTAL]]/Tabela22[[#This Row],[QUANTIDADE]] -> #DIV/0!
B39: =TEXT(Tabela223[[#This Row],[DATA]],"mmmm") -> janeiro | I39: =Tabela22[[#This Row],[PESO TOTAL]]/Tabela22[[#This Row],[QUANTIDADE]] -> #DIV/0!
... B572: =TEXT(Tabela223[[#This Row],[DATA]],"mmmm") -> janeiro | I572: =Tabela22[[#This Row],[PESO TOTAL]]/Tabela22[[#This Row],[QUANTIDADE]] -> #DIV/0!

Sheet MORADA DO BOI
A1: MOVIMENTAÇÃO FAZENDA MORADA DO BOI | S1: COMPRA
D2: ENTRADAS | J2: SAIDAS | O2: POSIÇÃO | S2: NASC.
S3: TRANSF. E
A4: CATEGORIAS | D4: SALDO ANTERIOR | E4: COMPRA | F4: EVOLUÇ | G4: NASC. | H4: TRANSF. E | I4: TOTAL | J4: ABATE | K4: MORTE | L4: VENDA | M4: TRANSF. S | N4: TOTAL | O4: FINAL | S4: ABATE
A5: Femeas + 36 meses | E5: =SUMIFS($E$20:$E$1048576,$D$20:$D$1048576,$E$4,$C$20:$C$1048576,A5) -> 0 | F5: =SUMIFS($E$20:$E$1048576,$D$20:$D$1048576,$F$4,$C$20:$C$1048576,B5) -> 0 | G5: =SUMIFS($E$20:$E$1048576,$D$20:$D$1048576,$G$4,$C$20:$C$1048576,A5) -> 0 | H5: =SUMIFS($E$20:$E$1048576,$D$20:$D$1048576,$H$4,$C$20:$C$1048576,A5) -> 0 | I5: =SUM(D5:H5) -> 0 | J5: =SUMIFS($E$20:$E$1048576,$D$20:$D$1048576,$J$4,$C$20:$C$1048576,A5) -> 0 | K5: =SUMIFS($E$20:$E$1048576,$D$20:$D$1048576,$K$4,$C$20:$C$1048576,A5) -> 0 | L5: =SUMIFS($E$20:$E$1048576,$D$20:$D$1048576,$L$4,$C$20:$C$1048576,A5) -> 0 | M5: =SUMIFS($E$20:$E$1048576,$D$20:$D$1048576,$M$4,$C$20:$C$1048576,A5) -> 0 | N5: =SUM(J5:M5) -> 0 | O5: =SUM(I5-N5) -> 0 | S5: MORTE
A6: Femeas 25 a 36 meses | E6: =SUMIFS($E$20:$E$1048576,$D$20:$D$1048576,$E$4,$C$20:$C$1048576,A6) -> 0 | F6: =SUMIFS($E$20:$E$1048576,$D$20:$D$1048576,$F$4,$C$20:$C$1048576,B6) -> 0 | G6: =SUMIFS($E$20:$E$1048576,$D$20:$D$1048576,$G$4,$C$20:$C$1048576,A6) -> 0 | H6: =SUMIFS($E$20:$E$1048576,$D$20:$D$1048576,$H$4,$C$20:$C$1048576,A6) -> 0 | I6: =SUM(D6:H6) -> 0 | J6: =SUMIFS($E$20:$E$1048576,$D$20:$D$1048576,$J$4,$C$20:$C$1048576,A6) -> 0 | K6: =SUMIFS($E$20:$E$1048576,$D$20:$D$1048576,$K$4,$C$20:$C$1048576,A6) -> 0 | L6: =SUMIFS($E$20:$E$1048576,$D$20:$D$1048576,$L$4,$C$20:$C$1048576,A6) -> 0 | M6: =SUMIFS($E$20:$E$1048576,$D$20:$D$1048576,$M$4,$C$20:$C$1048576,A6) -> 0 | N6: =SUM(J6:M6) -> 0 | O6: =SUM(I6-N6) -> 0 | S6: TRANSF. S
A7: Femeas 13 a 24 meses | E7: =SUMIFS($E$20:$E$1048576,$D$20:$D$1048576,$E$4,$C$20:$C$1048576,A7) -> 0 | F7: =SUMIFS($E$20:$E$1048576,$D$20:$D$1048576,$F$4,$C$20:$C$1048576,B7) -> 0 | G7: =SUMIFS($E$20:$E$1048576,$D$20:$D$1048576,$G$4,$C$20:$C$1048576,A7) -> 0 | H7: =SUMIFS($E$20:$E$1048576,$D$20:$D$1048576,$H$4,$C$20:$C$1048576,A7) -> 0 | I7: =SUM(D7:H7) -> 0 | J7: =SUMIFS($E$20:$E$1048576,$D$20:$D$1048576,$J$4,$C$20:$C$1048576,A7) -> 0 | K7: =SUMIFS($E$20:$E$1048576,$D$20:$D$1048576,$K$4,$C$20:$C$1048576,A7) -> 0 | L7: =SUMIFS($E$20:$E$1048576,$D$20:$D$1048576,$L$4,$C$20:$C$1048576,A7) -> 0 | M7: =SUMIFS($E$20:$E$1048576,$D$20:$D$1048576,$M$4,$C$20:$C$1048576,A7) -> 0 | N7: =SUM(J7:M7) -> 0 | O7: =SUM(I7-N7) -> 0 | S7: SALDO ANTERIOR
A8: Femeas Desm. até 12m | E8: =SUMIFS($E$20:$E$1048576,$D$20:$D$1048576,$E$4,$C$20:$C$1048576,A8) -> 0 | F8: =SUMIFS($E$20:$E$1048576,$D$20:$D$1048576,$F$4,$C$20:$C$1048576,B8) -> 0 | G8: =SUMIFS($E$20:$E$1048576,$D$20:$D$1048576,$G$4,$C$20:$C$1048576,A8) -> 0 | H8: =SUMIFS($E$20:$E$1048576,$D$20:$D$1048576,$H$4,$C$20:$C$1048576,A8) -> 0 | I8: =SUM(D8:H8) -> 0 | J8: =SUMIFS($E$20:$E$1048576,$D$20:$D$1048576,$J$4,$C$20:$C$1048576,A8) -> 0 | K8: =SUMIFS($E$20:$E$1048576,$D$20:$D$1048576,$K$4,$C$20:$C$1048576,A8) -> 0 | L8: =SUMIFS($E$20:$E$1048576,$D$20:$D$1048576,$L$4,$C$20:$C$1048576,A8) -> 0 | M8: =SUMIFS($E$20:$E$1048576,$D$20:$D$1048576,$M$4,$C$20:$C$1048576,A8) -> 0 | N8: =SUM(J8:M8) -> 0 | O8: =SUM(I8-N8) -> 0 | S8: EVOLUÇ
A9: Bezerras Mamando | E9: =SUMIFS($E$20:$E$1048576,$D$20:$D$1048576,$E$4,$C$20:$C$1048576,A9) -> 0 | F9: =SUMIFS($E$20:$E$1048576,$D$20:$D$1048576,$F$4,$C$20:$C$1048576,B9) -> 0 | G9: =SUMIFS($E$20:$E$1048576,$D$20:$D$1048576,$G$4,$C$20:$C$1048576,A9) -> 0 | H9: =SUMIFS($E$20:$E$1048576,$D$20:$D$1048576,$H$4,$C$20:$C$1048576,A9) -> 0 | I9: =SUM(D9:H9) -> 0 | J9: =SUMIFS($E$20:$E$1048576,$D$20:$D$1048576,$J$4,$C$20:$C$1048576,A9) -> 0 | K9: =SUMIFS($E$20:$E$1048576,$D$20:$D$1048576,$K$4,$C$20:$C$1048576,A9) -> 0 | L9: =SUMIFS($E$20:$E$1048576,$D$20:$D$1048576,$L$4,$C$20:$C$1048576,A9) -> 0 | M9: =SUMIFS($E$20:$E$1048576,$D$20:$D$1048576,$M$4,$C$20:$C$1048576,A9) -> 0 | N9: =SUM(J9:M9) -> 0 | O9: =SUM(I9-N9) -> 0 | S9: VENDA
A10: Bezerros Mamando | E10: =SUMIFS($E$20:$E$1048576,$D$20:$D$1048576,$E$4,$C$20:$C$1048576,A10) -> 0 | F10: =SUMIFS($E$20:$E$1048576,$D$20:$D$1048576,$F$4,$C$20:$C$1048576,B10) -> 0 | G10: =SUMIFS($E$20:$E$1048576,$D$20:$D$1048576,$G$4,$C$20:$C$1048576,A10) -> 0 | H10: =SUMIFS($E$20:$E$1048576,$D$20:$D$1048576,$H$4,$C$20:$C$1048576,A10) -> 0 | I10: =SUM(D10:H10) -> 0 | J10: =SUMIFS($E$20:$E$1048576,$D$20:$D$1048576,$J$4,$C$20:$C$1048576,A10) -> 0 | K10: =SUMIFS($E$20:$E$1048576,$D$20:$D$1048576,$K$4,$C$20:$C$1048576,A10) -> 0 | L10: =SUMIFS($E$20:$E$1048576,$D$20:$D$1048576,$L$4,$C$20:$C$1048576,A10) -> 0 | M10: =SUMIFS($E$20:$E$1048576,$D$20:$D$1048576,$M$4,$C$20:$C$1048576,A10) -> 0 | N10: =SUM(J10:M10) -> 0 | O10: =SUM(I10-N10) -> 0
A11: Machos Desm. até 12m | E11: =SUMIFS($E$20:$E$1048576,$D$20:$D$1048576,$E$4,$C$20:$C$1048576,A11) -> 0 | F11: =SUMIFS($E$20:$E$1048576,$D$20:$D$1048576,$F$4,$C$20:$C$1048576,B11) -> 0 | G11: =SUMIFS($E$20:$E$1048576,$D$20:$D$1048576,$G$4,$C$20:$C$1048576,A11) -> 0 | H11: =SUMIFS($E$20:$E$1048576,$D$20:$D$1048576,$H$4,$C$20:$C$1048576,A11) -> 0 | I11: =SUM(D11:H11) -> 0 | J11: =SUMIFS($E$20:$E$1048576,$D$20:$D$1048576,$J$4,$C$20:$C$1048576,A11) -> 0 | K11: =SUMIFS($E$20:$E$1048576,$D$20:$D$1048576,$K$4,$C$20:$C$1048576,A11) -> 0 | L11: =SUMIFS($E$20:$E$1048576,$D$20:$D$1048576,$L$4,$C$20:$C$1048576,A11) -> 0 | M11: =SUMIFS($E$20:$E$1048576,$D$20:$D$1048576,$M$4,$C$20:$C$1048576,A11) -> 0 | N11: =SUM(J11:M11) -> 0 | O11: =SUM(I11-N11) -> 0
A12: Machos 13 a 24 meses | E12: =SUMIFS($E$20:$E$1048576,$D$20:$D$1048576,$E$4,$C$20:$C$1048576,A12) -> 0 | F12: =SUMIFS($E$20:$E$1048576,$D$20:$D$1048576,$F$4,$C$20:$C$1048576,B12) -> 0 | G12: =SUMIFS($E$20:$E$1048576,$D$20:$D$1048576,$G$4,$C$20:$C$1048576,A12) -> 0 | H12: =SUMIFS($E$20:$E$1048576,$D$20:$D$1048576,$H$4,$C$20:$C$1048576,A12) -> 0 | I12: =SUM(D12:H12) -> 0 | J12: =SUMIFS($E$20:$E$1048576,$D$20:$D$1048576,$J$4,$C$20:$C$1048576,A12) -> 0 | K12: =SUMIFS($E$20:$E$1048576,$D$20:$D$1048576,$K$4,$C$20:$C$1048576,A12) -> 0 | L12: =SUMIFS($E$20:$E$1048576,$D$20:$D$1048576,$L$4,$C$20:$C$1048576,A12) -> 0 | M12: =SUMIFS($E$20:$E$1048576,$D$20:$D$1048576,$M$4,$C$20:$C$1048576,A12) -> 0 | N12: =SUM(J12:M12) -> 0 | O12: =SUM(I12-N12) -> 0
A13: Machos 25 a 36 meses | E13: =SUMIFS($E$20:$E$1048576,$D$20:$D$1048576,$E$4,$C$20:$C$1048576,A13) -> 0 | F13: =SUMIFS($E$20:$E$1048576,$D$20:$D$1048576,$F$4,$C$20:$C$1048576,B13) -> 0 | G13: =SUMIFS($E$20:$E$1048576,$D$20:$D$1048576,$G$4,$C$20:$C$1048576,A13) -> 0 | H13: =SUMIFS($E$20:$E$1048576,$D$20:$D$1048576,$H$4,$C$20:$C$1048576,A13) -> 0 | I13: =SUM(D13:H13) -> 0 | J13: =SUMIFS($E$20:$E$1048576,$D$20:$D$1048576,$J$4,$C$20:$C$1048576,A13) -> 0 | K13: =SUMIFS($E$20:$E$1048576,$D$20:$D$1048576,$K$4,$C$20:$C$1048576,A13) -> 0 | L13: =SUMIFS($E$20:$E$1048576,$D$20:$D$1048576,$L$4,$C$20:$C$1048576,A13) -> 0 | M13: =SUMIFS($E$20:$E$1048576,$D$20:$D$1048576,$M$4,$C$20:$C$1048576,A13) -> 0 | N13: =SUM(J13:M13) -> 0 | O13: =SUM(I13-N13) -> 0
A14: Touros | E14: =SUMIFS($E$20:$E$1048576,$D$20:$D$1048576,$E$4,$C$20:$C$1048576,A14) -> 0 | F14: =SUMIFS($E$20:$E$1048576,$D$20:$D$1048576,$F$4,$C$20:$C$1048576,B14) -> 0 | G14: =SUMIFS($E$20:$E$1048576,$D$20:$D$1048576,$G$4,$C$20:$C$1048576,A14) -> 0 | H14: =SUMIFS($E$20:$E$1048576,$D$20:$D$1048576,$H$4,$C$20:$C$1048576,A14) -> 0 | I14: =SUM(D14:H14) -> 0 | J14: =SUMIFS($E$20:$E$1048576,$D$20:$D$1048576,$J$4,$C$20:$C$1048576,A14) -> 0 | K14: =SUMIFS($E$20:$E$1048576,$D$20:$D$1048576,$K$4,$C$20:$C$1048576,A14) -> 0 | L14: =SUMIFS($E$20:$E$1048576,$D$20:$D$1048576,$L$4,$C$20:$C$1048576,A14) -> 0 | M14: =SUMIFS($E$20:$E$1048576,$D$20:$D$1048576,$M$4,$C$20:$C$1048576,A14) -> 0 | N14: =SUM(J14:M14) -> 0 | O14: =SUM(I14-N14) -> 0
A15: TROPA | E15: =SUMIFS($E$20:$E$1048576,$D$20:$D$1048576,$E$4,$C$20:$C$1048576,A15) -> 0 | F15: 0 | G15: =SUMIFS($E$20:$E$1048576,$D$20:$D$1048576,$G$4,$C$20:$C$1048576,A15) -> 0 | H15: =SUMIFS($E$20:$E$1048576,$D$20:$D$1048576,$H$4,$C$20:$C$1048576,A15) -> 0 | I15: =SUM(D15:H15) -> 0 | J15: =SUMIFS($E$20:$E$1048576,$D$20:$D$1048576,$J$4,$C$20:$C$1048576,A15) -> 0 | K15: =SUMIFS($E$20:$E$1048576,$D$20:$D$1048576,$K$4,$C$20:$C$1048576,A15) -> 0 | L15: =SUMIFS($E$20:$E$1048576,$D$20:$D$1048576,$L$4,$C$20:$C$1048576,A15) -> 0 | M15: =SUMIFS($E$20:$E$1048576,$D$20:$D$1048576,$M$4,$C$20:$C$1048576,A15) -> 0 | N15: =SUM(J15:M15) -> 0 | O15: =SUM(I15-N15) -> 0
A16: TOTAL | D16: =SUM(D5:D15) -> 0 | E16: =SUM(E5:E15) -> 0 | F16: =SUM(F5:F15) -> 0 | G16: =SUM(G5:G15) -> 0 | H16: =SUM(H5:H15) -> 0 | I16: =SUM(I5:I15) -> 0 | J16: =SUM(J5:J15) -> 0 | K16: =SUM(K5:K15) -> 0 | ... O16: =SUM(O5:O15) -> 0
A18: MOVIMENTAÇÕES DE BOVINOS
A19: DATA | B19: MÊS | C19: CATEGORIA | D19: TIPO | E19: QUANTIDADE | F19: SAIDA | G19: DESTINO | H19: PESO TOTAL | I19: PESO MÉDIO
B20: =TEXT(Tabela22345[[#This Row],[DATA]],"mmm") -> jan | I20: =Tabela22[[#This Row],[PESO TOTAL]]/Tabela22[[#This Row],[QUANTIDADE]] -> #VALUE!
B21: =TEXT(Tabela22345[[#This Row],[DATA]],"mmm") -> jan | I21: =Tabela22[[#This Row],[PESO TOTAL]]/Tabela22[[#This Row],[QUANTIDADE]] -> 0
B22: =TEXT(Tabela22345[[#This Row],[DATA]],"mmm") -> jan | I22: =Tabela22[[#This Row],[PESO TOTAL]]/Tabela22[[#This Row],[QUANTIDADE]] -> #DIV/0!
B23: =TEXT(Tabela22345[[#This Row],[DATA]],"mmm") -> jan | I23: =Tabela22[[#This Row],[PESO TOTAL]]/Tabela22[[#This Row],[QUANTIDADE]] -> #DIV/0!
B24: =TEXT(Tabela22345[[#This Row],[DATA]],"mmm") -> jan | I24: =Tabela22[[#This Row],[PESO TOTAL]]/Tabela22[[#This Row],[QUANTIDADE]] -> #DIV/0!
B25: =TEXT(Tabela22345[[#This Row],[DATA]],"mmm") -> jan | I25: =Tabela22[[#This Row],[PESO TOTAL]]/Tabela22[[#This Row],[QUANTIDADE]] -> #DIV/0!
B26: =TEXT(Tabela22345[[#This Row],[DATA]],"mmm") -> jan | I26: =Tabela22[[#This Row],[PESO TOTAL]]/Tabela22[[#This Row],[QUANTIDADE]] -> #DIV/0!
B27: =TEXT(Tabela22345[[#This Row],[DATA]],"mmmm") -> janeiro | I27: =Tabela22[[#This Row],[PESO TOTAL]]/Tabela22[[#This Row],[QUANTIDADE]] -> #DIV/0!
B28: =TEXT(Tabela22345[[#This Row],[DATA]],"mmmm") -> janeiro | I28: =Tabela22[[#This Row],[PESO TOTAL]]/Tabela22[[#This Row],[QUANTIDADE]] -> #DIV/0!
B29: =TEXT(Tabela22345[[#This Row],[DATA]],"mmmm") -> janeiro | I29: =Tabela22[[#This Row],[PESO TOTAL]]/Tabela22[[#This Row],[QUANTIDADE]] -> #DIV/0!
B30: =TEXT(Tabela22345[[#This Row],[DATA]],"mmmm") -> janeiro | I30: =Tabela22[[#This Row],[PESO TOTAL]]/Tabela22[[#This Row],[QUANTIDADE]] -> #DIV/0!
B31: =TEXT(Tabela22345[[#This Row],[DATA]],"mmmm") -> janeiro | I31: =Tabela22[[#This Row],[PESO TOTAL]]/Tabela22[[#This Row],[QUANTIDADE]] -> #DIV/0!
B32: =TEXT(Tabela22345[[#This Row],[DATA]],"mmmm") -> janeiro | I32: =Tabela22[[#This Row],[PESO TOTAL]]/Tabela22[[#This Row],[QUANTIDADE]] -> #DIV/0!
B33: =TEXT(Tabela22345[[#This Row],[DATA]],"mmmm") -> janeiro | I33: =Tabela22[[#This Row],[PESO TOTAL]]/Tabela22[[#This Row],[QUANTIDADE]] -> #DIV/0!
B34: =TEXT(Tabela22345[[#This Row],[DATA]],"mmmm") -> janeiro | I34: =Tabela22[[#This Row],[PESO TOTAL]]/Tabela22[[#This Row],[QUANTIDADE]] -> #DIV/0!
B35: =TEXT(Tabela22345[[#This Row],[DATA]],"mmmm") -> janeiro | I35: =Tabela22[[#This Row],[PESO TOTAL]]/Tabela22[[#This Row],[QUANTIDADE]] -> #DIV/0!
B36: =TEXT(Tabela22345[[#This Row],[DATA]],"mmmm") -> janeiro | I36: =Tabela22[[#This Row],[PESO TOTAL]]/Tabela22[[#This Row],[QUANTIDADE]] -> #DIV/0!
B37: =TEXT(Tabela22345[[#This Row],[DATA]],"mmmm") -> janeiro | I37: =Tabela22[[#This Row],[PESO TOTAL]]/Tabela22[[#This Row],[QUANTIDADE]] -> #DIV/0!
B38: =TEXT(Tabela22345[[#This Row],[DATA]],"mmmm") -> janeiro | I38: =Tabela22[[#This Row],[PESO TOTAL]]/Tabela22[[#This Row],[QUANTIDADE]] -> #DIV/0!
... B571: =TEXT(Tabela22345[[#This Row],[DATA]],"mmmm") -> janeiro | I571: =Tabela22[[#This Row],[PESO TOTAL]]/Tabela22[[#This Row],[QUANTIDADE]] -> #DIV/0!

Sheet SAO JOSE DO GROTAO
A1: MOVIMENTAÇÃO FAZENDA SÃO JOSE DO GROTÃO | S1: COMPRA
D2: ENTRADAS | J2: SAIDAS | O2: POSIÇÃO | S2: NASC.
S3: TRANSF. E
A4: CATEGORIAS | D4: SALDO ANTERIOR | E4: COMPRA | F4: EVOLUÇ | G4: NASC. | H4: TRANSF. E | I4: TOTAL | J4: ABATE | K4: MORTE | L4: VENDA | M4: TRANSF. S | N4: TOTAL | O4: FINAL | S4: ABATE
A5: Femeas + 36 meses | E5: =SUMIFS($E$20:$E$1048576,$D$20:$D$1048576,$E$4,$C$20:$C$1048576,A5) -> 0 | F5: =SUMIFS($E$20:$E$1048576,$D$20:$D$1048576,$F$4,$C$20:$C$1048576,B5) -> 0 | G5: =SUMIFS($E$20:$E$1048576,$D$20:$D$1048576,$G$4,$C$20:$C$1048576,A5) -> 0 | H5: =SUMIFS($E$20:$E$1048576,$D$20:$D$1048576,$H$4,$C$20:$C$1048576,A5) -> 0 | I5: =SUM(D5:H5) -> 0 | J5: =SUMIFS($E$20:$E$1048576,$D$20:$D$1048576,$J$4,$C$20:$C$1048576,A5) -> 0 | K5: =SUMIFS($E$20:$E$1048576,$D$20:$D$1048576,$K$4,$C$20:$C$1048576,A5) -> 0 | L5: =SUMIFS($E$20:$E$1048576,$D$20:$D$1048576,$L$4,$C$20:$C$1048576,A5) -> 0 | M5: =SUMIFS($E$20:$E$1048576,$D$20:$D$1048576,$M$4,$C$20:$C$1048576,A5) -> 0 | N5: =SUM(J5:M5) -> 0 | O5: =SUM(I5-N5) -> 0 | S5: MORTE
A6: Femeas 25 a 36 meses | E6: =SUMIFS($E$20:$E$1048576,$D$20:$D$1048576,$E$4,$C$20:$C$1048576,A6) -> 0 | F6: =SUMIFS($E$20:$E$1048576,$D$20:$D$1048576,$F$4,$C$20:$C$1048576,B6) -> 0 | G6: =SUMIFS($E$20:$E$1048576,$D$20:$D$1048576,$G$4,$C$20:$C$1048576,A6) -> 0 | H6: =SUMIFS($E$20:$E$1048576,$D$20:$D$1048576,$H$4,$C$20:$C$1048576,A6) -> 0 | I6: =SUM(D6:H6) -> 0 | J6: =SUMIFS($E$20:$E$1048576,$D$20:$D$1048576,$J$4,$C$20:$C$1048576,A6) -> 0 | K6: =SUMIFS($E$20:$E$1048576,$D$20:$D$1048576,$K$4,$C$20:$C$1048576,A6) -> 0 | L6: =SUMIFS($E$20:$E$1048576,$D$20:$D$1048576,$L$4,$C$20:$C$1048576,A6) -> 0 | M6: =SUMIFS($E$20:$E$1048576,$D$20:$D$1048576,$M$4,$C$20:$C$1048576,A6) -> 0 | N6: =SUM(J6:M6) -> 0 | O6: =SUM(I6-N6) -> 0 | S6: TRANSF. S
A7: Femeas 13 a 24 meses | E7: =SUMIFS($E$20:$E$1048576,$D$20:$D$1048576,$E$4,$C$20:$C$1048576,A7) -> 0 | F7: =SUMIFS($E$20:$E$1048576,$D$20:$D$1048576,$F$4,$C$20:$C$1048576,B7) -> 0 | G7: =SUMIFS($E$20:$E$1048576,$D$20:$D$1048576,$G$4,$C$20:$C$1048576,A7) -> 0 | H7: =SUMIFS($E$20:$E$1048576,$D$20:$D$1048576,$H$4,$C$20:$C$1048576,A7) -> 0 | I7: =SUM(D7:H7) -> 0 | J7: =SUMIFS($E$20:$E$1048576,$D$20:$D$1048576,$J$4,$C$20:$C$1048576,A7) -> 0 | K7: =SUMIFS($E$20:$E$1048576,$D$20:$D$1048576,$K$4,$C$20:$C$1048576,A7) -> 0 | L7: =SUMIFS($E$20:$E$1048576,$D$20:$D$1048576,$L$4,$C$20:$C$1048576,A7) -> 0 | M7: =SUMIFS($E$20:$E$1048576,$D$20:$D$1048576,$M$4,$C$20:$C$1048576,A7) -> 0 | N7: =SUM(J7:M7) -> 0 | O7: =SUM(I7-N7) -> 0 | S7: SALDO ANTERIOR
A8: Femeas Desm. até 12m | E8: =SUMIFS($E$20:$E$1048576,$D$20:$D$1048576,$E$4,$C$20:$C$1048576,A8) -> 0 | F8: =SUMIFS($E$20:$E$1048576,$D$20:$D$1048576,$F$4,$C$20:$C$1048576,B8) -> 0 | G8: =SUMIFS($E$20:$E$1048576,$D$20:$D$1048576,$G$4,$C$20:$C$1048576,A8) -> 0 | H8: =SUMIFS($E$20:$E$1048576,$D$20:$D$1048576,$H$4,$C$20:$C$1048576,A8) -> 0 | I8: =SUM(D8:H8) -> 0 | J8: =SUMIFS($E$20:$E$1048576,$D$20:$D$1048576,$J$4,$C$20:$C$1048576,A8) -> 0 | K8: =SUMIFS($E$20:$E$1048576,$D$20:$D$1048576,$K$4,$C$20:$C$1048576,A8) -> 0 | L8: =SUMIFS($E$20:$E$1048576,$D$20:$D$1048576,$L$4,$C$20:$C$1048576,A8) -> 0 | M8: =SUMIFS($E$20:$E$1048576,$D$20:$D$1048576,$M$4,$C$20:$C$1048576,A8) -> 0 | N8: =SUM(J8:M8) -> 0 | O8: =SUM(I8-N8) -> 0 | S8: EVOLUÇ
A9: Bezerras Mamando | E9: =SUMIFS($E$20:$E$1048576,$D$20:$D$1048576,$E$4,$C$20:$C$1048576,A9) -> 0 | F9: =SUMIFS($E$20:$E$1048576,$D$20:$D$1048576,$F$4,$C$20:$C$1048576,B9) -> 0 | G9: =SUMIFS($E$20:$E$1048576,$D$20:$D$1048576,$G$4,$C$20:$C$1048576,A9) -> 0 | H9: =SUMIFS($E$20:$E$1048576,$D$20:$D$1048576,$H$4,$C$20:$C$1048576,A9) -> 0 | I9: =SUM(D9:H9) -> 0 | J9: =SUMIFS($E$20:$E$1048576,$D$20:$D$1048576,$J$4,$C$20:$C$1048576,A9) -> 0 | K9: =SUMIFS($E$20:$E$1048576,$D$20:$D$1048576,$K$4,$C$20:$C$1048576,A9) -> 0 | L9: =SUMIFS($E$20:$E$1048576,$D$20:$D$1048576,$L$4,$C$20:$C$1048576,A9) -> 0 | M9: =SUMIFS($E$20:$E$1048576,$D$20:$D$1048576,$M$4,$C$20:$C$1048576,A9) -> 0 | N9: =SUM(J9:M9) -> 0 | O9: =SUM(I9-N9) -> 0 | S9: VENDA
A10: Bezerros Mamando | E10: =SUMIFS($E$20:$E$1048576,$D$20:$D$1048576,$E$4,$C$20:$C$1048576,A10) -> 0 | F10: =SUMIFS($E$20:$E$1048576,$D$20:$D$1048576,$F$4,$C$20:$C$1048576,B10) -> 0 | G10: =SUMIFS($E$20:$E$1048576,$D$20:$D$1048576,$G$4,$C$20:$C$1048576,A10) -> 0 | H10: =SUMIFS($E$20:$E$1048576,$D$20:$D$1048576,$H$4,$C$20:$C$1048576,A10) -> 0 | I10: =SUM(D10:H10) -> 0 | J10: =SUMIFS($E$20:$E$1048576,$D$20:$D$1048576,$J$4,$C$20:$C$1048576,A10) -> 0 | K10: =SUMIFS($E$20:$E$1048576,$D$20:$D$1048576,$K$4,$C$20:$C$1048576,A10) -> 0 | L10: =SUMIFS($E$20:$E$1048576,$D$20:$D$1048576,$L$4,$C$20:$C$1048576,A10) -> 0 | M10: =SUMIFS($E$20:$E$1048576,$D$20:$D$1048576,$M$4,$C$20:$C$1048576,A10) -> 0 | N10: =SUM(J10:M10) -> 0 | O10: =SUM(I10-N10) -> 0
A11: Machos Desm. até 12m | E11: =SUMIFS($E$20:$E$1048576,$D$20:$D$1048576,$E$4,$C$20:$C$1048576,A11) -> 0 | F11: =SUMIFS($E$20:$E$1048576,$D$20:$D$1048576,$F$4,$C$20:$C$1048576,B11) -> 0 | G11: =SUMIFS($E$20:$E$1048576,$D$20:$D$1048576,$G$4,$C$20:$C$1048576,A11) -> 0 | H11: =SUMIFS($E$20:$E$1048576,$D$20:$D$1048576,$H$4,$C$20:$C$1048576,A11) -> 0 | I11: =SUM(D11:H11) -> 0 | J11: =SUMIFS($E$20:$E$1048576,$D$20:$D$1048576,$J$4,$C$20:$C$1048576,A11) -> 0 | K11: =SUMIFS($E$20:$E$1048576,$D$20:$D$1048576,$K$4,$C$20:$C$1048576,A11) -> 0 | L11: =SUMIFS($E$20:$E$1048576,$D$20:$D$1048576,$L$4,$C$20:$C$1048576,A11) -> 0 | M11: =SUMIFS($E$20:$E$1048576,$D$20:$D$1048576,$M$4,$C$20:$C$1048576,A11) -> 0 | N11: =SUM(J11:M11) -> 0 | O11: =SUM(I11-N11) -> 0
A12: Machos 13 a 24 meses | E12: =SUMIFS($E$20:$E$1048576,$D$20:$D$1048576,$E$4,$C$20:$C$1048576,A12) -> 0 | F12: =SUMIFS($E$20:$E$1048576,$D$20:$D$1048576,$F$4,$C$20:$C$1048576,B12) -> 0 | G12: =SUMIFS($E$20:$E$1048576,$D$20:$D$1048576,$G$4,$C$20:$C$1048576,A12) -> 0 | H12: =SUMIFS($E$20:$E$1048576,$D$20:$D$1048576,$H$4,$C$20:$C$1048576,A12) -> 0 | I12: =SUM(D12:H12) -> 0 | J12: =SUMIFS($E$20:$E$1048576,$D$20:$D$1048576,$J$4,$C$20:$C$1048576,A12) -> 0 | K12: =SUMIFS($E$20:$E$1048576,$D$20:$D$1048576,$K$4,$C$20:$C$1048576,A12) -> 0 | L12: =SUMIFS($E$20:$E$1048576,$D$20:$D$1048576,$L$4,$C$20:$C$1048576,A12) -> 0 | M12: =SUMIFS($E$20:$E$1048576,$D$20:$D$1048576,$M$4,$C$20:$C$1048576,A12) -> 0 | N12: =SUM(J12:M12) -> 0 | O12: =SUM(I12-N12) -> 0
A13: Machos 25 a 36 meses | E13: =SUMIFS($E$20:$E$1048576,$D$20:$D$1048576,$E$4,$C$20:$C$1048576,A13) -> 0 | F13: =SUMIFS($E$20:$E$1048576,$D$20:$D$1048576,$F$4,$C$20:$C$1048576,B13) -> 0 | G13: =SUMIFS($E$20:$E$1048576,$D$20:$D$1048576,$G$4,$C$20:$C$1048576,A13) -> 0 | H13: =SUMIFS($E$20:$E$1048576,$D$20:$D$1048576,$H$4,$C$20:$C$1048576,A13) -> 0 | I13: =SUM(D13:H13) -> 0 | J13: =SUMIFS($E$20:$E$1048576,$D$20:$D$1048576,$J$4,$C$20:$C$1048576,A13) -> 0 | K13: =SUMIFS($E$20:$E$1048576,$D$20:$D$1048576,$K$4,$C$20:$C$1048576,A13) -> 0 | L13: =SUMIFS($E$20:$E$1048576,$D$20:$D$1048576,$L$4,$C$20:$C$1048576,A13) -> 0 | M13: =SUMIFS($E$20:$E$1048576,$D$20:$D$1048576,$M$4,$C$20:$C$1048576,A13) -> 0 | N13: =SUM(J13:M13) -> 0 | O13: =SUM(I13-N13) -> 0
A14: Touros | E14: =SUMIFS($E$20:$E$1048576,$D$20:$D$1048576,$E$4,$C$20:$C$1048576,A14) -> 0 | F14: =SUMIFS($E$20:$E$1048576,$D$20:$D$1048576,$F$4,$C$20:$C$1048576,B14) -> 0 | G14: =SUMIFS($E$20:$E$1048576,$D$20:$D$1048576,$G$4,$C$20:$C$1048576,A14) -> 0 | H14: =SUMIFS($E$20:$E$1048576,$D$20:$D$1048576,$H$4,$C$20:$C$1048576,A14) -> 0 | I14: =SUM(D14:H14) -> 0 | J14: =SUMIFS($E$20:$E$1048576,$D$20:$D$1048576,$J$4,$C$20:$C$1048576,A14) -> 0 | K14: =SUMIFS($E$20:$E$1048576,$D$20:$D$1048576,$K$4,$C$20:$C$1048576,A14) -> 0 | L14: =SUMIFS($E$20:$E$1048576,$D$20:$D$1048576,$L$4,$C$20:$C$1048576,A14) -> 0 | M14: =SUMIFS($E$20:$E$1048576,$D$20:$D$1048576,$M$4,$C$20:$C$1048576,A14) -> 0 | N14: =SUM(J14:M14) -> 0 | O14: =SUM(I14-N14) -> 0
A15: TROPA | E15: =SUMIFS($E$20:$E$1048576,$D$20:$D$1048576,$E$4,$C$20:$C$1048576,A15) -> 0 | G15: =SUMIFS($E$20:$E$1048576,$D$20:$D$1048576,$G$4,$C$20:$C$1048576,A15) -> 0 | H15: =SUMIFS($E$20:$E$1048576,$D$20:$D$1048576,$H$4,$C$20:$C$1048576,A15) -> 0 | I15: =SUM(D15:H15) -> 0 | J15: =SUMIFS($E$20:$E$1048576,$D$20:$D$1048576,$J$4,$C$20:$C$1048576,A15) -> 0 | K15: =SUMIFS($E$20:$E$1048576,$D$20:$D$1048576,$K$4,$C$20:$C$1048576,A15) -> 0 | L15: =SUMIFS($E$20:$E$1048576,$D$20:$D$1048576,$L$4,$C$20:$C$1048576,A15) -> 0 | M15: =SUMIFS($E$20:$E$1048576,$D$20:$D$1048576,$M$4,$C$20:$C$1048576,A15) -> 0 | N15: =SUM(J15:M15) -> 0 | O15: =SUM(I15-N15) -> 0
A16: TOTAL | D16: =SUM(D5:D15) -> 0 | E16: =SUM(E5:E15) -> 0 | F16: =SUM(F5:F15) -> 0 | G16: =SUM(G5:G15) -> 0 | H16: =SUM(H5:H15) -> 0 | I16: =SUM(I5:I15) -> 0 | J16: =SUM(J5:J15) -> 0 | K16: =SUM(K5:K15) -> 0 | ... M16: =SUM(M5:M15) -> 0 | N16: =SUM(J16:M16) -> 0 | O16: =SUM(O5:O14) -> 0
A18: MOVIMENTAÇÕES DE BOVINOS
A19: DATA | B19: MÊS | C19: CATEGORIA | D19: TIPO | E19: QUANTIDADE | F19: SAIDA | G19: DESTINO | H19: PESO TOTAL | I19: PESO MÉDIO
B20: =TEXT(Tabela223456[[#This Row],[DATA]],"mmm") -> jan | I20: =Tabela22[[#This Row],[PESO TOTAL]]/Tabela22[[#This Row],[QUANTIDADE]] -> #VALUE!
B21: =TEXT(Tabela223456[[#This Row],[DATA]],"mmm") -> jan | I21: =Tabela22[[#This Row],[PESO TOTAL]]/Tabela22[[#This Row],[QUANTIDADE]] -> 0
B22: =TEXT(Tabela223456[[#This Row],[DATA]],"mmm") -> jan | I22: =Tabela22[[#This Row],[PESO TOTAL]]/Tabela22[[#This Row],[QUANTIDADE]] -> #DIV/0!
B23: =TEXT(Tabela223456[[#This Row],[DATA]],"mmm") -> jan | I23: =Tabela22[[#This Row],[PESO TOTAL]]/Tabela22[[#This Row],[QUANTIDADE]] -> #DIV/0!
B24: =TEXT(Tabela223456[[#This Row],[DATA]],"mmm") -> jan | I24: =Tabela22[[#This Row],[PESO TOTAL]]/Tabela22[[#This Row],[QUANTIDADE]] -> #DIV/0!
B25: =TEXT(Tabela223456[[#This Row],[DATA]],"mmm") -> jan | I25: =Tabela22[[#This Row],[PESO TOTAL]]/Tabela22[[#This Row],[QUANTIDADE]] -> #DIV/0!
B26: =TEXT(Tabela223456[[#This Row],[DATA]],"mmm") -> jan | I26: =Tabela22[[#This Row],[PESO TOTAL]]/Tabela22[[#This Row],[QUANTIDADE]] -> #DIV/0!
B27: =TEXT(Tabela223456[[#This Row],[DATA]],"mmm") -> jan | I27: =Tabela22[[#This Row],[PESO TOTAL]]/Tabela22[[#This Row],[QUANTIDADE]] -> #DIV/0!
B28: =TEXT(Tabela223456[[#This Row],[DATA]],"mmmm") -> janeiro | I28: =Tabela22[[#This Row],[PESO TOTAL]]/Tabela22[[#This Row],[QUANTIDADE]] -> #DIV/0!
B29: =TEXT(Tabela223456[[#This Row],[DATA]],"mmmm") -> janeiro | I29: =Tabela22[[#This Row],[PESO TOTAL]]/Tabela22[[#This Row],[QUANTIDADE]] -> #DIV/0!
B30: =TEXT(Tabela223456[[#This Row],[DATA]],"mmmm") -> janeiro | I30: =Tabela22[[#This Row],[PESO TOTAL]]/Tabela22[[#This Row],[QUANTIDADE]] -> #DIV/0!
B31: =TEXT(Tabela223456[[#This Row],[DATA]],"mmmm") -> janeiro | I31: =Tabela22[[#This Row],[PESO TOTAL]]/Tabela22[[#This Row],[QUANTIDADE]] -> #DIV/0!
B32: =TEXT(Tabela223456[[#This Row],[DATA]],"mmmm") -> janeiro | I32: =Tabela22[[#This Row],[PESO TOTAL]]/Tabela22[[#This Row],[QUANTIDADE]] -> #DIV/0!
B33: =TEXT(Tabela223456[[#This Row],[DATA]],"mmmm") -> janeiro | I33: =Tabela22[[#This Row],[PESO TOTAL]]/Tabela22[[#This Row],[QUANTIDADE]] -> #DIV/0!
B34: =TEXT(Tabela223456[[#This Row],[DATA]],"mmmm") -> janeiro | I34: =SUM(Tabela223456[[#This Row],[PESO TOTAL]]/Tabela223456[[#This Row],[QUANTIDADE]]) -> #DIV/0!
B35: =TEXT(Tabela223456[[#This Row],[DATA]],"mmmm") -> janeiro | I35: =Tabela22[[#This Row],[PESO TOTAL]]/Tabela22[[#This Row],[QUANTIDADE]] -> #DIV/0!
B36: =TEXT(Tabela223456[[#This Row],[DATA]],"mmmm") -> janeiro | I36: =Tabela22[[#This Row],[PESO TOTAL]]/Tabela22[[#This Row],[QUANTIDADE]] -> #DIV/0!
B37: =TEXT(Tabela223456[[#This Row],[DATA]],"mmmm") -> janeiro | I37: =Tabela22[[#This Row],[PESO TOTAL]]/Tabela22[[#This Row],[QUANTIDADE]] -> #DIV/0!
B38: =TEXT(Tabela223456[[#This Row],[DATA]],"mmmm") -> janeiro | I38: =Tabela22[[#This Row],[PESO TOTAL]]/Tabela22[[#This Row],[QUANTIDADE]] -> #DIV/0!
B39: =TEXT(Tabela223456[[#This Row],[DATA]],"mmmm") -> janeiro | I39: =Tabela22[[#This Row],[PESO TOTAL]]/Tabela22[[#This Row],[QUANTIDADE]] -> #DIV/0!
B40: =TEXT(Tabela223456[[#This Row],[DATA]],"mmmm") -> janeiro | I40: =Tabela22[[#This Row],[PESO TOTAL]]/Tabela22[[#This Row],[QUANTIDADE]] -> #DIV/0!
B41: =TEXT(Tabela223456[[#This Row],[DATA]],"mmmm") -> janeiro | I41: =Tabela22[[#This Row],[PESO TOTAL]]/Tabela22[[#This Row],[QUANTIDADE]] -> #DIV/0!
B42: =TEXT(Tabela223456[[#This Row],[DATA]],"mmmm") -> janeiro | I42: =Tabela22[[#This Row],[PESO TOTAL]]/Tabela22[[#This Row],[QUANTIDADE]] -> #DIV/0!
B43: =TEXT(Tabela223456[[#This Row],[DATA]],"mmmm") -> janeiro | I43: =Tabela22[[#This Row],[PESO TOTAL]]/Tabela22[[#This Row],[QUANTIDADE]] -> #DIV/0!
B44: =TEXT(Tabela223456[[#This Row],[DATA]],"mmmm") -> janeiro | I44: =Tabela22[[#This Row],[PESO TOTAL]]/Tabela22[[#This Row],[QUANTIDADE]] -> #DIV/0!
B45: =TEXT(Tabela223456[[#This Row],[DATA]],"mmmm") -> janeiro | I45: =Tabela22[[#This Row],[PESO TOTAL]]/Tabela22[[#This Row],[QUANTIDADE]] -> #DIV/0!
B46: =TEXT(Tabela223456[[#This Row],[DATA]],"mmmm") -> janeiro | I46: =Tabela22[[#This Row],[PESO TOTAL]]/Tabela22[[#This Row],[QUANTIDADE]] -> #DIV/0!
... B572: =TEXT(Tabela223456[[#This Row],[DATA]],"mmmm") -> janeiro | I572: =Tabela22[[#This Row],[PESO TOTAL]]/Tabela22[[#This Row],[QUANTIDADE]] -> #DIV/0!

Sheet GERAL
A1: MOVIMENTAÇÃO GERAL DO REBANHO | S1: COMPRA
D2: ENTRADAS | J2: SAIDAS | O2: POSIÇÃO | S2: NASC.
S3: TRANSF. E
A4: CATEGORIAS | D4: SALDO ANTERIOR | E4: COMPRA | F4: EVOLUÇ | G4: NASC. | H4: TRANSF. E | I4: TOTAL | J4: ABATE | K4: MORTE | L4: VENDA | M4: TRANSF. S | N4: TOTAL | O4: FINAL | S4: ABATE
A5: Femeas + 36 meses | D5: =SUM('GOIANO:SAO JOSE DO GROTAO'!D5) -> 0 | E5: =SUM('GOIANO:SAO JOSE DO GROTAO'!E5) -> 0 | F5: =SUM('GOIANO:SAO JOSE DO GROTAO'!F5) -> 0 | G5: =SUM('GOIANO:SAO JOSE DO GROTAO'!G5) -> 0 | H5: =SUM('GOIANO:SAO JOSE DO GROTAO'!H5) -> 0 | I5: =SUM('GOIANO:SAO JOSE DO GROTAO'!I5) -> 0 | J5: =SUM('GOIANO:SAO JOSE DO GROTAO'!J5) -> 0 | K5: =SUM('GOIANO:SAO JOSE DO GROTAO'!K5) -> 0 | ... O5: =SUM('GOIANO:SAO JOSE DO GROTAO'!O5) -> 0 | S5: MORTE
A6: Femeas 25 a 36 meses | D6: =SUM('GOIANO:SAO JOSE DO GROTAO'!D6) -> 0 | E6: =SUM('GOIANO:SAO JOSE DO GROTAO'!E6) -> 0 | F6: =SUM('GOIANO:SAO JOSE DO GROTAO'!F6) -> 0 | G6: =SUM('GOIANO:SAO JOSE DO GROTAO'!G6) -> 0 | H6: =SUM('GOIANO:SAO JOSE DO GROTAO'!H6) -> 0 | I6: =SUM('GOIANO:SAO JOSE DO GROTAO'!I6) -> 0 | J6: =SUM('GOIANO:SAO JOSE DO GROTAO'!J6) -> 0 | K6: =SUM('GOIANO:SAO JOSE DO GROTAO'!K6) -> 0 | ... O6: =SUM('GOIANO:SAO JOSE DO GROTAO'!O6) -> 0 | S6: TRANSF. S
A7: Femeas 13 a 24 meses | D7: =SUM('GOIANO:SAO JOSE DO GROTAO'!D7) -> 0 | E7: =SUM('GOIANO:SAO JOSE DO GROTAO'!E7) -> 0 | F7: =SUM('GOIANO:SAO JOSE DO GROTAO'!F7) -> 0 | G7: =SUM('GOIANO:SAO JOSE DO GROTAO'!G7) -> 0 | H7: =SUM('GOIANO:SAO JOSE DO GROTAO'!H7) -> 0 | I7: =SUM('GOIANO:SAO JOSE DO GROTAO'!I7) -> 0 | J7: =SUM('GOIANO:SAO JOSE DO GROTAO'!J7) -> 0 | K7: =SUM('GOIANO:SAO JOSE DO GROTAO'!K7) -> 0 | ... O7: =SUM('GOIANO:SAO JOSE DO GROTAO'!O7) -> 0 | S7: SALDO ANTERIOR
A8: Femeas Desm. até 12m | D8: =SUM('GOIANO:SAO JOSE DO GROTAO'!D8) -> 0 | E8: =SUM('GOIANO:SAO JOSE DO GROTAO'!E8) -> 0 | F8: =SUM('GOIANO:SAO JOSE DO GROTAO'!F8) -> 0 | G8: =SUM('GOIANO:SAO JOSE DO GROTAO'!G8) -> 0 | H8: =SUM('GOIANO:SAO JOSE DO GROTAO'!H8) -> 0 | I8: =SUM('GOIANO:SAO JOSE DO GROTAO'!I8) -> 0 | J8: =SUM('GOIANO:SAO JOSE DO GROTAO'!J8) -> 0 | K8: =SUM('GOIANO:SAO JOSE DO GROTAO'!K8) -> 0 | ... O8: =SUM('GOIANO:SAO JOSE DO GROTAO'!O8) -> 0 | S8: EVOLUÇ
A9: Bezerras Mamando | D9: =SUM('GOIANO:SAO JOSE DO GROTAO'!D9) -> 0 | E9: =SUM('GOIANO:SAO JOSE DO GROTAO'!E9) -> 0 | F9: =SUM('GOIANO:SAO JOSE DO GROTAO'!F9) -> 0 | G9: =SUM('GOIANO:SAO JOSE DO GROTAO'!G9) -> 0 | H9: =SUM('GOIANO:SAO JOSE DO GROTAO'!H9) -> 0 | I9: =SUM('GOIANO:SAO JOSE DO GROTAO'!I9) -> 0 | J9: =SUM('GOIANO:SAO JOSE DO GROTAO'!J9) -> 0 | K9: =SUM('GOIANO:SAO JOSE DO GROTAO'!K9) -> 0 | ... O9: =SUM('GOIANO:SAO JOSE DO GROTAO'!O9) -> 0 | S9: VENDA
A10: Bezerros Mamando | D10: =SUM('GOIANO:SAO JOSE DO GROTAO'!D10) -> 0 | E10: =SUM('GOIANO:SAO JOSE DO GROTAO'!E10) -> 0 | F10: =SUM('GOIANO:SAO JOSE DO GROTAO'!F10) -> 0 | G10: =SUM('GOIANO:SAO JOSE DO GROTAO'!G10) -> 0 | H10: =SUM('GOIANO:SAO JOSE DO GROTAO'!H10) -> 0 | I10: =SUM('GOIANO:SAO JOSE DO GROTAO'!I10) -> 0 | J10: =SUM('GOIANO:SAO JOSE DO GROTAO'!J10) -> 0 | K10: =SUM('GOIANO:SAO JOSE DO GROTAO'!K10) -> 0 | ... O10: =SUM('GOIANO:SAO JOSE DO GROTAO'!O10) -> 0
A11: Machos Desm. até 12m | D11: =SUM('GOIANO:SAO JOSE DO GROTAO'!D11) -> 0 | E11: =SUM('GOIANO:SAO JOSE DO GROTAO'!E11) -> 0 | F11: =SUM('GOIANO:SAO JOSE DO GROTAO'!F11) -> 0 | G11: =SUM('GOIANO:SAO JOSE DO GROTAO'!G11) -> 0 | H11: =SUM('GOIANO:SAO JOSE DO GROTAO'!H11) -> 0 | I11: =SUM('GOIANO:SAO JOSE DO GROTAO'!I11) -> 0 | J11: =SUM('GOIANO:SAO JOSE DO GROTAO'!J11) -> 0 | K11: =SUM('GOIANO:SAO JOSE DO GROTAO'!K11) -> 0 | ... O11: =SUM('GOIANO:SAO JOSE DO GROTAO'!O11) -> -140
A12: Machos 13 a 24 meses | D12: =SUM('GOIANO:SAO JOSE DO GROTAO'!D12) -> 0 | E12: =SUM('GOIANO:SAO JOSE DO GROTAO'!E12) -> 0 | F12: =SUM('GOIANO:SAO JOSE DO GROTAO'!F12) -> 0 | G12: =SUM('GOIANO:SAO JOSE DO GROTAO'!G12) -> 0 | H12: =SUM('GOIANO:SAO JOSE DO GROTAO'!H12) -> 0 | I12: =SUM('GOIANO:SAO JOSE DO GROTAO'!I12) -> 0 | J12: =SUM('GOIANO:SAO JOSE DO GROTAO'!J12) -> 0 | K12: =SUM('GOIANO:SAO JOSE DO GROTAO'!K12) -> 0 | ... O12: =SUM('GOIANO:SAO JOSE DO GROTAO'!O12) -> 0
A13: Machos 25 a 36 meses | D13: =SUM('GOIANO:SAO JOSE DO GROTAO'!D13) -> 0 | E13: =SUM('GOIANO:SAO JOSE DO GROTAO'!E13) -> 0 | F13: =SUM('GOIANO:SAO JOSE DO GROTAO'!F13) -> 0 | G13: =SUM('GOIANO:SAO JOSE DO GROTAO'!G13) -> 0 | H13: =SUM('GOIANO:SAO JOSE DO GROTAO'!H13) -> 0 | I13: =SUM('GOIANO:SAO JOSE DO GROTAO'!I13) -> 0 | J13: =SUM('GOIANO:SAO JOSE DO GROTAO'!J13) -> 0 | K13: =SUM('GOIANO:SAO JOSE DO GROTAO'!K13) -> 0 | ... O13: =SUM('GOIANO:SAO JOSE DO GROTAO'!O13) -> 0
A14: Touros | D14: =SUM('GOIANO:SAO JOSE DO GROTAO'!D14) -> 0 | E14: =SUM('GOIANO:SAO JOSE DO GROTAO'!E14) -> 0 | F14: =SUM('GOIANO:SAO JOSE DO GROTAO'!F14) -> 0 | G14: =SUM('GOIANO:SAO JOSE DO GROTAO'!G14) -> 0 | H14: =SUM('GOIANO:SAO JOSE DO GROTAO'!H14) -> 0 | I14: =SUM('GOIANO:SAO JOSE DO GROTAO'!I14) -> 0 | J14: =SUM('GOIANO:SAO JOSE DO GROTAO'!J14) -> 0 | K14: =SUM('GOIANO:SAO JOSE DO GROTAO'!K14) -> 0 | ... O14: =SUM('GOIANO:SAO JOSE DO GROTAO'!O14) -> 0
A15: TROPAS | D15: =SUM('GOIANO:SAO JOSE DO GROTAO'!D15) -> 0 | E15: =SUM('GOIANO:SAO JOSE DO GROTAO'!E15) -> 0 | F15: =SUM('GOIANO:SAO JOSE DO GROTAO'!F15) -> 0 | G15: =SUM('GOIANO:SAO JOSE DO GROTAO'!G15) -> 0 | H15: =SUM('GOIANO:SAO JOSE DO GROTAO'!H15) -> 0 | I15: =SUM('GOIANO:SAO JOSE DO GROTAO'!I15) -> 0 | J15: =SUM('GOIANO:SAO JOSE DO GROTAO'!J15) -> 0 | K15: =SUM('GOIANO:SAO JOSE DO GROTAO'!K15) -> 0 | ... O15: =SUM('GOIANO:SAO JOSE DO GROTAO'!O15) -> 0
A16: TOTAL | D16: =SUM('GOIANO:SAO JOSE DO GROTAO'!D16) -> 0 | E16: =SUM('GOIANO:SAO JOSE DO GROTAO'!E16) -> 0 | F16: =SUM('GOIANO:SAO JOSE DO GROTAO'!F16) -> 0 | G16: =SUM('GOIANO:SAO JOSE DO GROTAO'!G16) -> 0 | H16: =SUM('GOIANO:SAO JOSE DO GROTAO'!H16) -> 0 | I16: =SUM('GOIANO:SAO JOSE DO GROTAO'!I16) -> 0 | J16: =SUM('GOIANO:SAO JOSE DO GROTAO'!J16) -> 0 | K16: =SUM('GOIANO:SAO JOSE DO GROTAO'!K16) -> 0 | ... O16: =SUM('GOIANO:SAO JOSE DO GROTAO'!O16) -> -140

Sheet COMPRA DE GADO
B7: DATA | C7: QUANT. | D7: NOVILHAS / BOIS | E7: VALOR TOTAL DA COMPRA | F7: MÉDIA / CAB | G7: FAZENDA | H7: MÊS | I7: PARCERIA | J7: ANO | K7: SAFRA | L7: FRETE | M7: COMISSÃO | N7: OBSERVAÇÕES | O7: IMPOSTOS | P7: OBSERVAÇÕES 2 | AF7: DATA | AG7: MÊS
B8: 45858 | C8: 96 | D8: BEZERROS | E8: 225000 | F8: =Tabela27[[#This Row],[VALOR TOTAL DA COMPRA]]/Tabela27[[#This Row],[QUANT.]] -> 2343.75 | G8: SÃO FRANCISCO | H8: JULHO | I8: - | J8: 2025 | K8: 2025/2026 | L8: - | M8: - | N8: - | O8: - | P8: - | AF8: 45292 | AG8: JANEIRO
B9: 45889 | C9: 40 | D9: BEZERROS | E9: 110000 | F9: =Tabela27[[#This Row],[VALOR TOTAL DA COMPRA]]/Tabela27[[#This Row],[QUANT.]] -> 2750 | G9: SÃO FRANCISCO | H9: AGOSTO | I9: - | J9: 2025 | K9: 2025/2026 | L9: - | M9: - | N9: - | O9: - | P9: - | AF9: 45293 | AG9: JANEIRO
B10: 45947 | C10: 12 | D10: BEZERROS | E10: 28800 | F10: =Tabela27[[#This Row],[VALOR TOTAL DA COMPRA]]/Tabela27[[#This Row],[QUANT.]] -> 2400 | G10: SÃO FRANCISCO | H10: OUTUBRO | I10: - | J10: 2025 | K10: 2025/2026 | L10: - | M10: - | N10: - | O10: - | AF10: 45294 | AG10: JANEIRO
B11: 45953 | C11: 42 | D11: BEZERROS | E11: 105000 | F11: =Tabela27[[#This Row],[VALOR TOTAL DA COMPRA]]/Tabela27[[#This Row],[QUANT.]] -> 2500 | G11: SÃO FRANCISCO | H11: OUTUBRO | I11: - | J11: 2025 | K11: 2025/2026 | L11: - | M11: - | N11: - | O11: - | AF11: 45295 | AG11: JANEIRO
B12: 45999 | C12: 69 | D12: BEZERROS | E12: 138000 | F12: =Tabela27[[#This Row],[VALOR TOTAL DA COMPRA]]/Tabela27[[#This Row],[QUANT.]] -> 2000 | G12: SÃO FRANCISCO | H12: DEZEMBRO | I12: - | J12: 2025 | K12: 2025/2026 | L12: - | M12: - | N12: - | O12: - | AF12: 45296 | AG12: JANEIRO
B13: 45981 | C13: 150 | D13: BEZERROS | E13: 375000 | F13: =Tabela27[[#This Row],[VALOR TOTAL DA COMPRA]]/Tabela27[[#This Row],[QUANT.]] -> 2500 | G13: SÃO FRANCISCO | H13: NOVEMBRO | I13: - | J13: 2025 | K13: 2025/2026 | L13: - | M13: - | N13: - | O13: - | AF13: 45297 | AG13: JANEIRO
B14: 46020 | C14: 105 | D14: BEZERROS | E14: =150000+110172.15 -> 260172.15 | F14: =Tabela27[[#This Row],[VALOR TOTAL DA COMPRA]]/Tabela27[[#This Row],[QUANT.]] -> 2477.83 | G14: SÃO FRANCISCO | H14: DEZEMBRO | J14: 2025 | K14: 2025/2026 | L14: - | M14: - | AF14: 45298 | AG14: JANEIRO
B15: 45989 | C15: 40 | D15: BEZERROS | E15: 98000 | F15: =Tabela27[[#This Row],[VALOR TOTAL DA COMPRA]]/Tabela27[[#This Row],[QUANT.]] -> 2450 | G15: SÃO FRANCISCO | H15: NOVEMBRO | J15: 2025 | K15: 2025/2026 | L15: - | M15: - | AF15: 45299 | AG15: JANEIRO
B16: 46098 | C16: 6 | D16: BEZERROS | E16: 14200 | F16: =Tabela27[[#This Row],[VALOR TOTAL DA COMPRA]]/Tabela27[[#This Row],[QUANT.]] -> 2366.6667 | G16: SÃO FRANCISCO | H16: MARÇO | J16: 2026 | K16: 2025/2026 | L16: - | M16: - | AF16: 45300 | AG16: JANEIRO
B17: 46139 | C17: 130 | D17: BEZERROS | E17: 344500 | F17: =Tabela27[[#This Row],[VALOR TOTAL DA COMPRA]]/Tabela27[[#This Row],[QUANT.]] -> 2650 | G17: SÃO FRANCISCO | H17: ABRIL | J17: 2026 | K17: 2025/2026 | AF17: 45301 | AG17: JANEIRO
B18: 46139 | C18: 120 | D18: BEZERROS | E18: 318000 | F18: =Tabela27[[#This Row],[VALOR TOTAL DA COMPRA]]/Tabela27[[#This Row],[QUANT.]] -> 2650 | G18: SÃO FRANCISCO | H18: ABRIL | J18: 2026 | K18: 2025/2026 | AF18: 45302 | AG18: JANEIRO
B19: 46139 | C19: 18 | D19: BEZERROS | E19: 53000 | F19: =Tabela27[[#This Row],[VALOR TOTAL DA COMPRA]]/Tabela27[[#This Row],[QUANT.]] -> 2944.4444 | G19: SÃO FRANCISCO | H19: ABRIL | J19: 2026 | K19: 2025/2026 | AF19: 45303 | AG19: JANEIRO
B20: 46139 | C20: 126 | D20: BEZERROS | E20: 388080 | F20: =Tabela27[[#This Row],[VALOR TOTAL DA COMPRA]]/Tabela27[[#This Row],[QUANT.]] -> 3080 | G20: SÃO FRANCISCO | H20: ABRIL | I20: - | J20: 2026 | K20: 2025/2026 | AF20: 45304 | AG20: JANEIRO
F21: =Tabela27[[#This Row],[VALOR TOTAL DA COMPRA]]/Tabela27[[#This Row],[QUANT.]] -> #DIV/0! | AF21: 45305 | AG21: JANEIRO
F22: =Tabela27[[#This Row],[VALOR TOTAL DA COMPRA]]/Tabela27[[#This Row],[QUANT.]] -> #DIV/0! | AF22: 45306 | AG22: JANEIRO
F23: =Tabela27[[#This Row],[VALOR TOTAL DA COMPRA]]/Tabela27[[#This Row],[QUANT.]] -> #DIV/0! | AF23: 45307 | AG23: JANEIRO
F24: =Tabela27[[#This Row],[VALOR TOTAL DA COMPRA]]/Tabela27[[#This Row],[QUANT.]] -> #DIV/0! | AF24: 45308 | AG24: JANEIRO
F25: =Tabela27[[#This Row],[VALOR TOTAL DA COMPRA]]/Tabela27[[#This Row],[QUANT.]] -> #DIV/0! | AF25: 45309 | AG25: JANEIRO
F26: =Tabela27[[#This Row],[VALOR TOTAL DA COMPRA]]/Tabela27[[#This Row],[QUANT.]] -> #DIV/0! | AF26: 45310 | AG26: JANEIRO
F27: =Tabela27[[#This Row],[VALOR TOTAL DA COMPRA]]/Tabela27[[#This Row],[QUANT.]] -> #DIV/0! | AF27: 45311 | AG27: JANEIRO
F28: =Tabela27[[#This Row],[VALOR TOTAL DA COMPRA]]/Tabela27[[#This Row],[QUANT.]] -> #DIV/0! | AF28: 45312 | AG28: JANEIRO
F29: =Tabela27[[#This Row],[VALOR TOTAL DA COMPRA]]/Tabela27[[#This Row],[QUANT.]] -> #DIV/0! | AF29: 45313 | AG29: JANEIRO
F30: =Tabela27[[#This Row],[VALOR TOTAL DA COMPRA]]/Tabela27[[#This Row],[QUANT.]] -> #DIV/0! | AF30: 45314 | AG30: JANEIRO
F31: =Tabela27[[#This Row],[VALOR TOTAL DA COMPRA]]/Tabela27[[#This Row],[QUANT.]] -> #DIV/0! | AF31: 45315 | AG31: JANEIRO
F32: =Tabela27[[#This Row],[VALOR TOTAL DA COMPRA]]/Tabela27[[#This Row],[QUANT.]] -> #DIV/0! | AF32: 45316 | AG32: JANEIRO
... F335: =Tabela27[[#This Row],[VALOR TOTAL DA COMPRA]]/Tabela27[[#This Row],[QUANT.]] -> #DIV/0! | AF335: 45619 | AG335: NOVEMBRO
AF336: 45620 | AG336: NOVEMBRO
AF337: 45621 | AG337: NOVEMBRO
AF338: 45622 | AG338: NOVEMBRO
AF339: 45623 | AG339: NOVEMBRO
AF340: 45624 | AG340: NOVEMBRO
AF341: 45625 | AG341: NOVEMBRO
AF342: 45626 | AG342: NOVEMBRO
AF343: 45627 | AG343: DEZEMBRO
AF344: 45628 | AG344: DEZEMBRO
AF345: 45629 | AG345: DEZEMBRO
AF346: 45630 | AG346: DEZEMBRO
AF347: 45631 | AG347: DEZEMBRO
... AF738: 46022 | AG738: DEZEMBRO
AG739: DEZEMBRO

Sheet CUSTOS
F1: LISTA SUSPENSA | G1: LISTA SUSPENSA
B2: DATA | C2: PAGADOR | D2: ITEM | E2: VALOR TOTAL | F2: SUB CENTRO | G2: CENTRO DE CUSTO | H2: CLASSE | I2: MÊS | J2: ANO | K2: SAFRA | S2: 45292
B3: 45840 | C3: ONODA | D3: SALÁRIO ALDEMAR | E3: 2967 | G3: FUNCIONARIO | H3: CUSTEIO | I3: JULHO | J3: 2025 | K3: 2025/2026 | S3: 45293
B4: 45840 | C4: ONODA | D4: SALÁRIO PRETO | E4: 2567 | G4: FUNCIONARIO | H4: CUSTEIO | I4: JULHO | J4: 2025 | K4: 2025/2026 | S4: 45294
B5: 45840 | C5: ONODA | D5: SALÁRIO WALDINEY | E5: 2600 | G5: FUNCIONARIO | H5: CUSTEIO | I5: JULHO | J5: 2025 | K5: 2025/2026 | S5: 45295
B6: 45840 | C6: ONODA | D6: SALÁRIO ZÉ | E6: 4000 | G6: FUNCIONARIO | H6: CUSTEIO | I6: JULHO | J6: 2025 | K6: 2025/2026 | S6: 45296
B7: 45840 | C7: ONODA | D7: SALÁRIO NILVAN | E7: 3200 | G7: FUNCIONARIO | H7: CUSTEIO | I7: JULHO | J7: 2025 | K7: 2025/2026 | S7: 45297
B8: 45841 | C8: ONODA | D8: COMPRA DE MANTIMENTOS | E8: 869.15 | G8: FUNCIONARIO | H8: CUSTEIO | I8: JULHO | J8: 2025 | K8: 2025/2026 | S8: 45298
B9: 45841 | C9: ONODA | D9: CONSERTO TRATOR AZUL | E9: 760 | G9: PARQUE DE MÁQUINAS | H9: CUSTEIO | I9: JULHO | J9: 2025 | K9: 2025/2026 | S9: 45299
B10: 45841 | C10: ONODA | D10: POSTO TIGRAO | E10: 1746 | G10: PARQUE DE MÁQUINAS | H10: CUSTEIO | I10: JULHO | J10: 2025 | K10: 2025/2026 | S10: 45300
B11: 45841 | C11: ONODA | D11: AUTO PEÇAS | E11: 4590.8 | G11: PARQUE DE MÁQUINAS | H11: CUSTEIO | I11: JULHO | J11: 2025 | K11: 2025/2026 | S11: 45301
B12: 45841 | C12: ONODA | D12: MERCADO ALFREDO | E12: 761.16 | G12: FUNCIONARIO | H12: CUSTEIO | I12: JULHO | J12: 2025 | K12: 2025/2026 | S12: 45302
B13: 45841 | C13: ONODA | D13: COMISSÃO CORRETOR | E13: 1966.5 | G13: COMISSÃO | H13: CUSTEIO | I13: JULHO | J13: 2025 | K13: 2025/2026 | S13: 45303
B14: 45841 | C14: ONODA | D14: HERBICIDA | E14: 11348 | G14: PASTAGEM | H14: CUSTEIO | I14: JULHO | J14: 2025 | K14: 2025/2026 | S14: 45304
... B21: 45841 | C21: ONODA | D21: IR | E21: 1672.41 | G21: IMPOSTO E TAXAS | H21: CUSTEIO | I21: JULHO | J21: 2025 | K21: 2025/2026 | S21: 45311
B22: 45841 | C22: ONODA | D22: CAMARA MONITORAMENTO | E22: 24275.19 | G22: INFRAESTRUTURA | H22: INVESTIMENTOS | I22: JULHO | J22: 2025 | K22: 2025/2026
B23: 45841 | C23: ONODA | D23: VISITA ORÇAMENTO | E23: 685 | G23: PARQUE DE MÁQUINAS | H23: CUSTEIO | I23: JULHO | J23: 2025 | K23: 2025/2026 | S23: 45312
B24: 45841 | C24: ONODA | D24: FÉRIAS WALDINEY | E24: 2881.53 | G24: FUNCIONARIO | H24: CUSTEIO | I24: JULHO | J24: 2025 | K24: 2025/2026 | S24: 45313
B25: 45841 | C25: ONODA | D25: POSTO TIGRAO | E25: 3313.45 | G25: PARQUE DE MÁQUINAS | H25: CUSTEIO | I25: JULHO | J25: 2025 | K25: 2025/2026 | S25: 45314
B26: 45841 | C26: ONODA | D26: ENCOMENDA ONIBUS | E26: 100 | G26: OUTROS | H26: CUSTEIO | I26: JULHO | J26: 2025 | K26: 2025/2026 | S26: 45315
B27: 45841 | C27: ONODA | D27: CONTADOR | E27: 944 | G27: FUNCIONARIO | H27: CUSTEIO | I27: JULHO | J27: 2025 | K27: 2025/2026 | S27: 45316
B28: 45841 | C28: ONODA | D28: JUNIOR TRATORISTA | E28: 4200 | G28: PARQUE DE MÁQUINAS | H28: CUSTEIO | I28: JULHO | J28: 2025 | K28: 2025/2026 | S28: 45317
B29: 45841 | C29: ONODA | D29: CONSERTO AR CONDICIONADO | E29: 400 | G29: INFRAESTRUTURA | H29: CUSTEIO | I29: JULHO | J29: 2025 | K29: 2025/2026 | S29: 45318
B30: 45841 | C30: ONODA | D30: CONSULTORIA | E30: 3000 | G30: FUNCIONARIO | H30: CUSTEIO | I30: JULHO | J30: 2025 | K30: 2025/2026 | S30: 45319
B31: 45841 | C31: ONODA | D31: FÉRIAS PRETO | E31: 3212.3 | G31: FUNCIONARIO | H31: CUSTEIO | I31: JULHO | J31: 2025 | K31: 2025/2026 | S31: 45320
B32: 45841 | C32: ONODA | D32: COMPRA MILHO | E32: 3400 | G32: DESPESA GADO | H32: CUSTEIO | I32: JULHO | J32: 2025 | K32: 2025/2026 | S32: 45321
B33: 45841 | C33: ONODA | D33: NUTRIÇÃO PROTEINADO | E33: 27475 | G33: NUTRIÇÃO | H33: CUSTEIO | I33: JULHO | J33: 2025 | K33: 2025/2026 | S33: 45322
B34: 45872 | C34: ONODA | D34: DESPESA VIAGEM FAZENDA | E34: 1290 | G34: OUTROS | H34: CUSTEIO | I34: AGOSTO | J34: 2025 | K34: 2025/2026 | S34: 45323
... B74: 45903 | C74: ONODA | D74: CONTADOR | E74: 944 | G74: FUNCIONARIO | H74: CUSTEIO | I74: SETEMBRO | J74: 2025 | K74: 2025/2026 | S74: 45363
B75: 45903 | C75: ONODA | D75: AGROVET | E75: 1740 | G75: DESPESA GADO | H75: CUSTEIO | I75: SETEMBRO | J75: 2025 | K75: 2025/2026
B76: 45903 | C76: ONODA | D76: CONSULTORIA | E76: 3000 | G76: FUNCIONARIO | H76: CUSTEIO | I76: SETEMBRO | J76: 2025 | K76: 2025/2026
B77: 45903 | C77: ONODA | D77: NUTRIÇÃO SAL MINERAL | E77: 27475 | G77: NUTRIÇÃO | H77: CUSTEIO | I77: SETEMBRO | J77: 2025 | K77: 2025/2026
B78: 45903 | C78: ONODA | D78: REVISÃO PROGRAMA | E78: 933.34 | G78: FUNCIONARIO | H78: CUSTEIO | I78: SETEMBRO | J78: 2025 | K78: 2025/2026
B79: 45903 | C79: ONODA | D79: MAQCAMPO PEÇAS TRATOR | E79: 953.29 | G79: PARQUE DE MÁQUINAS | H79: CUSTEIO | I79: SETEMBRO | J79: 2025 | K79: 2025/2026
B80: 45903 | C80: ONODA | D80: MAQCAMPO PEÇAS TRATOR | E80: 2494.82 | G80: PARQUE DE MÁQUINAS | H80: CUSTEIO | I80: SETEMBRO | J80: 2025 | K80: 2025/2026
B81: 45903 | C81: ONODA | D81: ANALISE DE SOLO | E81: 178.5 | G81: DESPESA GADO | H81: CUSTEIO | I81: SETEMBRO | J81: 2025 | K81: 2025/2026
B82: 45933 | C82: ONODA | D82: BATERIA PARA MOTO | E82: 375 | I82: OUTUBRO | J82: 2025 | K82: 2025/2026
B83: 45933 | C83: ONODA | D83: MATERIAL DE CONSTRUÇÃO | E83: 290 | G83: INFRAESTRUTURA | I83: OUTUBRO | J83: 2025 | K83: 2025/2026
B84: 45933 | C84: ONODA | D84: JUNIOR TRATORISTA | E84: 4200 | G84: FUNCIONARIO | I84: OUTUBRO | J84: 2025 | K84: 2025/2026
B85: 45933 | C85: ONODA | D85: MAQCAMPO PEÇAS TRATOR | E85: 831.85 | G85: PARQUE DE MÁQUINAS | I85: OUTUBRO | J85: 2025 | K85: 2025/2026
B86: 45933 | C86: ONODA | D86: MATSUDA SEMENTES | E86: 20699 | G86: PASTAGEM | I86: OUTUBRO | J86: 2025 | K86: 2025/2026
B87: 45933 | C87: ONODA | D87: TRATOR FERTIL OLEO | E87: 515 | G87: PARQUE DE MÁQUINAS | I87: OUTUBRO | J87: 2025 | K87: 2025/2026
B88: 45933 | C88: ONODA | D88: CONSERTO MOTO | E88: 375 | G88: FUNCIONARIO | I88: OUTUBRO | J88: 2025 | K88: 2025/2026
B89: 45933 | C89: ONODA | D89: SALARIO DOS FUNCIONÁRIOS | E89: 17700 | G89: FUNCIONARIO | I89: OUTUBRO | J89: 2025 | K89: 2025/2026
B90: 45933 | C90: ONODA | D90: CONSERTO DE MOTO J | E90: 251 | G90: FUNCIONARIO | I90: OUTUBRO | J90: 2025 | K90: 2025/2026
B91: 45933 | C91: ONODA | D91: FRETE | E91: 200 | G91: DESPESA GADO | I91: OUTUBRO | J91: 2025 | K91: 2025/2026
B92: 45933 | C92: ONODA | D92: TRATOR FERTIL OLEO | E92: 390 | G92: PARQUE DE MÁQUINAS | I92: OUTUBRO | J92: 2025 | K92: 2025/2026
B93: 45933 | C93: ONODA | D93: FERPAM | E93: 1785 | G93: INFRAESTRUTURA | I93: OUTUBRO | J93: 2025 | K93: 2025/2026
B94: 45933 | C94: ONODA | D94: HOME CENTER CONSTRUÇÃO | E94: 290 | G94: INFRAESTRUTURA | I94: OUTUBRO | J94: 2025 | K94: 2025/2026
... B96: 45933 | C96: ONODA | D96: VITORIA AUTOPEÇAS | E96: 196 | G96: PARQUE DE MÁQUINAS | I96: OUTUBRO | J96: 2025 | K96: 2025/2026
B97: 45933 | C97: ONODA | D97: CALTINS CALCARIO | E97: 41904 | I97: OUTUBRO | J97: 2025 | K97: 2025/2026
B98: 45933 | C98: ONODA | D98: OLEO DIESEL + GASOLINA | E98: 12998.62 | G98: PARQUE DE MÁQUINAS | I98: OUTUBRO | J98: 2025 | K98: 2025/2026
B99: 45933 | C99: ONODA | D99: RETIRADA SÓCIA CAMILA | E99: 4000 | G99: FUNCIONARIO | I99: OUTUBRO | J99: 2025 | K99: 2025/2026
B100: 45933 | C100: ONODA | D100: 10 BOLAS DE ARAME | E100: 3500 | G100: DESPESA GADO | I100: OUTUBRO | J100: 2025 | K100: 2025/2026
B101: 45933 | C101: ONODA | D101: FGTS | E101: 1330.4 | G101: FUNCIONARIO | I101: OUTUBRO | J101: 2025 | K101: 2025/2026
B102: 45933 | C102: ONODA | D102: IMPOSTO RECEITA FEDERAL | E102: 1437 | G102: IMPOSTO E TAXAS | I102: OUTUBRO | J102: 2025 | K102: 2025/2026
B103: 45933 | C103: ONODA | D103: MANGUEIRA TRATOS | E103: 193 | G103: PARQUE DE MÁQUINAS | I103: OUTUBRO | J103: 2025 | K103: 2025/2026
B104: 45933 | C104: ONODA | D104: MATSUDA SEMENTES MILHETO | E104: 2675 | I104: OUTUBRO | J104: 2025 | K104: 2025/2026
B105: 45933 | C105: ONODA | D105: FRETE CALCARIO | E105: 43316 | G105: PASTAGEM | I105: OUTUBRO | J105: 2025 | K105: 2025/2026
B106: 45933 | C106: ONODA | D106: CONTADOR | E106: 944 | G106: FUNCIONARIO | I106: OUTUBRO | J106: 2025 | K106: 2025/2026
B107: 45933 | C107: ONODA | D107: MAQCAMPO PEÇAS TRATOR | E107: 1353.31 | G107: PARQUE DE MÁQUINAS | I107: OUTUBRO | J107: 2025 | K107: 2025/2026
B108: 45933 | C108: ONODA | D108: CONSULTORIA | E108: 3000 | G108: FUNCIONARIO | I108: OUTUBRO | J108: 2025 | K108: 2025/2026
B109: 45933 | C109: ONODA | D109: COMISSÃO CORRETOR | E109: 1338 | G109: DESPESA GADO | I109: OUTUBRO | J109: 2025 | K109: 2025/2026
B110: 45933 | C110: ONODA | D110: CARGIRL NUTRIÇÃO | E110: 27474.99 | G110: NUTRIÇÃO | I110: OUTUBRO | J110: 2025 | K110: 2025/2026
B111: 45933 | C111: ONODA | D111: EUROCHEM ADUBO | E111: 66960 | G111: PASTAGEM | I111: OUTUBRO | J111: 2025 | K111: 2025/2026
B112: 45933 | C112: ONODA | D112: POSTO TIGRAO | E112: 1063.27 | I112: OUTUBRO | J112: 2025 | K112: 2025/2026
B113: 45964 | C113: ONODA | D113: SALARIO DOS FUNCIONÁRIOS | E113: 24623.44 | G113: FUNCIONARIO | I113: NOVEMBRO | J113: 2025 | K113: 2025/2026
B114: 45964 | C114: ONODA | D114: MERCADO MANOEL CARNES | E114: 439.51 | G114: FUNCIONARIO | I114: NOVEMBRO | J114: 2025 | K114: 2025/2026
B115: 45964 | C115: ONODA | D115: MAQCAMPO PEÇAS TRATOR | E115: 1384 | G115: PARQUE DE MÁQUINAS | I115: NOVEMBRO | J115: 2025 | K115: 2025/2026
B116: 45964 | C116: ONODA | D116: TORNEADORA | E116: 1930 | G116: PARQUE DE MÁQUINAS | I116: NOVEMBRO | J116: 2025 | K116: 2025/2026
B117: 45964 | C117: ONODA | D117: WILLIAN MECANICO | E117: 9000 | G117: PARQUE DE MÁQUINAS | I117: NOVEMBRO | J117: 2025 | K117: 2025/2026
B118: 45964 | C118: ONODA | D118: JUNIOR TRATORISTA | E118: 3850 | G118: PARQUE DE MÁQUINAS | I118: NOVEMBRO | J118: 2025 | K118: 2025/2026
B119: 45964 | C119: ONODA | D119: RETIFICA DA BOMBA INJETORA | E119: 4180 | G119: PARQUE DE MÁQUINAS | I119: NOVEMBRO | J119: 2025 | K119: 2025/2026
B120: 45964 | C120: ONODA | D120: COMPRAS AJJAI | E120: 1423.37 | I120: NOVEMBRO | J120: 2025 | K120: 2025/2026
B121: 45964 | C121: ONODA | D121: MERCADO ALFREDO | E121: 826 | G121: FUNCIONARIO | I121: NOVEMBRO | J121: 2025 | K121: 2025/2026
B122: 45964 | C122: ONODA | D122: CARGIRL NUTRIÇÃO | E122: 26200 | G122: NUTRIÇÃO | I122: NOVEMBRO | J122: 2025 | K122: 2025/2026
B123: 45964 | C123: ONODA | D123: VULCANIZAÇÃO TRATOR | E123: 1500 | G123: PARQUE DE MÁQUINAS | I123: NOVEMBRO | J123: 2025 | K123: 2025/2026
B124: 45964 | C124: ONODA | D124: CONSERTO AR CONDICIONADO TRATOR | E124: 525 | G124: PARQUE DE MÁQUINAS | I124: NOVEMBRO | J124: 2025 | K124: 2025/2026
B125: 45964 | C125: ONODA | D125: POSTO TIGRAO | E125: 292.6 | G125: PARQUE DE MÁQUINAS | I125: NOVEMBRO | J125: 2025 | K125: 2025/2026
B126: 45964 | C126: ONODA | D126: BALANSEG. CONSULTORIA | E126: 933.33 | I126: NOVEMBRO | J126: 2025 | K126: 2025/2026
B127: 45964 | C127: ONODA | D127: RETIRADA SÓCIA CAMILA | E127: 4000 | G127: FUNCIONARIO | I127: NOVEMBRO | J127: 2025 | K127: 2025/2026
B128: 45964 | C128: ONODA | D128: FGTS | E128: 1330.4 | G128: FUNCIONARIO | I128: NOVEMBRO | J128: 2025 | K128: 2025/2026
B129: 45964 | C129: ONODA | D129: IR | E129: 1437 | I129: NOVEMBRO | J129: 2025 | K129: 2025/2026
B130: 45964 | C130: ONODA | D130: FRETE | E130: 4000 | G130: DESPESA GADO | I130: NOVEMBRO | J130: 2025 | K130: 2025/2026
B131: 45964 | C131: ONODA | D131: AR CONDICIONADO VALE | E131: 2000 | I131: NOVEMBRO | J131: 2025 | K131: 2025/2026
B132: 45964 | C132: ONODA | D132: CONTADOR | E132: 944 | G132: FUNCIONARIO | I132: NOVEMBRO | J132: 2025 | K132: 2025/2026
B133: 45964 | C133: ONODA | D133: MAQCAMPO PEÇAS TRATOR | E133: 5845.67 | G133: PARQUE DE MÁQUINAS | I133: NOVEMBRO | J133: 2025 | K133: 2025/2026
B134: 45964 | C134: ONODA | D134: CONSULTORIA | E134: 3000 | G134: FUNCIONARIO | I134: NOVEMBRO | J134: 2025 | K134: 2025/2026 | P134: 1000
B135: 45964 | C135: ONODA | D135: AR CONDICIONADO IMPLEMENTO | E135: 3500 | I135: NOVEMBRO | J135: 2025 | K135: 2025/2026 | P135: 8
B136: 45964 | C136: ONODA | D136: CONSERTO MOTO | E136: 160 | G136: FUNCIONARIO | I136: NOVEMBRO | J136: 2025 | K136: 2025/2026 | P136: 90
B137: 45964 | C137: ONODA | D137: PEÇAS PARA TRATOR | E137: 3500 | G137: PARQUE DE MÁQUINAS | I137: NOVEMBRO | J137: 2025 | K137: 2025/2026 | P137: =P134*P135*P136 -> 720000
B138: 45964 | C138: ONODA | D138: POSTO TIGRAO | E138: 14175.9 | G138: PARQUE DE MÁQUINAS | I138: NOVEMBRO | J138: 2025 | K138: 2025/2026 | P138: =P137/250 -> 2880
B139: 45964 | C139: ONODA | D139: FRETE 40 BEZERROS | E139: 2000 | G139: DESPESA GADO | I139: NOVEMBRO | J139: 2025 | K139: 2025/2026 | P139: =P138/40 -> 72
B140: 45994 | C140: ONODA | D140: SALARIO DOS FUNCIONÁRIOS | E140: 17600 | G140: FUNCIONARIO | I140: DEZEMBRO | J140: 2025 | K140: 2025/2026 | P140: =35 -> 35
B141: 45994 | C141: ONODA | D141: CONTADOR | E141: 933.33 | I141: DEZEMBRO | J141: 2025 | K141: 2025/2026 | P141: =P138*P140 -> 100800
B142: 45994 | C142: ONODA | E142: 143 | I142: DEZEMBRO | J142: 2025 | K142: 2025/2026
B143: 45994 | C143: ONODA | E143: 5000 | I143: DEZEMBRO | J143: 2025 | K143: 2025/2026
B144: 45994 | C144: ONODA | E144: 3850 | I144: DEZEMBRO | J144: 2025 | K144: 2025/2026
B145: 45994 | C145: ONODA | E145: 5804 | I145: DEZEMBRO | J145: 2025 | K145: 2025/2026
B146: 45994 | C146: ONODA | E146: 26200 | I146: DEZEMBRO | J146: 2025 | K146: 2025/2026
...

Sheet VENDAS
B4: DATA | C4: TIPO DE VENDA | D4: CATEGORIA | E4: ANIMAIS | F4: PESO TOTAL | G4: PESO MÉDIO | H4: CARCAÇA TOTAL | I4: CARCAÇA MÉDIA | J4: RENDIMENTO % | K4: VALOR TOTAL | L4: VALOR CABEÇA | M4: VALOR POR @ | N4: COMPRADOR | O4: MÊS | P4: ANO | Q4: FORMA | R4: SOMA RENDIMENTO | S4: FAZENDA | T4: STATUS | U4: PARCERIA | V4: SAFRA
B5: 45872 | C5: ABATE | D5: MACHOS 25 - 36 | E5: 84 | F5: 43540 | G5: =Tabela3[[#This Row],[PESO TOTAL]]/Tabela3[[#This Row],[ANIMAIS]] -> 518.33333 | H5: 22350.4 | I5: =Tabela3[[#This Row],[CARCAÇA TOTAL]]/Tabela3[[#This Row],[ANIMAIS]] -> 266.07619 | J5: =Tabela3[[#This Row],[CARCAÇA MÉDIA]]/Tabela3[[#This Row],[PESO MÉDIO]] -> 0.51333027 | K5: 401502.68 | L5: =K5/E5 -> 4779.7938 | M5: =Tabela3[[#This Row],[VALOR CABEÇA]]/(Tabela3[[#This Row],[CARCAÇA MÉDIA]]/15) -> 269.46006 | N5: COPERFRIGU | O5: AGOSTO | P5: 2025 | Q5: PASTO | R5: =Tabela3[[#This Row],[RENDIMENTO %]]*Tabela3[[#This Row],[ANIMAIS]] -> 43.119743 | S5: SÃO FRANCISCO II | T5: - | U5: - | V5: 2025/2026
B6: 46108 | C6: ABATE | D6: MACHOS 25 - 36 | E6: 189 | F6: 106680 | G6: =Tabela3[[#This Row],[PESO TOTAL]]/Tabela3[[#This Row],[ANIMAIS]] -> 564.44444 | H6: 60225 | I6: =Tabela3[[#This Row],[CARCAÇA TOTAL]]/Tabela3[[#This Row],[ANIMAIS]] -> 318.65079 | J6: =Tabela3[[#This Row],[CARCAÇA MÉDIA]]/Tabela3[[#This Row],[PESO MÉDIO]] -> 0.56453881 | K6: 1302000 | L6: =K6/E6 -> 6888.8889 | M6: =Tabela3[[#This Row],[VALOR CABEÇA]]/(Tabela3[[#This Row],[CARCAÇA MÉDIA]]/15) -> 324.28394 | N6: COPERFRIGU | O6: MARÇO | P6: 2026 | Q6: PASTO | S6: SÃO FRANCISCO II | T6: - | U6: - | V6: 2025/2026
B7: 46136 | C7: ABATE | D7: MACHOS 25 - 36 | E7: 81 | F7: 45000 | G7: =Tabela3[[#This Row],[PESO TOTAL]]/Tabela3[[#This Row],[ANIMAIS]] -> 555.55556 | H7: 25555 | I7: =Tabela3[[#This Row],[CARCAÇA TOTAL]]/Tabela3[[#This Row],[ANIMAIS]] -> 315.49383 | J7: =Tabela3[[#This Row],[CARCAÇA MÉDIA]]/Tabela3[[#This Row],[PESO MÉDIO]] -> 0.56788889 | K7: 595083.55 | L7: =K7/E7 -> 7346.7105 | M7: =Tabela3[[#This Row],[VALOR CABEÇA]]/(Tabela3[[#This Row],[CARCAÇA MÉDIA]]/15) -> 349.29576 | N7: COPERFRIGU | O7: ABRIL | P7: 2026 | Q7: PASTO | S7: SÃO FRANCISCO II | T7: - | U7: - | V7: 2025/2026
G8: =Tabela3[[#This Row],[PESO TOTAL]]/Tabela3[[#This Row],[ANIMAIS]] -> #DIV/0! | I8: =Tabela3[[#This Row],[CARCAÇA TOTAL]]/Tabela3[[#This Row],[ANIMAIS]] -> #DIV/0! | J8: =Tabela3[[#This Row],[CARCAÇA MÉDIA]]/Tabela3[[#This Row],[PESO MÉDIO]] -> #DIV/0! | L8: =K8/E8 -> #DIV/0! | M8: =Tabela3[[#This Row],[VALOR CABEÇA]]/(Tabela3[[#This Row],[CARCAÇA MÉDIA]]/15) -> #DIV/0!
G9: =Tabela3[[#This Row],[PESO TOTAL]]/Tabela3[[#This Row],[ANIMAIS]] -> #DIV/0! | I9: =Tabela3[[#This Row],[CARCAÇA TOTAL]]/Tabela3[[#This Row],[ANIMAIS]] -> #DIV/0! | J9: =Tabela3[[#This Row],[CARCAÇA MÉDIA]]/Tabela3[[#This Row],[PESO MÉDIO]] -> #DIV/0! | L9: =K9/E9 -> #DIV/0! | M9: =Tabela3[[#This Row],[VALOR CABEÇA]]/(Tabela3[[#This Row],[CARCAÇA MÉDIA]]/15) -> #DIV/0!
G10: =Tabela3[[#This Row],[PESO TOTAL]]/Tabela3[[#This Row],[ANIMAIS]] -> #DIV/0! | I10: =Tabela3[[#This Row],[CARCAÇA TOTAL]]/Tabela3[[#This Row],[ANIMAIS]] -> #DIV/0! | J10: =Tabela3[[#This Row],[CARCAÇA MÉDIA]]/Tabela3[[#This Row],[PESO MÉDIO]] -> #DIV/0! | L10: =K10/E10 -> #DIV/0! | M10: =Tabela3[[#This Row],[VALOR CABEÇA]]/(Tabela3[[#This Row],[CARCAÇA MÉDIA]]/15) -> #DIV/0!
G11: =Tabela3[[#This Row],[PESO TOTAL]]/Tabela3[[#This Row],[ANIMAIS]] -> #DIV/0! | I11: =Tabela3[[#This Row],[CARCAÇA TOTAL]]/Tabela3[[#This Row],[ANIMAIS]] -> #DIV/0! | J11: =Tabela3[[#This Row],[CARCAÇA MÉDIA]]/Tabela3[[#This Row],[PESO MÉDIO]] -> #DIV/0! | L11: =K11/E11 -> #DIV/0! | M11: =Tabela3[[#This Row],[VALOR CABEÇA]]/(Tabela3[[#This Row],[CARCAÇA MÉDIA]]/15) -> #DIV/0!
G12: =Tabela3[[#This Row],[PESO TOTAL]]/Tabela3[[#This Row],[ANIMAIS]] -> #DIV/0! | I12: =Tabela3[[#This Row],[CARCAÇA TOTAL]]/Tabela3[[#This Row],[ANIMAIS]] -> #DIV/0! | J12: =Tabela3[[#This Row],[CARCAÇA MÉDIA]]/Tabela3[[#This Row],[PESO MÉDIO]] -> #DIV/0! | L12: =K12/E12 -> #DIV/0! | M12: =Tabela3[[#This Row],[VALOR CABEÇA]]/(Tabela3[[#This Row],[CARCAÇA MÉDIA]]/15) -> #DIV/0!
G13: =Tabela3[[#This Row],[PESO TOTAL]]/Tabela3[[#This Row],[ANIMAIS]] -> #DIV/0! | I13: =Tabela3[[#This Row],[CARCAÇA TOTAL]]/Tabela3[[#This Row],[ANIMAIS]] -> #DIV/0! | J13: =Tabela3[[#This Row],[CARCAÇA MÉDIA]]/Tabela3[[#This Row],[PESO MÉDIO]] -> #DIV/0! | L13: =K13/E13 -> #DIV/0! | M13: =Tabela3[[#This Row],[VALOR CABEÇA]]/(Tabela3[[#This Row],[CARCAÇA MÉDIA]]/15) -> #DIV/0!
G14: =Tabela3[[#This Row],[PESO TOTAL]]/Tabela3[[#This Row],[ANIMAIS]] -> #DIV/0! | I14: =Tabela3[[#This Row],[CARCAÇA TOTAL]]/Tabela3[[#This Row],[ANIMAIS]] -> #DIV/0! | J14: =Tabela3[[#This Row],[CARCAÇA MÉDIA]]/Tabela3[[#This Row],[PESO MÉDIO]] -> #DIV/0! | L14: =K14/E14 -> #DIV/0! | M14: =Tabela3[[#This Row],[VALOR CABEÇA]]/(Tabela3[[#This Row],[CARCAÇA MÉDIA]]/15) -> #DIV/0!
G15: =Tabela3[[#This Row],[PESO TOTAL]]/Tabela3[[#This Row],[ANIMAIS]] -> #DIV/0! | I15: =Tabela3[[#This Row],[CARCAÇA TOTAL]]/Tabela3[[#This Row],[ANIMAIS]] -> #DIV/0! | J15: =Tabela3[[#This Row],[CARCAÇA MÉDIA]]/Tabela3[[#This Row],[PESO MÉDIO]] -> #DIV/0! | L15: =K15/E15 -> #DIV/0! | M15: =Tabela3[[#This Row],[VALOR CABEÇA]]/(Tabela3[[#This Row],[CARCAÇA MÉDIA]]/15) -> #DIV/0!
G16: =Tabela3[[#This Row],[PESO TOTAL]]/Tabela3[[#This Row],[ANIMAIS]] -> #DIV/0! | I16: =Tabela3[[#This Row],[CARCAÇA TOTAL]]/Tabela3[[#This Row],[ANIMAIS]] -> #DIV/0! | J16: =Tabela3[[#This Row],[CARCAÇA MÉDIA]]/Tabela3[[#This Row],[PESO MÉDIO]] -> #DIV/0! | L16: =K16/E16 -> #DIV/0! | M16: =Tabela3[[#This Row],[VALOR CABEÇA]]/(Tabela3[[#This Row],[CARCAÇA MÉDIA]]/15) -> #DIV/0!
G17: =Tabela3[[#This Row],[PESO TOTAL]]/Tabela3[[#This Row],[ANIMAIS]] -> #DIV/0! | I17: =Tabela3[[#This Row],[CARCAÇA TOTAL]]/Tabela3[[#This Row],[ANIMAIS]] -> #DIV/0! | J17: =Tabela3[[#This Row],[CARCAÇA MÉDIA]]/Tabela3[[#This Row],[PESO MÉDIO]] -> #DIV/0! | L17: =K17/E17 -> #DIV/0! | M17: =Tabela3[[#This Row],[VALOR CABEÇA]]/(Tabela3[[#This Row],[CARCAÇA MÉDIA]]/15) -> #DIV/0!
G18: =Tabela3[[#This Row],[PESO TOTAL]]/Tabela3[[#This Row],[ANIMAIS]] -> #DIV/0! | I18: =Tabela3[[#This Row],[CARCAÇA TOTAL]]/Tabela3[[#This Row],[ANIMAIS]] -> #DIV/0! | J18: =Tabela3[[#This Row],[CARCAÇA MÉDIA]]/Tabela3[[#This Row],[PESO MÉDIO]] -> #DIV/0! | L18: =K18/E18 -> #DIV/0! | M18: =Tabela3[[#This Row],[VALOR CABEÇA]]/(Tabela3[[#This Row],[CARCAÇA MÉDIA]]/15) -> #DIV/0!
G19: =Tabela3[[#This Row],[PESO TOTAL]]/Tabela3[[#This Row],[ANIMAIS]] -> #DIV/0! | I19: =Tabela3[[#This Row],[CARCAÇA TOTAL]]/Tabela3[[#This Row],[ANIMAIS]] -> #DIV/0! | J19: =Tabela3[[#This Row],[CARCAÇA MÉDIA]]/Tabela3[[#This Row],[PESO MÉDIO]] -> #DIV/0! | L19: =K19/E19 -> #DIV/0! | M19: =Tabela3[[#This Row],[VALOR CABEÇA]]/(Tabela3[[#This Row],[CARCAÇA MÉDIA]]/15) -> #DIV/0!
... G68: =Tabela3[[#This Row],[PESO TOTAL]]/Tabela3[[#This Row],[ANIMAIS]] -> #DIV/0! | I68: =Tabela3[[#This Row],[CARCAÇA TOTAL]]/Tabela3[[#This Row],[ANIMAIS]] -> #DIV/0! | J68: =Tabela3[[#This Row],[CARCAÇA MÉDIA]]/Tabela3[[#This Row],[PESO MÉDIO]] -> #DIV/0! | L68: =K68/E68 -> #DIV/0! | M68: =Tabela3[[#This Row],[VALOR CABEÇA]]/(Tabela3[[#This Row],[CARCAÇA MÉDIA]]/15) -> #DIV/0!

Sheet DASH VENDAS
A1: VENDAS DE BOVINOS | B1: ='PAINEL ENTRADA'!T1 -> SÃO FRANCISCO | G1: =TODAY() -> 46294 | I1: SAFRA | J1: 2025/2026 | L1: SAFRA | M1: 2025/2026 | O1: SAFRA | P1: 2025/2026 | R1: SAFRA | S1: 2025/2026 | U1: SAFRA | V1: 2025/2026
I3: Soma de ANIMAIS | L3: Soma de VALOR TOTAL | O3: Rótulos de Linha | P3: Soma de ANIMAIS | R3: Rótulos de Linha | S3: Soma de ANIMAIS | U3: Rótulos de Linha | V3: Soma de ANIMAIS
I4: 354 | L4: 2298586.2 | O4: ABATE | P4: 354 | R4: MACHOS 25 - 36 | S4: 354 | U4: AGOSTO | V4: 84
A5: QUANTIDADE DE ANIMAIS VENDIDOS | D5: VALOR TOTAL EM VENDAS | O5: Total Geral | P5: 354 | R5: Total Geral | S5: 354 | U5: MARÇO | V5: 189
A6: =I4 -> 354 | D6: =L4 -> 2298586.2 | U6: ABRIL | V6: 81
U7: Total Geral | V7: 354

Sheet DASH COMPRAS
A1: COMPRAS DE BOVINOS | B1: ='PAINEL ENTRADA'!T1 -> SÃO FRANCISCO | G1: =TODAY() -> 46294 | I1: SAFRA | J1: 2025/2026 | L1: SAFRA | M1: 2025/2026 | O1: SAFRA | P1: 2025/2026 | R1: SAFRA | S1: 2025/2026 | U1: SAFRA | V1: 2025/2026
I3: Soma de QUANT. | L3: Soma de VALOR TOTAL DA COMPRA | O3: Rótulos de Linha | P3: Soma de QUANT. | R3: Rótulos de Linha | S3: Média de MÉDIA / CAB | U3: Rótulos de Linha | V3: Soma de QUANT.
I4: 954 | L4: 2457752.1 | O4: BEZERROS | P4: 954 | R4: BEZERROS | S4: 2547.1301 | U4: JULHO | V4: 96
A5: QUANTIDADE DE ANIMAIS COMPRADOS | D5: VALOR TOTAL EM COMPRAS | O5: Total Geral | P5: 954 | R5: Total Geral | S5: 2547.1301 | U5: AGOSTO | V5: 40
A6: =I4 -> 954 | D6: =L4 -> 2457752.1 | U6: OUTUBRO | V6: 54
U7: NOVEMBRO | V7: 190
U8: DEZEMBRO | V8: 174
U9: MARÇO | V9: 6
U10: ABRIL | V10: 394
U11: Total Geral | V11: 954

Sheet DASH FINANCEIRO
A1: FINANCEIRO | B1: ='PAINEL ENTRADA'!T1 -> SÃO FRANCISCO | G1: =TODAY() -> 46294 | I1: SAFRA | J1: 2025/2026 | L1: SAFRA | M1: 2025/2026 | O1: SAFRA | P1: 2025/2026
I3: Sum of VALOR TOTAL | L3: Rótulos de Linha | M3: Sum of VALOR TOTAL | O3: Rótulos de Linha | P3: Sum of VALOR TOTAL
I4: 1046907.8 | L4: PASTAGEM | M4: 142323 | O4: JULHO | P4: 132051.39
A5: VALOR TOTAL DE DESPESAS | L5: SANIDADE | M5: 11348.9 | O5: AGOSTO | P5: 40697.85
A6: =I4 -> 1046907.8 | L6: FUNCIONARIO | M6: 172593.34 | O6: SETEMBRO | P6: 114842.69
L7: (vazio) | M7: 411132.64 | O7: OUTUBRO | P7: 262893.94
L8: PARQUE DE MÁQUINAS | M8: 109794.93 | O8: NOVEMBRO | P8: 123000.22
L9: COMISSÃO | M9: 2866.5 | O9: DEZEMBRO | P9: 98020.74
L10: IMPOSTO E TAXAS | M10: 6330.77 | O10: JANEIRO | P10: 96004.04
L11: OUTROS | M11: 5262 | O11: FEVEREIRO | P11: 97382.76
L12: INFRAESTRUTURA | M12: 27740.19 | O12: MARÇO | P12: 82014.13
L13: DESPESA GADO | M13: 20776.5 | O13: Total Geral | P13: 1046907.8
L14: NUTRIÇÃO | M14: 136099.99
L15: FERPAM | M15: 639
L16: Total Geral | M16: 1046907.8

Sheet DASH CAIXA
A1: CAIXA | B1: ='PAINEL ENTRADA'!T1 -> SÃO FRANCISCO | G1: =TODAY() -> 46294 | I1: PARCERIA | J1: (Vários itens) | L1: SAFRA | M1: 2025/2026 | P1: PARCERIA | Q1: (Vários itens)
I3: Sum of VALOR TOTAL DA COMPRA | L3: Sum of VALOR TOTAL | P3: Sum of VALOR TOTAL
L4: 1046907.8
A5: RECEITAS VENDAS DE BOVINOS | D5: DESPESAS E CUSTEIO
A6: =P4 -> 0 | D6: =L4 -> 1046907.8
A9: COMPRAS A PRAZO BOVINOS | D9: COMPRAS A VISTA BOVINOS
A10: =I11 -> 0 | D10: =I4 -> 0
I11: =SUM(I12:I30) -> 0
I12: 0
A13: VALOR CALCULADO EM CAIXA | I13: 0
A14: =A6-D6-A10-D10 -> -1046907.8 | I14: 0
I15: 0
I16: 0
I17: 0
I18: 0
I19: 0
I20: 0
I21: 0
I22: 0
I23: 0
I24: 0
I25: 0
I26: 0
... I31: 0

Sheet ADF E COMPRAS
A1: QUANTIDADE DE ANIMAIS JÁ OBTIDOS | J1: VALOR TOTAL ADF | N1: ANIMAIS CONCLUÍDAS / PENDENTES
A4: QUANTIDADE | B4: PESO BRUTO | C4: MÉDIA @ | D4: VALOR TOTAL PAGO | F4: MÉDIA R$ CAB | G4: TOTAL @ PAGA | H4: CUSTO @ FINAL | J4: PAGO | L4: =SUMIF(L13:L1048576,L13,K13:K1048576) -> 0 | N4: CONCLUIDA | P4: =SUMIF(P13:P1048576,N4,O13:O1048576) -> 0
A5: =SUM(B13:B1048576) -> 0 | B5: =SUM(C13:C1048576) -> 0 | C5: =SUM(B5/A5/2/15) -> #DIV/0! | D5: =SUM(F13:F1048576) -> 0 | F5: =IFERROR(SUM(D5/A5),0) -> 0 | G5: =SUM(B5/2/15) -> 0 | H5: =IFERROR(SUM(D5/G5),0) -> 0 | J5: PENDENTE | L5: =SUMIF(L13:L1048576,J5,K13:K1048576) -> 0 | N5: PENDENTE | P5: =SUMIF(P13:P1048576,N5,O13:O1048576) -> 0
A10: ANIMAIS JÁ OBTIDO | J10: ADF JÁ PAGO | N10: VIAGENS CONCLUÍDAS / PENDENTES
A12: DATA | B12: QUANTIDADE | C12: PESO BRUTO | D12: MÉD. @ | E12: M/F | F12: VALOR PAGO | G12: MÉDIA R$ CAB | H12: CUSTO @ | I12: @ | J12: DATA | K12: VALOR | L12: STATUS | N12: DATA | O12: QUANTIDADE | P12: STATUS
D13: =IFERROR(SUM(C13/B13)/2/15,0) -> 0 | G13: =IFERROR(SUM(F13/B13),0) -> 0 | H13: =IFERROR(SUM(F13/I13),0) -> 0 | I13: =SUM(C13/2/15) -> 0 | L13: PAGO | P13: CONCLUIDA
D14: =IFERROR(SUM(C14/B14)/2/15,0) -> 0 | G14: =IFERROR(SUM(F14/B14),0) -> 0 | H14: =IFERROR(SUM(F14/I14),0) -> 0 | I14: =SUM(C14/2/15) -> 0 | L14: PAGO | P14: PENDENTE
D15: =IFERROR(SUM(C15/B15)/2/15,0) -> 0 | G15: =IFERROR(SUM(F15/B15),0) -> 0 | H15: =IFERROR(SUM(F15/I15),0) -> 0 | I15: =SUM(C15/2/15) -> 0 | L15: PAGO | P15: PENDENTE
D16: =IFERROR(SUM(C16/B16)/2/15,0) -> 0 | G16: =IFERROR(SUM(F16/B16),0) -> 0 | H16: =IFERROR(SUM(F16/I16),0) -> 0 | I16: =SUM(C16/2/15) -> 0 | L16: PAGO | P16: PENDENTE
D17: =IFERROR(SUM(C17/B17)/2/15,0) -> 0 | G17: =IFERROR(SUM(F17/B17),0) -> 0 | H17: =IFERROR(SUM(F17/I17),0) -> 0 | I17: =SUM(C17/2/15) -> 0 | L17: PENDENTE
D18: =IFERROR(SUM(C18/B18)/2/15,0) -> 0 | G18: =IFERROR(SUM(F18/B18),0) -> 0 | H18: =IFERROR(SUM(F18/I18),0) -> 0 | I18: =SUM(C18/2/15) -> 0 | L18: PENDENTE
D19: =IFERROR(SUM(C19/B19)/2/15,0) -> 0 | G19: =IFERROR(SUM(F19/B19),0) -> 0 | H19: =IFERROR(SUM(F19/I19),0) -> 0 | I19: =SUM(C19/2/15) -> 0 | L19: PENDENTE
D20: =IFERROR(SUM(C20/B20)/2/15,0) -> 0 | G20: =IFERROR(SUM(F20/B20),0) -> 0 | H20: =IFERROR(SUM(F20/I20),0) -> 0 | I20: =SUM(C20/2/15) -> 0
D21: =IFERROR(SUM(C21/B21)/2/15,0) -> 0 | G21: =IFERROR(SUM(F21/B21),0) -> 0 | H21: =IFERROR(SUM(F21/I21),0) -> 0 | I21: =SUM(C21/2/15) -> 0
D22: =IFERROR(SUM(C22/B22)/2/15,0) -> 0 | G22: =IFERROR(SUM(F22/B22),0) -> 0 | H22: =IFERROR(SUM(F22/I22),0) -> 0 | I22: =SUM(C22/2/15) -> 0
D23: =IFERROR(SUM(C23/B23)/2/15,0) -> 0 | G23: =IFERROR(SUM(F23/B23),0) -> 0 | H23: =IFERROR(SUM(F23/I23),0) -> 0 | I23: =SUM(C23/2/15) -> 0
D24: =IFERROR(SUM(C24/B24)/2/15,0) -> 0 | G24: =IFERROR(SUM(F24/B24),0) -> 0 | H24: =IFERROR(SUM(F24/I24),0) -> 0 | I24: =SUM(C24/2/15) -> 0
D25: =IFERROR(SUM(C25/B25)/2/15,0) -> 0 | G25: =IFERROR(SUM(F25/B25),0) -> 0 | H25: =IFERROR(SUM(F25/I25),0) -> 0 | I25: =SUM(C25/2/15) -> 0
D26: =IFERROR(SUM(C26/B26)/2/15,0) -> 0 | G26: =IFERROR(SUM(F26/B26),0) -> 0 | H26: =IFERROR(SUM(F26/I26),0) -> 0 | I26: =SUM(C26/2/15) -> 0
D27: =IFERROR(SUM(C27/B27)/2/15,0) -> 0 | G27: =IFERROR(SUM(F27/B27),0) -> 0 | H27: =IFERROR(SUM(F27/I27),0) -> 0 | I27: =SUM(C27/2/15) -> 0
D28: =IFERROR(SUM(C28/B28)/2/15,0) -> 0 | G28: =IFERROR(SUM(F28/B28),0) -> 0 | H28: =IFERROR(SUM(F28/I28),0) -> 0 | I28: =SUM(C28/2/15) -> 0
D29: =IFERROR(SUM(C29/B29)/2/15,0) -> 0 | G29: =IFERROR(SUM(F29/B29),0) -> 0 | H29: =IFERROR(SUM(F29/I29),0) -> 0 | I29: =SUM(C29/2/15) -> 0
D30: =IFERROR(SUM(C30/B30)/2/15,0) -> 0 | G30: =IFERROR(SUM(F30/B30),0) -> 0 | H30: =IFERROR(SUM(F30/I30),0) -> 0 | I30: =SUM(C30/2/15) -> 0
D31: =IFERROR(SUM(C31/B31)/2/15,0) -> 0 | G31: =IFERROR(SUM(F31/B31),0) -> 0 | H31: =IFERROR(SUM(F31/I31),0) -> 0 | I31: =SUM(C31/2/15) -> 0
... D166: =IFERROR(SUM(C166/B166)/2/15,0) -> 0 | G166: =IFERROR(SUM(F166/B166),0) -> 0 | H166: =IFERROR(SUM(F166/I166),0) -> 0 | I166: =SUM(C166/2/15) -> 0

Sheet PESAGENS E CONFERENCIA
B2: DATA | C2: BRINCO | D2: PESO | E2: MOVIMENTAÇÃO | G2: DATA | H2: BRINCO | I2: PESO | J2: MOVIMENTAÇÃO | L2: DATA | M2: BRINCO | N2: PESO | O2: MOVIMENTAÇÃO | Q2: DATA | R2: BRINCO | S2: PESO | T2: MOVIMENTAÇÃO | V2: DATA | W2: BRINCO | X2: PESO | Y2: MOVIMENTAÇÃO | AA2: DATA | AB2: BRINCO | AC2: PESO | AD2: MOVIMENTAÇÃO | AF2: DATA | AG2: BRINCO | AH2: PESO | AI2: MOVIMENTAÇÃO | AK2: DATA | AL2: BRINCO | AM2: PESO | AN2: MOVIMENTAÇÃO | AP2: DATA | AQ2: BRINCO | AR2: PESO | AS2: MOVIMENTAÇÃO
B3: 46168 | C3: 948 | D3: 567 | E3: CONFERENCIA | G3: 45872 | H3: 324 | I3: 528 | J3: ABATE | L3: 45953 | M3: 1632 | N3: 162 | O3: COMPRA | Q3: 46006 | R3: 2024 | S3: 219 | T3: VACINA COFERENCIA | V3: 46007 | W3: 1996 | X3: 523 | Y3: VACINA COFERENCIA | AA3: 46135 | AB3: 359 | AC3: 493 | AD3: ABATE | AF3: 45912 | AH3: 115 | AI3: COMPRA GOIANO | AK3: 45989 | AM3: 145 | AN3: COMPRA | AP3: 46139 | AR3: 158
B4: 46168 | C4: 559 | D4: 564 | E4: CONFERENCIA | G4: 45872 | H4: 7471 | I4: 546 | J4: ABATE | L4: 45953 | M4: 1633 | N4: 181 | O4: COMPRA | Q4: 46006 | R4: 1986 | S4: 545 | T4: VACINA COFERENCIA | V4: 46007 | W4: 1995 | X4: 557 | Y4: VACINA COFERENCIA | AA4: 46135 | AB4: 1199 | AC4: 518 | AD4: ABATE | AF4: 45912 | AH4: 175 | AI4: COMPRA GOIANO | AK4: 45989 | AM4: 159 | AN4: COMPRA | AP4: 46139 | AR4: 124
B5: 46168 | C5: 1236 | D5: 554 | E5: CONFERENCIA | G5: 45872 | H5: 926 | I5: 481 | J5: ABATE | L5: 45953 | M5: 1634 | N5: 149 | O5: COMPRA | Q5: 46006 | R5: 1983 | S5: 557 | T5: VACINA COFERENCIA | V5: 46007 | W5: 1994 | X5: 145 | Y5: VACINA COFERENCIA | AA5: 46135 | AB5: 1179 | AC5: 619 | AD5: ABATE | AF5: 45912 | AH5: 159 | AI5: COMPRA GOIANO | AK5: 45989 | AM5: 129 | AN5: COMPRA | AP5: 46139 | AR5: 134
B6: 46168 | C6: 845 | D6: 553 | E6: CONFERENCIA | G6: 45872 | H6: 333 | I6: 508 | J6: ABATE | L6: 45953 | M6: 1635 | N6: 197 | O6: COMPRA | Q6: 46006 | R6: 1697 | S6: 247 | T6: VACINA COFERENCIA | V6: 46007 | W6: 1990 | X6: 497 | Y6: VACINA COFERENCIA | AA6: 46135 | AB6: 304 | AC6: 540 | AD6: ABATE | AF6: 45912 | AH6: 193 | AI6: COMPRA GOIANO | AK6: 45989 | AM6: 133 | AN6: COMPRA | AP6: 46139 | AR6: 110
B7: 46168 | C7: 410 | D7: 551 | E7: CONFERENCIA | G7: 45872 | H7: 337 | I7: 520 | J7: ABATE | L7: 45953 | M7: 1636 | N7: 168 | O7: COMPRA | Q7: 46006 | R7: 1695 | S7: 236 | T7: VACINA COFERENCIA | V7: 46007 | W7: 1988 | X7: 587 | Y7: VACINA COFERENCIA | AA7: 46135 | AB7: 892 | AC7: 632 | AD7: ABATE | AF7: 45912 | AH7: 144 | AI7: COMPRA GOIANO | AK7: 45989 | AM7: 147 | AN7: COMPRA | AP7: 46139 | AR7: 156
B8: 46168 | C8: 503 | D8: 547 | E8: CONFERENCIA | G8: 45872 | H8: 1027 | I8: 483 | J8: ABATE | L8: 45953 | M8: 1637 | N8: 162 | O8: COMPRA | Q8: 46006 | R8: 1694 | S8: 195 | T8: VACINA COFERENCIA | V8: 46007 | W8: 1985 | X8: 454 | Y8: VACINA COFERENCIA | AA8: 46135 | AB8: 904 | AC8: 488 | AD8: ABATE | AF8: 45912 | AH8: 119 | AI8: COMPRA GOIANO | AK8: 45989 | AM8: 140 | AN8: COMPRA | AP8: 46139 | AR8: 136
B9: 46168 | C9: 876 | D9: 541 | E9: CONFERENCIA | G9: 45872 | H9: 934 | I9: 510 | J9: ABATE | L9: 45953 | M9: 1638 | N9: 122 | O9: COMPRA | Q9: 46006 | R9: 1693 | S9: 324 | T9: VACINA COFERENCIA | V9: 46007 | W9: 1984 | X9: 463 | Y9: VACINA COFERENCIA | AA9: 46135 | AB9: 693 | AC9: 576 | AD9: ABATE | AF9: 45912 | AH9: 186 | AI9: COMPRA GOIANO | AK9: 45989 | AM9: 163 | AN9: COMPRA | AP9: 46139 | AR9: 154
B10: 46168 | C10: 15 | D10: 541 | E10: CONFERENCIA | G10: 45872 | H10: 480 | I10: 511 | J10: ABATE | L10: 45953 | M10: 1639 | N10: 122 | O10: COMPRA | Q10: 46006 | R10: 1692 | S10: 233 | T10: VACINA COFERENCIA | V10: 46007 | W10: 1982 | X10: 178 | Y10: VACINA COFERENCIA | AA10: 46135 | AB10: 481 | AC10: 652 | AD10: ABATE | AF10: 45912 | AH10: 171 | AI10: COMPRA GOIANO | AK10: 45989 | AM10: 150 | AN10: COMPRA | AP10: 46139 | AR10: 140
B11: 46168 | C11: 1173 | D11: 540 | E11: CONFERENCIA | G11: 45872 | H11: 465 | I11: 527 | J11: ABATE | L11: 45953 | M11: 1640 | N11: 126 | O11: COMPRA | Q11: 46006 | R11: 1691 | S11: 189 | T11: VACINA COFERENCIA | V11: 46007 | W11: 1981 | X11: 92 | Y11: VACINA COFERENCIA | AA11: 46135 | AB11: 1103 | AC11: 555 | AD11: ABATE | AF11: 45912 | AH11: 152 | AI11: COMPRA GOIANO | AK11: 45989 | AM11: 158 | AN11: COMPRA | AP11: 46139 | AR11: 136
B12: 46168 | C12: 941 | D12: 540 | E12: CONFERENCIA | G12: 45872 | H12: 949 | I12: 505 | J12: ABATE | L12: 45953 | M12: 1641 | N12: 133 | O12: COMPRA | Q12: 46006 | R12: 1690 | S12: 281 | T12: VACINA COFERENCIA | V12: 46007 | W12: 1980 | X12: 100 | Y12: VACINA COFERENCIA | AA12: 46135 | AB12: 664 | AC12: 620 | AD12: ABATE | AF12: 45912 | AH12: 193 | AI12: COMPRA GOIANO | AK12: 45989 | AM12: 147 | AN12: COMPRA | AP12: 46139 | AR12: 129
B13: 46168 | C13: 926 | D13: 540 | E13: CONFERENCIA | G13: 45872 | H13: 866 | I13: 499 | J13: ABATE | L13: 45953 | M13: 1642 | N13: 175 | O13: COMPRA | Q13: 46006 | R13: 1688 | S13: 217 | T13: VACINA COFERENCIA | V13: 46007 | W13: 1979 | X13: 134 | Y13: VACINA COFERENCIA | AA13: 46135 | AB13: 674 | AC13: 571 | AD13: ABATE | AF13: 45912 | AH13: 180 | AI13: COMPRA GOIANO | AK13: 45989 | AM13: 181 | AN13: COMPRA | AP13: 46139 | AR13: 139
B14: 46168 | C14: 866 | D14: 540 | E14: CONFERENCIA | G14: 45872 | H14: 470 | I14: 527 | J14: ABATE | L14: 45953 | M14: 1643 | N14: 124 | O14: COMPRA | Q14: 46006 | R14: 1687 | S14: 197 | T14: VACINA COFERENCIA | V14: 46007 | W14: 1978 | X14: 114 | Y14: VACINA COFERENCIA | AA14: 46135 | AB14: 492 | AC14: 652 | AD14: ABATE | AF14: 45912 | AH14: 218 | AI14: COMPRA GOIANO | AK14: 45989 | AM14: 143 | AN14: COMPRA | AP14: 46139 | AR14: 152
... B44: 46168 | C44: 465 | D44: 518 | E44: CONFERENCIA | G44: 45872 | H44: 515 | I44: 552 | J44: ABATE | L44: 45953 | M44: 1722 | N44: 177 | O44: COMPRA | Q44: 46006 | R44: 1545 | S44: 235 | T44: VACINA COFERENCIA | V44: 46007 | W44: 1948 | X44: 106 | Y44: VACINA COFERENCIA | AA44: 46135 | AB44: 573 | AC44: 581 | AD44: ABATE | AF44: 45912 | AH44: 266 | AI44: COMPRA GOIANO | AK44: 45989 | AM44: 161 | AN44: COMPRA | AP44: 46139 | AR44: 156
B45: 46168 | C45: 454 | D45: 518 | E45: CONFERENCIA | G45: 45872 | H45: 387 | I45: 501 | J45: ABATE | Q45: 46006 | R45: 1543 | S45: 193 | T45: VACINA COFERENCIA | V45: 46007 | W45: 1947 | X45: 115 | Y45: VACINA COFERENCIA | AA45: 46135 | AB45: 875 | AC45: 625 | AD45: ABATE | AF45: 45912 | AH45: 272 | AI45: COMPRA GOIANO | AK45: 45989 | AM45: 167 | AN45: COMPRA | AP45: 46139 | AR45: 136
B46: 46168 | C46: 1209 | D46: 517 | E46: CONFERENCIA | G46: 45872 | H46: 441 | I46: 524 | J46: ABATE | Q46: 46006 | R46: 1541 | S46: 267 | T46: VACINA COFERENCIA | V46: 46007 | W46: 1946 | X46: 95 | Y46: VACINA COFERENCIA | AA46: 46135 | AB46: 1101 | AC46: 575 | AD46: ABATE | AF46: 45912 | AH46: 344 | AI46: COMPRA GOIANO | AK46: 45989 | AM46: 116 | AN46: COMPRA | AP46: 46139 | AR46: 147
B47: 46168 | C47: 1040 | D47: 517 | E47: CONFERENCIA | G47: 45872 | H47: 4320 | I47: 538 | J47: ABATE | Q47: 46006 | R47: 1540 | S47: 288 | T47: VACINA COFERENCIA | V47: 46007 | W47: 1945 | X47: 120 | Y47: VACINA COFERENCIA | AA47: 46135 | AB47: 791 | AC47: 650 | AD47: ABATE | AF47: 45912 | AH47: 188 | AI47: COMPRA GOIANO | AK47: 45989 | AM47: 135 | AN47: COMPRA | AP47: 46139 | AR47: 101
B48: 46168 | C48: 1030 | D48: 517 | E48: CONFERENCIA | G48: 45872 | H48: 360 | I48: 516 | J48: ABATE | Q48: 46006 | R48: 1534 | S48: 199 | T48: VACINA COFERENCIA | V48: 46007 | W48: 1944 | X48: 99 | Y48: VACINA COFERENCIA | AA48: 46135 | AB48: 381 | AC48: 643 | AD48: ABATE | AF48: 45912 | AH48: 152 | AI48: COMPRA GOIANO | AK48: 45989 | AM48: 149 | AN48: COMPRA | AP48: 46139 | AR48: 150
B49: 46168 | C49: 555 | D49: 517 | E49: CONFERENCIA | G49: 45872 | H49: 567 | I49: 541 | J49: ABATE | Q49: 46006 | R49: 1490 | S49: 470 | T49: VACINA COFERENCIA | V49: 46007 | W49: 1943 | X49: 90 | Y49: VACINA COFERENCIA | AA49: 46135 | AB49: 599 | AC49: 570 | AD49: ABATE | AF49: 45912 | AH49: 289 | AI49: COMPRA GOIANO | AK49: 45989 | AM49: 122 | AN49: COMPRA | AP49: 46139 | AR49: 128
B50: 46168 | C50: 370 | D50: 517 | E50: CONFERENCIA | G50: 45872 | H50: 3399 | I50: 561 | J50: ABATE | Q50: 46006 | R50: 1305 | S50: 235 | T50: VACINA COFERENCIA | V50: 46007 | W50: 1942 | X50: 96 | Y50: VACINA COFERENCIA | AA50: 46135 | AB50: 616 | AC50: 659 | AD50: ABATE | AF50: 45912 | AH50: 270 | AI50: COMPRA GOIANO | AK50: 45989 | AM50: 142 | AN50: COMPRA | AP50: 46139 | AR50: 110
B51: 46168 | C51: 841 | D51: 515 | E51: CONFERENCIA | G51: 45872 | H51: 582 | I51: 536 | J51: ABATE | Q51: 46006 | R51: 1301 | S51: 187 | T51: VACINA COFERENCIA | V51: 46007 | W51: 1941 | X51: 113 | Y51: VACINA COFERENCIA | AA51: 46135 | AB51: 1037 | AC51: 618 | AD51: ABATE | AF51: 45912 | AH51: 247 | AI51: COMPRA GOIANO | AK51: 45989 | AM51: 139 | AN51: COMPRA | AP51: 46139 | AR51: 160
B52: 46168 | C52: 819 | D52: 515 | E52: CONFERENCIA | G52: 45872 | H52: 3026 | I52: 552 | J52: ABATE | Q52: 46006 | R52: 1277 | S52: 215 | T52: VACINA COFERENCIA | V52: 46007 | W52: 1940 | X52: 104 | Y52: VACINA COFERENCIA | AA52: 46135 | AB52: 803 | AC52: 572 | AD52: ABATE | AF52: 45912 | AH52: 136 | AI52: COMPRA GOIANO | AK52: 45989 | AM52: 125 | AN52: COMPRA | AP52: 46139 | AR52: 151
B53: 46168 | C53: 459 | D53: 515 | E53: CONFERENCIA | G53: 45872 | H53: 971 | I53: 506 | J53: ABATE | Q53: 46006 | R53: 1275 | S53: 232 | T53: VACINA COFERENCIA | V53: 46007 | W53: 1939 | X53: 104 | Y53: VACINA COFERENCIA | AA53: 46135 | AB53: 961 | AC53: 564 | AD53: ABATE | AF53: 45912 | AH53: 191 | AI53: COMPRA GOIANO | AK53: 45989 | AM53: 158 | AN53: COMPRA | AP53: 46139 | AR53: 137
B54: 46168 | C54: 1176 | D54: 513 | E54: CONFERENCIA | G54: 45872 | H54: 921 | I54: 470 | J54: ABATE | Q54: 46006 | R54: 1262 | S54: 235 | T54: VACINA COFERENCIA | V54: 46007 | W54: 1938 | X54: 136 | Y54: VACINA COFERENCIA | AA54: 46135 | AB54: 414 | AC54: 575 | AD54: ABATE | AF54: 45912 | AH54: 318 | AI54: COMPRA GOIANO | AK54: 45989 | AM54: 154 | AN54: COMPRA | AP54: 46139 | AR54: 123
B55: 46168 | C55: 859 | D55: 513 | E55: CONFERENCIA | G55: 45872 | H55: 411 | I55: 512 | J55: ABATE | Q55: 46006 | R55: 1261 | S55: 205 | T55: VACINA COFERENCIA | V55: 46007 | W55: 1937 | X55: 117 | Y55: VACINA COFERENCIA | AA55: 46135 | AB55: 335 | AC55: 585 | AD55: ABATE | AF55: 45912 | AH55: 263 | AI55: COMPRA GOIANO | AK55: 45989 | AM55: 145 | AN55: COMPRA | AP55: 46139 | AR55: 142
B56: 46168 | C56: 706 | D56: 513 | E56: CONFERENCIA | G56: 45872 | H56: 75 | I56: 522 | J56: ABATE | Q56: 46006 | R56: 1260 | S56: 230 | T56: VACINA COFERENCIA | V56: 46007 | W56: 1936 | X56: 129 | Y56: VACINA COFERENCIA | AA56: 46135 | AB56: 509 | AC56: 615 | AD56: ABATE | AF56: 45912 | AH56: 374 | AI56: COMPRA GOIANO | AK56: 45989 | AM56: 147 | AN56: COMPRA | AP56: 46139 | AR56: 137
... B64: 46168 | C64: 1210 | D64: 512 | E64: CONFERENCIA | G64: 45872 | H64: 1218 | I64: 493 | J64: ABATE | Q64: 46006 | R64: 1252 | S64: 230 | T64: VACINA COFERENCIA | V64: 46007 | W64: 1928 | X64: 140 | Y64: VACINA COFERENCIA | AA64: 46135 | AB64: 726 | AC64: 565 | AD64: ABATE | AF64: 45912 | AH64: 205 | AI64: COMPRA GOIANO | AK64: 45989 | AM64: 138 | AN64: COMPRA | AP64: 46139 | AR64: 159
B65: 46168 | C65: 1180 | D65: 512 | E65: CONFERENCIA | G65: 45872 | H65: 418 | I65: 540 | J65: ABATE | Q65: 46006 | R65: 1250 | S65: 202 | T65: VACINA COFERENCIA | V65: 46007 | W65: 1927 | X65: 112 | Y65: VACINA COFERENCIA | AA65: 46135 | AB65: SB | AC65: 591 | AD65: ABATE | AF65: 45912 | AH65: 223 | AI65: COMPRA GOIANO | AK65: 45989 | AM65: 174 | AN65: COMPRA | AP65: 46139 | AR65: 150
B66: 46168 | C66: 1021 | D66: 512 | E66: CONFERENCIA | G66: 45872 | H66: 1223 | I66: 510 | J66: ABATE | Q66: 46006 | R66: 1249 | S66: 280 | T66: VACINA COFERENCIA | V66: 46007 | W66: 1926 | X66: 87 | Y66: VACINA COFERENCIA | AA66: 46135 | AB66: 1143 | AC66: 636 | AD66: ABATE | AF66: 45912 | AH66: 139 | AI66: COMPRA GOIANO | AK66: 45989 | AM66: 155 | AN66: COMPRA | AP66: 46139 | AR66: 119
B67: 46168 | C67: 964 | D67: 512 | E67: CONFERENCIA | G67: 45872 | H67: 3270 | I67: 519 | J67: ABATE | Q67: 46006 | R67: 1247 | S67: 224 | T67: VACINA COFERENCIA | V67: 46007 | W67: 1925 | X67: 100 | Y67: VACINA COFERENCIA | AA67: 46135 | AB67: 361 | AC67: 578 | AD67: ABATE | AF67: 45912 | AH67: 177 | AI67: COMPRA GOIANO | AK67: 45989 | AM67: 144 | AN67: COMPRA | AP67: 46139 | AR67: 228
B68: 46168 | C68: 949 | D68: 512 | E68: CONFERENCIA | G68: 45872 | H68: 4475 | I68: 586 | J68: ABATE | Q68: 46006 | R68: 1246 | S68: 244 | T68: VACINA COFERENCIA | V68: 46007 | W68: 1924 | X68: 100 | Y68: VACINA COFERENCIA | AA68: 46135 | AB68: 863 | AC68: 504 | AD68: ABATE | AF68: 45912 | AH68: 216 | AI68: COMPRA GOIANO | AK68: 45989 | AM68: 136 | AN68: COMPRA | AP68: 46139 | AR68: 143
B69: 46168 | C69: 877 | D69: 512 | E69: CONFERENCIA | G69: 45872 | H69: 555 | I69: 551 | J69: ABATE | Q69: 46006 | R69: 1243 | S69: 181 | T69: VACINA COFERENCIA | V69: 46007 | W69: 1923 | X69: 124 | Y69: VACINA COFERENCIA | AA69: 46135 | AB69: 332 | AC69: 600 | AD69: ABATE | AF69: 45912 | AH69: 229 | AI69: COMPRA GOIANO | AK69: 45989 | AM69: 139 | AN69: COMPRA | AP69: 46139 | AR69: 134
B70: 46168 | C70: 337 | D70: 512 | E70: CONFERENCIA | G70: 45872 | H70: 1230 | I70: 512 | J70: ABATE | Q70: 46006 | R70: 1237 | S70: 429 | T70: VACINA COFERENCIA | V70: 46007 | W70: 1922 | X70: 94 | Y70: VACINA COFERENCIA | AA70: 46135 | AB70: SB | AC70: 633 | AD70: ABATE | AF70: 45912 | AH70: 244 | AI70: COMPRA GOIANO | AK70: 45989 | AM70: 157 | AN70: COMPRA | AP70: 46139 | AR70: 149
B71: 46168 | C71: 976 | D71: 511 | E71: CONFERENCIA | G71: 45872 | H71: 413 | I71: 513 | J71: ABATE | Q71: 46006 | R71: 1201 | S71: 427 | T71: VACINA COFERENCIA | V71: 46007 | W71: 1921 | X71: 124 | Y71: VACINA COFERENCIA | AA71: 46135 | AB71: 649 | AC71: 555 | AD71: ABATE | AF71: 45912 | AH71: 143 | AI71: COMPRA GOIANO | AK71: 45989 | AM71: 141 | AN71: COMPRA | AP71: 46139 | AR71: 157
B72: 46168 | C72: 407 | D72: 511 | E72: CONFERENCIA | G72: 45872 | H72: 1193 | I72: 508 | J72: ABATE | Q72: 46006 | R72: 1166 | S72: 461 | T72: VACINA COFERENCIA | V72: 46007 | W72: 1920 | X72: 152 | Y72: VACINA COFERENCIA | AA72: 46135 | AB72: 1010 | AC72: 579 | AD72: ABATE | AF72: 45912 | AH72: 260 | AI72: COMPRA GOIANO | AK72: 45989 | AM72: 153 | AN72: COMPRA | AP72: 46139 | AR72: 134
B73: 46168 | C73: 480 | D73: 510 | E73: CONFERENCIA | G73: 45872 | H73: 422 | I73: 508 | J73: ABATE | Q73: 46006 | R73: 1149 | S73: 449 | T73: VACINA COFERENCIA | V73: 46007 | W73: 1919 | X73: 119 | Y73: VACINA COFERENCIA | AA73: 46135 | AB73: 1236 | AC73: 683 | AD73: ABATE | AF73: 45912 | AH73: 216 | AI73: COMPRA GOIANO | AK73: 45989 | AM73: 138 | AN73: COMPRA | AP73: 46139 | AR73: 161
B74: 46168 | C74: 1230 | D74: 509 | E74: CONFERENCIA | G74: 45872 | H74: 378 | I74: 538 | J74: ABATE | Q74: 46006 | R74: 1146 | S74: 488 | T74: VACINA COFERENCIA | V74: 46007 | W74: 1918 | X74: 127 | Y74: VACINA COFERENCIA | AA74: 46135 | AB74: 918 | AC74: 553 | AD74: ABATE | AF74: 45912 | AH74: 241 | AI74: COMPRA GOIANO | AK74: 45989 | AM74: 159 | AN74: COMPRA | AP74: 46139 | AR74: 134
B75: 46168 | C75: 461 | D75: 509 | E75: CONFERENCIA | G75: 45872 | H75: 325 | I75: 535 | J75: ABATE | Q75: 46006 | R75: 1145 | S75: 455 | T75: VACINA COFERENCIA | V75: 46007 | W75: 1917 | X75: 107 | Y75: VACINA COFERENCIA | AA75: 46135 | AB75: 1012 | AC75: 574 | AD75: ABATE | AF75: 45912 | AH75: 184 | AI75: COMPRA GOIANO | AK75: 45989 | AM75: 123 | AN75: COMPRA | AP75: 46139 | AR75: 127
B76: 46168 | C76: 438 | D76: 509 | E76: CONFERENCIA | G76: 45872 | H76: 1183 | I76: 504 | J76: ABATE | Q76: 46006 | R76: 1085 | S76: 309 | T76: VACINA COFERENCIA | V76: 46007 | W76: 1916 | X76: 124 | Y76: VACINA COFERENCIA | AA76: 46135 | AB76: 871 | AC76: 581 | AD76: ABATE | AF76: 45912 | AH76: 216 | AI76: COMPRA GOIANO | AK76: 45989 | AM76: 137 | AN76: COMPRA | AP76: 46139 | AR76: 108
B77: 46168 | C77: 411 | D77: 509 | E77: CONFERENCIA | G77: 45872 | H77: 826 | I77: 520 | J77: ABATE | Q77: 46006 | R77: 1074 | S77: 447 | T77: VACINA COFERENCIA | V77: 46007 | W77: 1915 | X77: 103 | Y77: VACINA COFERENCIA | AA77: 46135 | AB77: 1135 | AC77: 581 | AD77: ABATE | AF77: 45912 | AH77: 220 | AI77: COMPRA GOIANO | AK77: 45989 | AM77: 152 | AN77: COMPRA | AP77: 46139 | AR77: 128
B78: 46168 | C78: 333 | D78: 509 | E78: CONFERENCIA | G78: 45872 | H78: 1270 | I78: 492 | J78: ABATE | Q78: 46006 | R78: 1058 | S78: 411 | T78: VACINA COFERENCIA | V78: 46007 | W78: 1914 | X78: 135 | Y78: VACINA COFERENCIA | AA78: 46135 | AB78: 487 | AC78: 588 | AD78: ABATE | AF78: 45912 | AH78: 186 | AI78: COMPRA GOIANO | AK78: 45989 | AM78: 134 | AN78: COMPRA | AP78: 46139 | AR78: 148
B79: 46168 | C79: 387 | D79: 508 | E79: CONFERENCIA | G79: 45872 | H79: 559 | I79: 571 | J79: ABATE | Q79: 46006 | R79: 1052 | S79: 440 | T79: VACINA COFERENCIA | V79: 46007 | W79: 1913 | X79: 125 | Y79: VACINA COFERENCIA | AA79: 46135 | AB79: 908 | AC79: 623 | AD79: ABATE | AF79: 45912 | AH79: 182 | AI79: COMPRA GOIANO | AK79: 45989 | AM79: 162 | AN79: COMPRA | AP79: 46139 | AR79: 174
B80: 46168 | C80: 373 | D80: 508 | E80: CONFERENCIA | G80: 45872 | H80: 1176 | I80: 510 | J80: ABATE | Q80: 46006 | R80: 1045 | S80: 439 | T80: VACINA COFERENCIA | V80: 46007 | W80: 1912 | X80: 135 | Y80: VACINA COFERENCIA | AA80: 46135 | AB80: 504 | AC80: 568 | AD80: ABATE | AF80: 45912 | AH80: 189 | AI80: COMPRA GOIANO | AK80: 45989 | AM80: 113 | AN80: COMPRA | AP80: 46139 | AR80: 127
B81: 46168 | C81: 1193 | D81: 507 | E81: CONFERENCIA | G81: 45872 | H81: 554 | I81: 531 | J81: ABATE | Q81: 46006 | R81: 1036 | S81: 411 | T81: VACINA COFERENCIA | V81: 46007 | W81: 1911 | X81: 129 | Y81: VACINA COFERENCIA | AA81: 46135 | AB81: 502 | AC81: 559 | AD81: ABATE | AF81: 45912 | AH81: 255 | AI81: COMPRA GOIANO | AK81: 45989 | AM81: 133 | AN81: COMPRA | AP81: 46139 | AR81: 119
B82: 46168 | C82: 540 | D82: 507 | E82: CONFERENCIA | G82: 45872 | H82: 832 | I82: 511 | J82: ABATE | Q82: 46006 | R82: 1029 | S82: 434 | T82: VACINA COFERENCIA | V82: 46007 | W82: 1910 | X82: 154 | Y82: VACINA COFERENCIA | AA82: 46135 | AB82: 1186 | AC82: 588 | AD82: ABATE | AF82: 45912 | AH82: 135 | AI82: COMPRA GOIANO | AK82: 45989 | AM82: 127 | AN82: COMPRA | AP82: 46139 | AR82: 107
B83: 46168 | C83: 441 | D83: 507 | E83: CONFERENCIA | G83: 45872 | H83: 1030 | I83: 489 | J83: ABATE | Q83: 46006 | R83: 1022 | S83: 406 | T83: VACINA COFERENCIA | V83: 46007 | W83: 1909 | X83: 128 | Y83: VACINA COFERENCIA | AA83: 46135 | AB83: 437 | AC83: 563 | AD83: ABATE | AF83: 45912 | AH83: 144 | AI83: COMPRA GOIANO | AK83: 45989 | AM83: 139 | AN83: COMPRA | AP83: 46139 | AR83: 100
B84: 46168 | C84: 357 | D84: 507 | E84: CONFERENCIA | G84: 45872 | H84: 3409 | I84: 569 | J84: ABATE | Q84: 46006 | R84: 1019 | S84: 478 | T84: VACINA COFERENCIA | V84: 46007 | W84: 1908 | X84: 165 | Y84: VACINA COFERENCIA | AF84: 45912 | AH84: 154 | AI84: COMPRA GOIANO | AK84: 45989 | AM84: 157 | AN84: COMPRA | AP84: 46139 | AR84: 122
B85: 46168 | C85: 483 | D85: 506 | E85: CONFERENCIA | G85: 45872 | H85: 358 | I85: 503 | J85: ABATE | Q85: 46006 | R85: 1017 | S85: 453 | T85: VACINA COFERENCIA | V85: 46007 | W85: 1907 | X85: 121 | Y85: VACINA COFERENCIA | AF85: 45912 | AH85: 106 | AI85: COMPRA GOIANO | AK85: 45989 | AM85: 140 | AN85: COMPRA | AP85: 46139 | AR85: 136
B86: 46168 | C86: 1212 | D86: 505 | E86: CONFERENCIA | G86: 45872 | H86: 438 | I86: 524 | J86: ABATE | Q86: 46006 | R86: 1013 | S86: 451 | T86: VACINA COFERENCIA | V86: 46007 | W86: 1906 | X86: 152 | Y86: VACINA COFERENCIA | AF86: 45912 | AH86: 238 | AI86: COMPRA GOIANO | AK86: 45989 | AM86: 168 | AN86: COMPRA | AP86: 46139 | AR86: 134
B87: 46168 | C87: 358 | D87: 504 | E87: CONFERENCIA | Q87: 46006 | R87: 1001 | S87: 385 | T87: VACINA COFERENCIA | V87: 46007 | W87: 1905 | X87: 194 | Y87: VACINA COFERENCIA | AF87: 45912 | AH87: 184 | AI87: COMPRA GOIANO | AK87: 45989 | AM87: 158 | AN87: COMPRA | AP87: 46139 | AR87: 154
B88: 46168 | C88: 1172 | D88: 503 | E88: CONFERENCIA | Q88: 46006 | R88: 986 | S88: 410 | T88: VACINA COFERENCIA | V88: 46007 | W88: 1904 | X88: 134 | Y88: VACINA COFERENCIA | AF88: 45912 | AH88: 262 | AI88: COMPRA GOIANO | AK88: 45989 | AM88: 132 | AN88: COMPRA | AP88: 46139 | AR88: 114
B89: 46168 | C89: 1020 | D89: 503 | E89: CONFERENCIA | Q89: 46006 | R89: 957 | S89: 414 | T89: VACINA COFERENCIA | V89: 46007 | W89: 1903 | X89: 161 | Y89: VACINA COFERENCIA | AF89: 45912 | AH89: 151 | AI89: COMPRA GOIANO | AK89: 45989 | AM89: 127 | AN89: COMPRA | AP89: 46139 | AR89: 115
B90: 46168 | C90: 737 | D90: 503 | E90: CONFERENCIA | Q90: 46006 | R90: 956 | S90: 411 | T90: VACINA COFERENCIA | V90: 46007 | W90: 1902 | X90: 163 | Y90: VACINA COFERENCIA | AF90: 45912 | AH90: 197 | AI90: COMPRA GOIANO | AK90: 45989 | AM90: 138 | AN90: COMPRA | AP90: 46139 | AR90: 123
B91: 46168 | C91: 935 | D91: 502 | E91: CONFERENCIA | Q91: 46006 | R91: 922 | S91: 450 | T91: VACINA COFERENCIA | V91: 46007 | W91: 1901 | X91: 156 | Y91: VACINA COFERENCIA | AF91: 45912 | AH91: 317 | AI91: COMPRA GOIANO | AK91: 45989 | AM91: 161 | AN91: COMPRA | AP91: 46139 | AR91: 117
B92: 46168 | C92: 867 | D92: 502 | E92: CONFERENCIA | Q92: 46006 | R92: 910 | S92: 510 | T92: VACINA COFERENCIA | V92: 46007 | W92: 1900 | X92: 128 | Y92: VACINA COFERENCIA | AF92: 45912 | AH92: 298 | AI92: COMPRA GOIANO | AK92: 45989 | AM92: 114 | AN92: COMPRA | AP92: 46139 | AR92: 151
B93: 46168 | C93: 365 | D93: 502 | E93: CONFERENCIA | Q93: 46006 | R93: 894 | S93: 534 | T93: VACINA COFERENCIA | V93: 46007 | W93: 1899 | X93: 151 | Y93: VACINA COFERENCIA | AF93: 45912 | AH93: 171 | AI93: COMPRA GOIANO | AK93: 45989 | AM93: 168 | AN93: COMPRA | AP93: 46139 | AR93: 144
B94: 46168 | C94: 614 | D94: 501 | E94: CONFERENCIA | Q94: 46006 | R94: 888 | S94: 452 | T94: VACINA COFERENCIA | V94: 46007 | W94: 1898 | X94: 157 | Y94: VACINA COFERENCIA | AF94: 45912 | AH94: 258 | AI94: COMPRA GOIANO | AK94: 45989 | AM94: 138 | AN94: COMPRA | AP94: 46139 | AR94: 120
B95: 46168 | C95: 499 | D95: 501 | E95: CONFERENCIA | Q95: 46006 | R95: 887 | S95: 447 | T95: VACINA COFERENCIA | V95: 46007 | W95: 1897 | X95: 146 | Y95: VACINA COFERENCIA | AF95: 45912 | AH95: 265 | AI95: COMPRA GOIANO | AK95: 45989 | AM95: 120 | AN95: COMPRA | AP95: 46139 | AR95: 169
B96: 46168 | C96: 1219 | D96: 500 | E96: CONFERENCIA | Q96: 46006 | R96: 874 | S96: 416 | T96: VACINA COFERENCIA | V96: 46007 | W96: 1896 | X96: 170 | Y96: VACINA COFERENCIA | AF96: 45912 | AH96: 301 | AI96: COMPRA GOIANO | AK96: 45989 | AM96: 140 | AN96: COMPRA | AP96: 46139 | AR96: 133
B97: 46168 | C97: 1190 | D97: 500 | E97: CONFERENCIA | Q97: 46006 | R97: 861 | S97: 442 | T97: VACINA COFERENCIA | V97: 46007 | W97: 1895 | X97: 150 | Y97: VACINA COFERENCIA | AF97: 45912 | AH97: 237 | AI97: COMPRA GOIANO | AK97: 45989 | AM97: 130 | AN97: COMPRA | AP97: 46139 | AR97: 120
B98: 46168 | C98: 1056 | D98: 500 | E98: CONFERENCIA | Q98: 46006 | R98: 840 | S98: 477 | T98: VACINA COFERENCIA | V98: 46007 | W98: 1893 | X98: 184 | Y98: VACINA COFERENCIA | AF98: 45912 | AH98: 188 | AI98: COMPRA GOIANO | AK98: 45989 | AM98: 159 | AN98: COMPRA | AP98: 46139 | AR98: 148
... B103: 46168 | C103: 334 | D103: 500 | E103: CONFERENCIA | Q103: 46006 | R103: 736 | S103: 327 | T103: VACINA COFERENCIA | V103: 46007 | W103: 1888 | X103: 144 | Y103: VACINA COFERENCIA | AF103: 45912 | AH103: 225 | AI103: COMPRA GOIANO | AK103: 45989 | AM103: 167 | AN103: COMPRA | AP103: 46139 | AR103: 132
B104: 46168 | C104: SB | D104: 500 | E104: CONFERENCIA | Q104: 46006 | R104: 734 | S104: 372 | T104: VACINA COFERENCIA | V104: 46007 | W104: 1887 | X104: 131 | Y104: VACINA COFERENCIA | AF104: 45912 | AH104: 203 | AI104: COMPRA GOIANO | AK104: 45989 | AM104: 203 | AN104: COMPRA | AP104: 46139 | AR104: 157
B105: 46168 | C105: SB | D105: 500 | E105: CONFERENCIA | Q105: 46006 | R105: 699 | S105: 433 | T105: VACINA COFERENCIA | V105: 46007 | W105: 1886 | X105: 127 | Y105: VACINA COFERENCIA | AF105: 45912 | AH105: 256 | AI105: COMPRA GOIANO | AK105: 45989 | AM105: 149 | AN105: COMPRA | AP105: 46139 | AR105: 115
B106: 46168 | C106: SB | D106: 500 | E106: CONFERENCIA | Q106: 46006 | R106: 692 | S106: 456 | T106: VACINA COFERENCIA | V106: 46007 | W106: 1885 | X106: 130 | Y106: VACINA COFERENCIA | AF106: 45912 | AH106: 221 | AI106: COMPRA GOIANO | AK106: 45989 | AM106: 160 | AN106: COMPRA | AP106: 46139 | AR106: 101
B107: 46168 | C107: SB | D107: 500 | E107: CONFERENCIA | Q107: 46006 | R107: 690 | S107: 446 | T107: VACINA COFERENCIA | V107: 46007 | W107: 1884 | X107: 149 | Y107: VACINA COFERENCIA | AF107: 45912 | AH107: 179 | AI107: COMPRA GOIANO | AK107: 45989 | AM107: 155 | AN107: COMPRA | AP107: 46139 | AR107: 159
B108: 46168 | C108: SB | D108: 500 | E108: CONFERENCIA | Q108: 46006 | R108: 676 | S108: 501 | T108: VACINA COFERENCIA | V108: 46007 | W108: 1883 | X108: 145 | Y108: VACINA COFERENCIA | AF108: 45912 | AH108: 160 | AI108: COMPRA GOIANO | AK108: 45989 | AM108: 156 | AN108: COMPRA | AP108: 46139 | AR108: 122
B109: 46168 | C109: SB | D109: 500 | E109: CONFERENCIA | Q109: 46006 | R109: 655 | S109: 349 | T109: VACINA COFERENCIA | V109: 46007 | W109: 1882 | X109: 116 | Y109: VACINA COFERENCIA | AF109: 45912 | AH109: 193 | AI109: COMPRA GOIANO | AK109: 45989 | AM109: 136 | AN109: COMPRA | AP109: 46139 | AR109: 142
B110: 46168 | C110: SB | D110: 500 | E110: CONFERENCIA | Q110: 46006 | R110: 645 | S110: 452 | T110: VACINA COFERENCIA | V110: 46007 | W110: 1881 | X110: 165 | Y110: VACINA COFERENCIA | AF110: 45912 | AH110: 218 | AI110: COMPRA GOIANO | AK110: 45989 | AM110: 157 | AN110: COMPRA | AP110: 46139 | AR110: 148
B111: 46168 | C111: SB | D111: 500 | E111: CONFERENCIA | Q111: 46006 | R111: 630 | S111: 454 | T111: VACINA COFERENCIA | V111: 46007 | W111: 1880 | X111: 169 | Y111: VACINA COFERENCIA | AF111: 45912 | AH111: 286 | AI111: COMPRA GOIANO | AK111: 45989 | AM111: 140 | AN111: COMPRA | AP111: 46139 | AR111: 108
B112: 46168 | C112: SB | D112: 500 | E112: CONFERENCIA | Q112: 46006 | R112: 625 | S112: 451 | T112: VACINA COFERENCIA | V112: 46007 | W112: 1879 | X112: 154 | Y112: VACINA COFERENCIA | AF112: 45912 | AH112: 272 | AI112: COMPRA GOIANO | AK112: 45989 | AM112: 156 | AN112: COMPRA | AP112: 46139 | AR112: 115
B113: 46168 | C113: SB | D113: 500 | E113: CONFERENCIA | Q113: 46006 | R113: 617 | S113: 528 | T113: VACINA COFERENCIA | V113: 46007 | W113: 1878 | X113: 181 | Y113: VACINA COFERENCIA | AF113: 45912 | AH113: 249 | AI113: COMPRA GOIANO | AK113: 45989 | AM113: 120 | AN113: COMPRA | AP113: 46139 | AR113: 93
B114: 46168 | C114: SB | D114: 500 | E114: CONFERENCIA | Q114: 46006 | R114: 614 | S114: 532 | T114: VACINA COFERENCIA | V114: 46007 | W114: 1877 | X114: 144 | Y114: VACINA COFERENCIA | AF114: 45912 | AH114: 248 | AI114: COMPRA GOIANO | AK114: 45989 | AM114: 131 | AN114: COMPRA | AP114: 46139 | AR114: 189
B115: 46168 | C115: SB | D115: 500 | E115: CONFERENCIA | Q115: 46006 | R115: 603 | S115: 503 | T115: VACINA COFERENCIA | V115: 46007 | W115: 1876 | X115: 130 | Y115: VACINA COFERENCIA | AF115: 45912 | AH115: 178 | AI115: COMPRA GOIANO | AK115: 45989 | AM115: 125 | AN115: COMPRA | AP115: 46139 | AR115: 151
... B119: 46168 | C119: SB | D119: 500 | E119: CONFERENCIA | Q119: 46006 | R119: 546 | S119: 523 | T119: VACINA COFERENCIA | V119: 46007 | W119: 1872 | X119: 156 | Y119: VACINA COFERENCIA | AF119: 45912 | AH119: 193 | AI119: COMPRA GOIANO | AK119: 45989 | AM119: 130 | AN119: COMPRA | AP119: 46139 | AR119: 151
B120: 46168 | C120: 1215 | D120: 499 | E120: CONFERENCIA | Q120: 46006 | R120: 543 | S120: 540 | T120: VACINA COFERENCIA | V120: 46007 | W120: 1871 | X120: 160 | Y120: VACINA COFERENCIA | AF120: 45912 | AH120: 137 | AI120: COMPRA GOIANO | AK120: 45989 | AM120: 132 | AN120: COMPRA | AP120: 46139 | AR120: 138
B121: 46168 | C121: 619 | D121: 499 | E121: CONFERENCIA | Q121: 46006 | R121: 539 | S121: 390 | T121: VACINA COFERENCIA | V121: 46007 | W121: 1870 | X121: 124 | Y121: VACINA COFERENCIA | AF121: 45912 | AH121: 157 | AI121: COMPRA GOIANO | AK121: 45989 | AM121: 168 | AN121: COMPRA | AP121: 46139 | AR121: 124
B122: 46168 | C122: 314 | D122: 499 | E122: CONFERENCIA | Q122: 46006 | R122: 536 | S122: 478 | T122: VACINA COFERENCIA | V122: 46007 | W122: 1869 | X122: 131 | Y122: VACINA COFERENCIA | AF122: 45912 | AH122: 136 | AI122: COMPRA GOIANO | AK122: 45989 | AM122: 153 | AN122: COMPRA | AP122: 46139 | AR122: 138
B123: 46168 | C123: 980 | D123: 498 | E123: CONFERENCIA | Q123: 46006 | R123: 533 | S123: 440 | T123: VACINA COFERENCIA | V123: 46007 | W123: 1868 | X123: 146 | Y123: VACINA COFERENCIA | AF123: 45912 | AH123: 192 | AI123: COMPRA GOIANO | AK123: 45989 | AM123: 146 | AN123: COMPRA | AP123: 46139 | AR123: 140
B124: 46168 | C124: 623 | D124: 498 | E124: CONFERENCIA | Q124: 46006 | R124: 531 | S124: 511 | T124: VACINA COFERENCIA | V124: 46007 | W124: 1867 | X124: 124 | Y124: VACINA COFERENCIA | AF124: 45912 | AH124: 203 | AI124: COMPRA GOIANO | AK124: 45989 | AM124: 115 | AN124: COMPRA | AP124: 46139 | AR124: 164
B125: 46168 | C125: 622 | D125: 498 | E125: CONFERENCIA | Q125: 46006 | R125: 522 | S125: 490 | T125: VACINA COFERENCIA | V125: 46007 | W125: 1866 | X125: 150 | Y125: VACINA COFERENCIA | AF125: 45912 | AH125: 260 | AI125: COMPRA GOIANO | AK125: 45989 | AM125: 131 | AN125: COMPRA | AP125: 46139 | AR125: 122
B126: 46168 | C126: 1228 | D126: 497 | E126: CONFERENCIA | Q126: 46006 | R126: 518 | S126: 497 | T126: VACINA COFERENCIA | V126: 46007 | W126: 1865 | X126: 131 | Y126: VACINA COFERENCIA | AF126: 45912 | AH126: 202 | AI126: COMPRA GOIANO | AK126: 45989 | AM126: 126 | AN126: COMPRA | AP126: 46139 | AR126: 129
B127: 46168 | C127: 1216 | D127: 497 | E127: CONFERENCIA | Q127: 46006 | R127: 514 | S127: 517 | T127: VACINA COFERENCIA | V127: 46007 | W127: 1864 | X127: 111 | Y127: VACINA COFERENCIA | AF127: 45912 | AH127: 250 | AI127: COMPRA GOIANO | AK127: 45989 | AM127: 162 | AN127: COMPRA | AP127: 46139 | AR127: 124
B128: 46168 | C128: 1181 | D128: 497 | E128: CONFERENCIA | Q128: 46006 | R128: 510 | S128: 459 | T128: VACINA COFERENCIA | V128: 46007 | W128: 1863 | X128: 162 | Y128: VACINA COFERENCIA | AF128: 45912 | AH128: 187 | AI128: COMPRA GOIANO | AK128: 45989 | AM128: 172 | AN128: COMPRA | AP128: 46139 | AR128: 132
B129: 46168 | C129: 985 | D129: 497 | E129: CONFERENCIA | Q129: 46006 | R129: 496 | S129: 475 | T129: VACINA COFERENCIA | V129: 46007 | W129: 1862 | X129: 159 | Y129: VACINA COFERENCIA | AF129: 45912 | AH129: 191 | AI129: COMPRA GOIANO | AK129: 45989 | AM129: 160 | AN129: COMPRA | AP129: 46139 | AR129: 139
B130: 46168 | C130: 945 | D130: 497 | E130: CONFERENCIA | Q130: 46006 | R130: 485 | S130: 456 | T130: VACINA COFERENCIA | V130: 46007 | W130: 1861 | X130: 145 | Y130: VACINA COFERENCIA | AF130: 45912 | AH130: 208 | AI130: COMPRA GOIANO | AK130: 45989 | AM130: 143 | AN130: COMPRA | AP130: 46139 | AR130: 119
B131: 46168 | C131: 490 | D131: 497 | E131: CONFERENCIA | Q131: 46006 | R131: 472 | S131: 541 | T131: VACINA COFERENCIA | V131: 46007 | W131: 1860 | X131: 118 | Y131: VACINA COFERENCIA | AF131: 45912 | AH131: 167 | AI131: COMPRA GOIANO | AK131: 45989 | AM131: 142 | AN131: COMPRA | AP131: 46139 | AR131: 138
... B135: 46168 | C135: 1194 | D135: 495 | E135: CONFERENCIA | Q135: 46006 | R135: 404 | S135: 481 | T135: VACINA COFERENCIA | V135: 46007 | W135: 1856 | X135: 160 | Y135: VACINA COFERENCIA | AF135: 45912 | AH135: 201 | AI135: COMPRA GOIANO | AK135: 45989 | AM135: 185 | AN135: COMPRA | AP135: 46139 | AR135: 134
B136: 46168 | C136: 1041 | D136: 495 | E136: CONFERENCIA | Q136: 46006 | R136: 402 | S136: 487 | T136: VACINA COFERENCIA | V136: 46007 | W136: 1855 | X136: 130 | Y136: VACINA COFERENCIA | AK136: 45989 | AM136: 164 | AN136: COMPRA | AP136: 46139 | AR136: 143
B137: 46168 | C137: 606 | D137: 495 | E137: CONFERENCIA | Q137: 46006 | R137: 390 | S137: 494 | T137: VACINA COFERENCIA | V137: 46007 | W137: 1854 | X137: 133 | Y137: VACINA COFERENCIA | AK137: 45989 | AM137: 143 | AN137: COMPRA | AP137: 46139 | AR137: 144
B138: 46168 | C138: 544 | D138: 495 | E138: CONFERENCIA | Q138: 46006 | R138: 388 | S138: 463 | T138: VACINA COFERENCIA | V138: 46007 | W138: 1853 | X138: 192 | Y138: VACINA COFERENCIA | AK138: 45989 | AM138: 121 | AN138: COMPRA | AP138: 46139 | AR138: 137
B139: 46168 | C139: 425 | D139: 495 | E139: CONFERENCIA | Q139: 46006 | R139: 384 | S139: 450 | T139: VACINA COFERENCIA | V139: 46007 | W139: 1852 | X139: 150 | Y139: VACINA COFERENCIA | AK139: 45989 | AM139: 144 | AN139: COMPRA | AP139: 46139 | AR139: 150
B140: 46168 | C140: 332 | D140: 495 | E140: CONFERENCIA | Q140: 46006 | R140: 382 | S140: 472 | T140: VACINA COFERENCIA | V140: 46007 | W140: 1851 | X140: 162 | Y140: VACINA COFERENCIA | AK140: 45989 | AM140: 141 | AN140: COMPRA | AP140: 46139 | AR140: 108
B141: 46168 | C141: 1224 | D141: 493 | E141: CONFERENCIA | Q141: 46006 | R141: 363 | S141: 476 | T141: VACINA COFERENCIA | V141: 46007 | W141: 1850 | X141: 149 | Y141: VACINA COFERENCIA | AK141: 45989 | AM141: 152 | AN141: COMPRA | AP141: 46139 | AR141: 122
B142: 46168 | C142: 1177 | D142: 493 | E142: CONFERENCIA | Q142: 46006 | R142: 359 | S142: 488 | T142: VACINA COFERENCIA | V142: 46007 | W142: 1849 | X142: 137 | Y142: VACINA COFERENCIA | AK142: 45989 | AM142: 184 | AN142: COMPRA | AP142: 46139 | AR142: 120
B143: 46168 | C143: 1108 | D143: 493 | E143: CONFERENCIA | Q143: 46006 | R143: 353 | S143: 373 | T143: VACINA COFERENCIA | V143: 46007 | W143: 1848 | X143: 157 | Y143: VACINA COFERENCIA | AK143: 45989 | AM143: 166 | AN143: COMPRA | AP143: 46139 | AR143: 156
B144: 46168 | C144: 1049 | D144: 493 | E144: CONFERENCIA | Q144: 46006 | R144: 334 | S144: 481 | T144: VACINA COFERENCIA | V144: 46007 | W144: 1847 | X144: 178 | Y144: VACINA COFERENCIA | AK144: 45989 | AM144: 161 | AN144: COMPRA | AP144: 46139 | AR144: 151
B145: 46168 | C145: 693 | D145: 493 | E145: CONFERENCIA | Q145: 46006 | R145: 330 | S145: 383 | T145: VACINA COFERENCIA | V145: 46007 | W145: 1846 | X145: 134 | Y145: VACINA COFERENCIA | AK145: 45989 | AM145: 169 | AN145: COMPRA | AP145: 46139 | AR145: 141
B146: 46168 | C146: 422 | D146: 493 | E146: CONFERENCIA | Q146: 46006 | R146: 326 | S146: 500 | T146: VACINA COFERENCIA | V146: 46007 | W146: 1845 | X146: 173 | Y146: VACINA COFERENCIA | AK146: 45989 | AM146: 173 | AN146: COMPRA | AP146: 46139 | AR146: 130
B147: 46168 | C147: 750 | D147: 491 | E147: CONFERENCIA | Q147: 46006 | R147: 323 | S147: 460 | T147: VACINA COFERENCIA | V147: 46007 | W147: 1844 | X147: 142 | Y147: VACINA COFERENCIA | AK147: 45989 | AM147: 122 | AN147: COMPRA | AP147: 46139 | AR147: 138
...

Sheet Planilha9
B2: 45499 | C2: 48 | F2: 1 | G2: BURRO
C3: 54 | F3: 2 | G3: CAVALO
C4: 54 | I4: 59
C5: 54 | I5: 110
C6: 50 | I6: 55
C7: 51 | I7: 137
C8: 52 | I8: 52
C9: 50 | I9: 1
C10: 50 | I10: 67
C11: 52 | I11: 49
C12: 52 | I12: 80
C13: 52 | I13: 110
C14: 54
C15: 54
C16: 50
C17: 52
C18: 50
C19: 52
C20: 52
C21: 17
C22: 11 | D22: VACA
